Workbook
Name NativeTimeline_Date: #N/A
Name Slicer_Region: #N/A

Sheet DataSet
A1: Transaction_ID | B1: Date | C1: Customer_ID | D1: Customer_Name | E1: Product_ID | F1: Product_Name | G1: Category | H1: Quantity | I1: Unit_Price | J1: Payment_Method | K1: Region | L1: Customer_Segment | M1: Customer_Since | N1: Total_Amount
A2: TRX0155 | B2: 45393 | C2: CUST023 | D2: Paul Baker | E2: P009 | F2: Monitor | G2: Electronics | H2: 3 | I2: 249.99 | J2: Cash | K2: Central | L2: Basic | M2: 44425 | N2: 749.97
A3: TRX0023 | B3: 45396 | C3: CUST013 | D3: Joseph Jackson | E3: P009 | F3: Monitor | G3: Electronics | H3: 3 | I3: 249.99 | J3: Credit Card | K3: Central | L3: Premium | M3: 44575 | N3: 749.97
A4: TRX0139 | B4: 45399 | C4: CUST021 | D4: Kevin Scott | E4: P005 | F4: Blender | G4: Appliances | H4: 3 | I4: 59.99 | J4: PayPal | K4: South | L4: Standard | M4: 45262 | N4: 179.97
A5: TRX0043 | B5: 45400 | C5: CUST046 | D5: Kathleen Bennett | E5: P005 | F5: Blender | G5: Appliances | H5: 3 | I5: 59.99 | J5: Cash | K5: North | L5: Premium | M5: 45114 | N5: 179.97
A6: TRX0212 | B6: 45400 | C6: CUST003 | D6: Michael Brown | E6: P008 | F6: Bookshelf | G6: Furniture | H6: 5 | I6: 149.99 | J6: Credit Card | K6: North | L6: Premium | M6: 45295 | N6: 749.95
A7: TRX0092 | B7: 45403 | C7: CUST024 | D7: Dorothy Nelson | E7: P005 | F7: Blender | G7: Appliances | H7: 2 | I7: 59.99 | J7: Cash | K7: West | L7: Standard | M7: 44746 | N7: 119.98
A8: TRX0193 | B8: 45403 | C8: CUST024 | D8: Dorothy Nelson | E8: P003 | F8: Headphones | G8: Electronics | H8: 5 | I8: 149.99 | J8: Credit Card | K8: Central | L8: Standard | M8: 44418 | N8: 749.95
A9: TRX0240 | B9: 45403 | C9: CUST017 | D9: Charles Allen | E9: P005 | F9: Blender | G9: Appliances | H9: 3 | I9: 59.99 | J9: Debit Card | K9: South | L9: Basic | M9: 45007 | N9: 179.97
A10: TRX0135 | B10: 45405 | C10: CUST009 | D10: Robert Thomas | E10: P001 | F10: Laptop | G10: Electronics | H10: 3 | I10: 899.99 | J10: PayPal | K10: East | L10: Standard | M10: 45299 | N10: 2699.97
A11: TRX0185 | B11: 45408 | C11: CUST026 | D11: Karen Hill | E11: P005 | F11: Blender | G11: Appliances | H11: 3 | I11: 59.99 | J11: Cash | K11: West | L11: Premium | M11: 45207 | N11: 179.97
A12: TRX0138 | B12: 45408 | C12: CUST022 | D12: Susan Green | E12: P008 | F12: Bookshelf | G12: Furniture | H12: 1 | I12: 149.99 | J12: Credit Card | K12: West | L12: Standard | M12: 45103 | N12: 149.99
A13: TRX0209 | B13: 45408 | C13: CUST046 | D13: Kathleen Bennett | E13: P008 | F13: Bookshelf | G13: Furniture | H13: 5 | I13: 149.99 | J13: Debit Card | K13: North | L13: Basic | M13: 44830 | N13: 749.95
... A251: TRX0064 | B251: 45758 | C251: CUST031 | D251: Steven Turner | E251: P010 | F251: Keyboard | G251: Electronics | H251: 3 | I251: 89.99 | J251: Debit Card | K251: North | L251: Premium | M251: 44878 | N251: 269.97

Sheet Scenario Summary
B2: Scenario Summary
D3: Current Values: | E3: Low Sales | F3: Normal Sales | G3: High Sales
E4: Created by Sneha on 19-09-2026 | F4: Created by Sneha on 19-09-2026 | G4: Created by Sneha on 19-09-2026
B5: Changing Cells:
C6: $B$408 | D6: 10 | E6: 5 | F6: 10 | G6: 20
C7: $B$409 | D7: 100 | E7: 80 | F7: 100 | G7: 150
B8: Result Cells:
C9: $B$410 | D9: 1000 | E9: 400 | F9: 1000 | G9: 3000
B10: Notes: Current Values column represents values of changing cells at
B11: time Scenario Summary Report was created. Changing cells for each
B12: scenario are highlighted in gray.

Sheet Main Task
A1: Task 1: Date & Time Functions.
A3: Function | B3: Result
A4: TODAY | B4: =TODAY() -> 46286
A5: NOW | B5: =NOW() -> 46286.527
A6: DATEDIFF | B6: =DATEDIF(DataSet!M2,DataSet!B2,"d") -> 968
A7: EOMONTH | B7: =EOMONTH(DataSet!B2,0) -> 45412
A9: Task 2: FILTER Function.
A11: Electronics Transactions
A12: {=_xlfn._xlws.FILTER(DataSet!A2:N251,DataSet!G2:G251="Electronics","No records found")} -> TRX0155 | B12: 45393 | C12: CUST023 | D12: Paul Baker | E12: P009 | F12: Monitor | G12: Electronics | H12: 3 | I12: 249.99 | J12: Cash | K12: Central | L12: Basic | M12: 44425 | N12: 749.97
A13: TRX0023 | B13: 45396 | C13: CUST013 | D13: Joseph Jackson | E13: P009 | F13: Monitor | G13: Electronics | H13: 3 | I13: 249.99 | J13: Credit Card | K13: Central | L13: Premium | M13: 44575 | N13: 749.97
A14: TRX0193 | B14: 45403 | C14: CUST024 | D14: Dorothy Nelson | E14: P003 | F14: Headphones | G14: Electronics | H14: 5 | I14: 149.99 | J14: Credit Card | K14: Central | L14: Standard | M14: 44418 | N14: 749.95
A15: TRX0135 | B15: 45405 | C15: CUST009 | D15: Robert Thomas | E15: P001 | F15: Laptop | G15: Electronics | H15: 3 | I15: 899.99 | J15: PayPal | K15: East | L15: Standard | M15: 45299 | N15: 2699.97
A16: TRX0191 | B16: 45409 | C16: CUST038 | D16: Michelle Rogers | E16: P002 | F16: Smartphone | G16: Electronics | H16: 3 | I16: 699.99 | J16: Credit Card | K16: West | L16: Basic | M16: 44577 | N16: 2099.97
A17: TRX0230 | B17: 45409 | C17: CUST027 | D17: George Adams | E17: P001 | F17: Laptop | G17: Electronics | H17: 1 | I17: 899.99 | J17: Debit Card | K17: North | L17: Standard | M17: 44920 | N17: 899.99
A18: TRX0134 | B18: 45410 | C18: CUST010 | D18: Maria Garcia | E18: P002 | F18: Smartphone | G18: Electronics | H18: 2 | I18: 699.99 | J18: Cash | K18: North | L18: Basic | M18: 44781 | N18: 1399.98
A19: TRX0122 | B19: 45410 | C19: CUST025 | D19: Mark Carter | E19: P001 | F19: Laptop | G19: Electronics | H19: 4 | I19: 899.99 | J19: Credit Card | K19: West | L19: Standard | M19: 45327 | N19: 3599.96
A20: TRX0222 | B20: 45410 | C20: CUST048 | D20: Virginia Sanders | E20: P009 | F20: Monitor | G20: Electronics | H20: 3 | I20: 249.99 | J20: Credit Card | K20: North | L20: Premium | M20: 45224 | N20: 749.97
A21: TRX0231 | B21: 45412 | C21: CUST018 | D21: Barbara Young | E21: P002 | F21: Smartphone | G21: Electronics | H21: 5 | I21: 699.99 | J21: Cash | K21: West | L21: Basic | M21: 45167 | N21: 3499.95
A22: TRX0239 | B22: 45413 | C22: CUST012 | D22: Patricia Moore | E22: P002 | F22: Smartphone | G22: Electronics | H22: 4 | I22: 699.99 | J22: Cash | K22: East | L22: Standard | M22: 44409 | N22: 2799.96
A23: TRX0204 | B23: 45415 | C23: CUST044 | D23: Cynthia Price | E23: P009 | F23: Monitor | G23: Electronics | H23: 4 | I23: 249.99 | J23: PayPal | K23: North | L23: Standard | M23: 44468 | N23: 999.96
A24: TRX0071 | B24: 45422 | C24: CUST036 | D24: Nancy Collins | E24: P009 | F24: Monitor | G24: Electronics | H24: 5 | I24: 249.99 | J24: Credit Card | K24: West | L24: Standard | M24: 44525 | N24: 1249.95
... A142: TRX0064 | B142: 45758 | C142: CUST031 | D142: Steven Turner | E142: P010 | F142: Keyboard | G142: Electronics | H142: 3 | I142: 89.99 | J142: Debit Card | K142: North | L142: Premium | M142: 44878 | N142: 269.97
A144: Task 3: Conditional Formatting with Icons/Arrows.
A146: Transaction_ID | B146: Customer_Name | C146: Product_Name | D146: Total_Amount
A147: =DataSet!A2 -> TRX0155 | B147: =DataSet!D2 -> Paul Baker | C147: =DataSet!F2 -> Monitor | D147: =DataSet!N2 -> 749.97
A148: =DataSet!A3 -> TRX0023 | B148: =DataSet!D3 -> Joseph Jackson | C148: =DataSet!F3 -> Monitor | D148: =DataSet!N3 -> 749.97
A149: =DataSet!A4 -> TRX0139 | B149: =DataSet!D4 -> Kevin Scott | C149: =DataSet!F4 -> Blender | D149: =DataSet!N4 -> 179.97
A150: =DataSet!A5 -> TRX0043 | B150: =DataSet!D5 -> Kathleen Bennett | C150: =DataSet!F5 -> Blender | D150: =DataSet!N5 -> 179.97
A151: =DataSet!A6 -> TRX0212 | B151: =DataSet!D6 -> Michael Brown | C151: =DataSet!F6 -> Bookshelf | D151: =DataSet!N6 -> 749.95
A152: =DataSet!A7 -> TRX0092 | B152: =DataSet!D7 -> Dorothy Nelson | C152: =DataSet!F7 -> Blender | D152: =DataSet!N7 -> 119.98
A153: =DataSet!A8 -> TRX0193 | B153: =DataSet!D8 -> Dorothy Nelson | C153: =DataSet!F8 -> Headphones | D153: =DataSet!N8 -> 749.95
A154: =DataSet!A9 -> TRX0240 | B154: =DataSet!D9 -> Charles Allen | C154: =DataSet!F9 -> Blender | D154: =DataSet!N9 -> 179.97
A155: =DataSet!A10 -> TRX0135 | B155: =DataSet!D10 -> Robert Thomas | C155: =DataSet!F10 -> Laptop | D155: =DataSet!N10 -> 2699.97
A156: =DataSet!A11 -> TRX0185 | B156: =DataSet!D11 -> Karen Hill | C156: =DataSet!F11 -> Blender | D156: =DataSet!N11 -> 179.97
A157: =DataSet!A12 -> TRX0138 | B157: =DataSet!D12 -> Susan Green | C157: =DataSet!F12 -> Bookshelf | D157: =DataSet!N12 -> 149.99
A158: =DataSet!A13 -> TRX0209 | B158: =DataSet!D13 -> Kathleen Bennett | C158: =DataSet!F13 -> Bookshelf | D158: =DataSet!N13 -> 749.95
... A396: =DataSet!A251 -> TRX0064 | B396: =DataSet!D251 -> Steven Turner | C396: =DataSet!F251 -> Keyboard | D396: =DataSet!N251 -> 269.97
A400: Task 4: Create Timestamp.
A402: Current Timestamp | B402: =NOW() -> 46286.527
A405: Task 5 & 6: WHAT-IF Analysis – Scenario Manager & Goal Seek
A407: Input | B407: Value
A408: Quantity | B408: 20
A409: Unit Price | B409: 100
A410: Total Sales | B410: =B408*B409 -> 2000
A412: Task 7: Linear Regression using Data Analysis ToolPak
A414: Regression Data | D414: SUMMARY OUTPUT
A416: Quantity | B416: Total Amount | D416: Regression Statistics
A417: =DataSet!H2 -> 3 | B417: =DataSet!N2 -> 749.97 | D417: Multiple R | E417: 0.45808036
A418: =DataSet!H3 -> 3 | B418: =DataSet!N3 -> 749.97 | D418: R Square | E418: 0.20983762
A419: =DataSet!H4 -> 3 | B419: =DataSet!N4 -> 179.97 | D419: Adjusted R Square | E419: 0.20665148
A420: =DataSet!H5 -> 3 | B420: =DataSet!N5 -> 179.97 | D420: Standard Error | E420: 919.60715
A421: =DataSet!H6 -> 5 | B421: =DataSet!N6 -> 749.95 | D421: Observations | E421: 250
A422: =DataSet!H7 -> 2 | B422: =DataSet!N7 -> 119.98
A423: =DataSet!H8 -> 5 | B423: =DataSet!N8 -> 749.95 | D423: ANOVA
A424: =DataSet!H9 -> 3 | B424: =DataSet!N9 -> 179.97 | E424: df | F424: SS | G424: MS | H424: F | I424: Significance F
A425: =DataSet!H10 -> 3 | B425: =DataSet!N10 -> 2699.97 | D425: Regression | E425: 1 | F425: 55695917 | G425: 55695917 | H425: 65.859537 | I425: 2.2586479e-14
A426: =DataSet!H11 -> 3 | B426: =DataSet!N11 -> 179.97 | D426: Residual | E426: 248 | F426: 2.0972797e+08 | G426: 845677.32
A427: =DataSet!H12 -> 1 | B427: =DataSet!N12 -> 149.99 | D427: Total | E427: 249 | F427: 2.6542389e+08
A428: =DataSet!H13 -> 5 | B428: =DataSet!N13 -> 749.95
A429: =DataSet!H14 -> 3 | B429: =DataSet!N14 -> 449.97 | E429: Coefficients | F429: Standard Error | G429: t Stat | H429: P-value | I429: Lower 95% | J429: Upper 95% | K429: Lower 95.0% | L429: Upper 95.0%
A430: =DataSet!H15 -> 3 | B430: =DataSet!N15 -> 179.97 | D430: Intercept | E430: -148.85465 | F430: 143.61334 | G430: -1.0364959 | H430: 0.3009804 | I430: -431.712 | J430: 134.0027 | K430: -431.712 | L430: 134.0027
A431: =DataSet!H16 -> 3 | B431: =DataSet!N16 -> 2099.97 | D431: Quantity | E431: 353.793 | F431: 43.595323 | G431: 8.1153889 | H431: 2.2586479e-14 | I431: 267.92872 | J431: 439.65729 | K431: 267.92872 | L431: 439.65729
A432: =DataSet!H17 -> 1 | B432: =DataSet!N17 -> 899.99
A433: =DataSet!H18 -> 4 | B433: =DataSet!N18 -> 599.96
A434: =DataSet!H19 -> 2 | B434: =DataSet!N19 -> 1399.98 | D434: Task 8: Data Analysis & Storytelling
A435: =DataSet!H20 -> 4 | B435: =DataSet!N20 -> 3599.96
A436: =DataSet!H21 -> 3 | B436: =DataSet!N21 -> 749.97
A437: =DataSet!H22 -> 5 | B437: =DataSet!N22 -> 3499.95 | D437: Key Insight | E437: Result
A438: =DataSet!H23 -> 4 | B438: =DataSet!N23 -> 2799.96 | D438: Total Revenue | E438: =SUM(DataSet!N2:N251) -> 229192.47
A439: =DataSet!H24 -> 4 | B439: =DataSet!N24 -> 999.96 | D439: Total Transactions | E439: =COUNTA(DataSet!A2:A251) -> 250
A440: =DataSet!H25 -> 4 | B440: =DataSet!N25 -> 1199.96 | D440: Total Quality Sold | E440: =+SUM(DataSet!H2:H251) -> 753
A441: =DataSet!H26 -> 5 | B441: =DataSet!N26 -> 1249.95 | D441: Average Transaction value | E441: =AVERAGE(DataSet!N2:N251) -> 916.76988
A442: =DataSet!H27 -> 5 | B442: =DataSet!N27 -> 1499.95 | D442: Average Quantity Per Transaction | E442: =AVERAGE(DataSet!H2:H251) -> 3.012
A443: =DataSet!H28 -> 3 | B443: =DataSet!N28 -> 239.97
A444: =DataSet!H29 -> 5 | B444: =DataSet!N29 -> 449.95
A445: =DataSet!H30 -> 2 | B445: =DataSet!N30 -> 119.98 | D445: Task 8.1: Top customer
A446: =DataSet!H31 -> 4 | B446: =DataSet!N31 -> 239.96
A447: =DataSet!H32 -> 5 | B447: =DataSet!N32 -> 999.95
A448: =DataSet!H33 -> 2 | B448: =DataSet!N33 -> 299.98 | D448: Top customer | E448: Result
A449: =DataSet!H34 -> 3 | B449: =DataSet!N34 -> 449.97 | D449: Customer | E449: {=_xlfn.LET(_xlpm.names,_xlfn.UNIQUE(DataSet!D2:D251),_xlpm.totals,SUMIF(DataSet!D2:D251,_xlpm.names,DataSet!N2:N251),INDEX(_xlpm.names,MATCH(MAX(_xlpm.totals),_xlpm.totals,0)))} -> Mark Carter
A450: =DataSet!H35 -> 1 | B450: =DataSet!N35 -> 899.99
A451: =DataSet!H36 -> 3 | B451: =DataSet!N36 -> 899.97
A452: =DataSet!H37 -> 3 | B452: =DataSet!N37 -> 239.97 | D452: Task 8.2: Most Sold Product
A453: =DataSet!H38 -> 3 | B453: =DataSet!N38 -> 599.97
A454: =DataSet!H39 -> 5 | B454: =DataSet!N39 -> 3499.95
A455: =DataSet!H40 -> 3 | B455: =DataSet!N40 -> 269.97 | D455: Most sold Product | E455: Result
A456: =DataSet!H41 -> 1 | B456: =DataSet!N41 -> 79.99 | D456: Product | E456: {=_xlfn.LET(_xlpm.products,_xlfn.UNIQUE(DataSet!F2:F251),_xlpm.qty,SUMIF(DataSet!F2:F251,_xlpm.products,DataSet!H2:H251),INDEX(_xlpm.products,MATCH(MAX(_xlpm.qty),_xlpm.qty,0)))} -> Bookshelf
A457: =DataSet!H42 -> 2 | B457: =DataSet!N42 -> 119.98
A458: =DataSet!H43 -> 1 | B458: =DataSet!N43 -> 89.99
A459: =DataSet!H44 -> 5 | B459: =DataSet!N44 -> 449.95 | D459: Task 8.3: Regional Sales
A460: =DataSet!H45 -> 5 | B460: =DataSet!N45 -> 1249.95
A461: =DataSet!H46 -> 1 | B461: =DataSet!N46 -> 89.99
A462: =DataSet!H47 -> 2 | B462: =DataSet!N47 -> 299.98 | D462: Region | E462: Total Sales
A463: =DataSet!H48 -> 4 | B463: =DataSet!N48 -> 239.96 | D463: North | E463: =SUMIF(DataSet!K$2:K$251,D463,DataSet!N$2:N$251) -> 50808.31
A464: =DataSet!H49 -> 5 | B464: =DataSet!N49 -> 449.95 | D464: South | E464: =SUMIF(DataSet!K$2:K$251,D464,DataSet!N$2:N$251) -> 36398.75
A465: =DataSet!H50 -> 2 | B465: =DataSet!N50 -> 179.98 | D465: East | E465: =SUMIF(DataSet!K$2:K$251,D465,DataSet!N$2:N$251) -> 59288.39
A466: =DataSet!H51 -> 5 | B466: =DataSet!N51 -> 4499.95 | D466: West | E466: =SUMIF(DataSet!K$2:K$251,D466,DataSet!N$2:N$251) -> 41408.68
A467: =DataSet!H52 -> 5 | B467: =DataSet!N52 -> 4499.95 | D467: Central | E467: =SUMIF(DataSet!K$2:K$251,D467,DataSet!N$2:N$251) -> 41288.34
A468: =DataSet!H53 -> 1 | B468: =DataSet!N53 -> 59.99
A469: =DataSet!H54 -> 2 | B469: =DataSet!N54 -> 599.98
...

Sheet Pivot tables
A1: Task 12.1: Total Revenue by Region
A3: Row Labels | B3: Sum of Total_Amount
A4: Central | B4: 41288.34
A5: East | B5: 59288.39
A6: North | B6: 50808.31
A7: South | B7: 36398.75
A8: West | B8: 41408.68
A9: Grand Total | B9: 229192.47
A12: Task 12.2: Total Revenue and Quantity by Category
A14: Row Labels | B14: Sum of Total_Amount | C14: Sum of Quantity
A15: Appliances | B15: 8338.74 | C15: 126
A16: Electronics | B16: 171756.05 | C16: 395
A17: Furniture | B17: 49097.68 | C17: 232
A18: Grand Total | B18: 229192.47 | C18: 753
A20: Task 12.3: Revenue by Customer Segment and Payment Method
A22: Sum of Total_Amount | B22: Column Labels
A23: Row Labels | B23: Cash | C23: Credit Card | D23: Debit Card | E23: PayPal | F23: Grand Total
A24: Basic | B24: 15199.44 | C24: 16009.36 | D24: 9839.57 | E24: 21129.44 | F24: 62177.81
A25: Premium | B25: 20949.03 | C25: 24309.23 | D25: 18429.46 | E25: 20969.4 | F25: 84657.12
A26: Standard | B26: 21279.32 | C26: 21129.37 | D26: 23849.28 | E26: 16099.57 | F26: 82357.54
A27: Grand Total | B27: 57427.79 | C27: 61447.96 | D27: 52118.31 | E27: 58198.41 | F27: 229192.47
A29: Task 12.4: Product Sales and Quantity Analysis
A31: Row Labels | B31: Sum of Quantity | C31: Sum of Total_Amount
A32: Blender | B32: 87 | C32: 5219.13
A33: Bookshelf | B33: 102 | C33: 15298.98
A34: Coffee Maker | B34: 39 | C34: 3119.61
A35: Desk | B35: 78 | C35: 23399.22
A36: Headphones | B36: 47 | C36: 7049.53
A37: Keyboard | B37: 89 | C37: 8009.11
A38: Laptop | B38: 75 | C38: 67499.25
A39: Monitor | B39: 88 | C39: 21999.12
A40: Office Chair | B40: 52 | C40: 10399.48
A41: Smartphone | B41: 96 | C41: 67199.04
A42: Grand Total | B42: 753 | C42: 229192.47

Sheet Dashboard
A1: Data Intelligence
A3: Total Revenue | D3: Total Transactions | G3: Total Quantity | J3: Average Transaction value
A4: =SUM(DataSet!N2:N251) -> 229192.47 | D4: =COUNTA(DataSet!A2:A251) -> 250 | G4: =SUM(DataSet!H2:H251) -> 753 | J4: =AVERAGE(DataSet!N2:N251) -> 916.76988
A26: Key Insights & storytelling
A28: Insight | B28: Result
A29: Total revenue | B29: =SUM(DataSet!N2:N251) -> 229192.47
A30: Total Transactions | B30: =COUNTA(DataSet!A2:A251) -> 250
A31: Total Quantity sold | B31: =SUM(DataSet!H2:H251) -> 753
A32: Average Transaction value | B32: =AVERAGE(DataSet!N2:N251) -> 916.76988
A33: Top Customer | B33: ='Main Task'!E449 -> Mark Carter
A34: Most Sold Product | B34: ='Main Task'!E456 -> Bookshelf
A37: Highest Revenue Region | B37: =INDEX('Main Task'!D463:D467,MATCH(MAX('Main Task'!E463:E467),'Main Task'!E463:E467,0)) -> East
A38: High-Value Customer Count | B38: =COUNTIF(_xlfn.ANCHORARRAY('Main Task'!F473),"High-Value") -> 24
A39: Most Frequently Purchased Product | B39: =INDEX('Main Task'!D528:D537,MATCH("Most Frequent",'Main Task'!F528:F537,0)) -> Bookshelf
A41: Business Summary
A43: The dashboard summarizes customer transactions using revenue, quantity, customer, product and regional analysis. It highlights key performance indicators,
A44: identifies the top customer and most frequently purchased products, and provides regional and category-level revenue insights for easier business analysis.
