Workbook
Name NativeTimeline_Order_Date: #N/A
Name Slicer_Product_Category: #N/A
Name Slicer_Region: #N/A

Sheet Pivot Tables
A1: Task 3: Create Pivot Tables – Analyze and summarize the dataset using Pivot Tables.
A3: Row Labels | B3: Sum of Sales
A4: Central | B4: 3678973.1
A5: East | B5: 3891741.7
A6: North | B6: 3866226.5
A7: South | B7: 3919562.1
A8: West | B8: 4097279.9
A9: (blank)
A10: Grand Total | B10: 19453783
A12: Pivot Table 2: Summarize Total sales and Total Profit by Product Category.
A14: Row Labels | B14: Sum of Sales | C14: Sum of Profit
A15: Books | B15: 4097279.9 | C15: 726304.07
A16: Clothing | B16: 3919562.1 | C16: 746508.07
A17: Electronics | B17: 3866226.5 | C17: 769795.44
A18: Furniture | B18: 3891741.7 | C18: 729963.8
A19: Office Supplies | B19: 3678973.1 | C19: 682854.52
A20: (blank)
A21: Grand Total | B21: 19453783 | C21: 3655425.9
A23: Pivot Table 3: Summarize Total Quantity Sold by Salesperson.
A25: Row Labels | B25: Sum of Quantity
A26: Amit | B26: 153
A27: Karan | B27: 163
A28: Meera | B28: 180
A29: Neha | B29: 173
A30: Pooja | B30: 179
A31: Rahul | B31: 165
A32: Riya | B32: 179
A33: Vikram | B33: 173
A34: (blank)
A35: Grand Total | B35: 1365
A37: Pivot Tables 4: Summarize Total Sales by Customer Segment and Payment Mode.
A39: Sum of Sales | B39: Column Labels
A40: Row Labels | B40: Cash | C40: Credit Card | D40: Debit Card | E40: Net Banking | F40: UPI | G40: (blank) | H40: Grand Total
A41: Corporate | B41: 1069799.4 | C41: 1131819.7 | D41: 957146.32 | E41: 835604.04 | F41: 893309.1 | H41: 4887678.6
A42: Education | B42: 1237138.5 | C42: 839850.2 | D42: 1052593.5 | E42: 863411.1 | F42: 1010783 | H42: 5003776.3
A43: Retail | B43: 1020549.6 | C43: 1002873.2 | D43: 1026966 | E43: 969490.4 | F43: 974188 | H43: 4994067.2
A44: Small Business | B44: 769792.44 | C44: 945019 | D44: 855035.88 | E44: 1010467.5 | F44: 987946.4 | H44: 4568261.2
A45: (blank)
A46: Grand Total | B46: 4097279.9 | C46: 3919562.1 | D46: 3891741.7 | E46: 3678973.1 | F46: 3866226.5 | H46: 19453783

Sheet DataSet
A1: Customer_ID | B1: Customer_Name | C1: Region | D1: Product_Category | E1: Unit_Price | F1: Quantity | G1: Discount | H1: Order_Date | I1: Sales | J1: Profit | K1: Salesperson | L1: Payment_Mode | M1: Customer_Segment
A2: ="CUST"&TEXT(ROW()-1,"0000") -> CUST0001 | B2: {=INDEX({"Aarav","Vivaan","Aditya","Arjun","Kabir","Rohan","Ananya","Diya","Ishita","Meera","Riya","Pooja","Neha","Kavya","Aisha","Priya","Rahul","Karan","Vikram","Sahil"},MOD(ROW()-2,20)+1)&" "&INDEX({"Shah","Patel","Mehta","Desai","Joshi","Gupta","Verma","Sharma","Trivedi","Rana","Mishra","Kapoor","Iyer","Nair","Singh"},MOD(INT((ROW()-2)/20),15)+1)} -> Aarav Shah | C2: {=INDEX({"North","South","East","West","Central"},MOD(ROW()-2,5)+1)} -> North | D2: {=INDEX({"Electronics","Clothing","Furniture","Books","Office Supplies"},MOD(ROW()-2,5)+1)} -> Electronics | E2: =ROUND(500+MOD((ROW()-2)*137,44500),2) -> 500 | F2: =MOD((ROW()-2)*7,11)+1 -> 1 | G2: =CHOOSE(MOD(ROW()-2,8)+1,0,0.02,0.05,0.08,0.1,0.12,0.15,0.2) -> 0 | H2: =DATE(2025,1,1)+MOD(ROW()-2,365) -> 45658 | I2: =ROUND(E2*F2*(1-G2),2) -> 500 | J2: =ROUND(I2*(0.08+MOD(ROW()-2,12)*0.02),2) -> 40 | K2: {=INDEX({"Amit","Neha","Riya","Karan","Pooja","Rahul","Meera","Vikram"},MOD(ROW()-2,8)+1)} -> Amit | L2: {=INDEX({"UPI","Credit Card","Debit Card","Cash","Net Banking"},MOD(ROW()-2,5)+1)} -> UPI | M2: {=INDEX({"Retail","Corporate","Education","Small Business"},MOD(ROW()-2,4)+1)} -> Retail
A3: ="CUST"&TEXT(ROW()-1,"0000") -> CUST0002 | B3: {=INDEX({"Aarav","Vivaan","Aditya","Arjun","Kabir","Rohan","Ananya","Diya","Ishita","Meera","Riya","Pooja","Neha","Kavya","Aisha","Priya","Rahul","Karan","Vikram","Sahil"},MOD(ROW()-2,20)+1)&" "&INDEX({"Shah","Patel","Mehta","Desai","Joshi","Gupta","Verma","Sharma","Trivedi","Rana","Mishra","Kapoor","Iyer","Nair","Singh"},MOD(INT((ROW()-2)/20),15)+1)} -> Vivaan Shah | C3: {=INDEX({"North","South","East","West","Central"},MOD(ROW()-2,5)+1)} -> South | D3: {=INDEX({"Electronics","Clothing","Furniture","Books","Office Supplies"},MOD(ROW()-2,5)+1)} -> Clothing | E3: =ROUND(500+MOD((ROW()-2)*137,44500),2) -> 637 | F3: =MOD((ROW()-2)*7,11)+1 -> 8 | G3: =CHOOSE(MOD(ROW()-2,8)+1,0,0.02,0.05,0.08,0.1,0.12,0.15,0.2) -> 0.02 | H3: =DATE(2025,1,1)+MOD(ROW()-2,365) -> 45659 | I3: =ROUND(E3*F3*(1-G3),2) -> 4994.08 | J3: =ROUND(I3*(0.08+MOD(ROW()-2,12)*0.02),2) -> 499.41 | K3: {=INDEX({"Amit","Neha","Riya","Karan","Pooja","Rahul","Meera","Vikram"},MOD(ROW()-2,8)+1)} -> Neha | L3: {=INDEX({"UPI","Credit Card","Debit Card","Cash","Net Banking"},MOD(ROW()-2,5)+1)} -> Credit Card | M3: {=INDEX({"Retail","Corporate","Education","Small Business"},MOD(ROW()-2,4)+1)} -> Corporate
A4: ="CUST"&TEXT(ROW()-1,"0000") -> CUST0003 | B4: {=INDEX({"Aarav","Vivaan","Aditya","Arjun","Kabir","Rohan","Ananya","Diya","Ishita","Meera","Riya","Pooja","Neha","Kavya","Aisha","Priya","Rahul","Karan","Vikram","Sahil"},MOD(ROW()-2,20)+1)&" "&INDEX({"Shah","Patel","Mehta","Desai","Joshi","Gupta","Verma","Sharma","Trivedi","Rana","Mishra","Kapoor","Iyer","Nair","Singh"},MOD(INT((ROW()-2)/20),15)+1)} -> Aditya Shah | C4: {=INDEX({"North","South","East","West","Central"},MOD(ROW()-2,5)+1)} -> East | D4: {=INDEX({"Electronics","Clothing","Furniture","Books","Office Supplies"},MOD(ROW()-2,5)+1)} -> Furniture | E4: =ROUND(500+MOD((ROW()-2)*137,44500),2) -> 774 | F4: =MOD((ROW()-2)*7,11)+1 -> 4 | G4: =CHOOSE(MOD(ROW()-2,8)+1,0,0.02,0.05,0.08,0.1,0.12,0.15,0.2) -> 0.05 | H4: =DATE(2025,1,1)+MOD(ROW()-2,365) -> 45660 | I4: =ROUND(E4*F4*(1-G4),2) -> 2941.2 | J4: =ROUND(I4*(0.08+MOD(ROW()-2,12)*0.02),2) -> 352.94 | K4: {=INDEX({"Amit","Neha","Riya","Karan","Pooja","Rahul","Meera","Vikram"},MOD(ROW()-2,8)+1)} -> Riya | L4: {=INDEX({"UPI","Credit Card","Debit Card","Cash","Net Banking"},MOD(ROW()-2,5)+1)} -> Debit Card | M4: {=INDEX({"Retail","Corporate","Education","Small Business"},MOD(ROW()-2,4)+1)} -> Education
A5: ="CUST"&TEXT(ROW()-1,"0000") -> CUST0004 | B5: {=INDEX({"Aarav","Vivaan","Aditya","Arjun","Kabir","Rohan","Ananya","Diya","Ishita","Meera","Riya","Pooja","Neha","Kavya","Aisha","Priya","Rahul","Karan","Vikram","Sahil"},MOD(ROW()-2,20)+1)&" "&INDEX({"Shah","Patel","Mehta","Desai","Joshi","Gupta","Verma","Sharma","Trivedi","Rana","Mishra","Kapoor","Iyer","Nair","Singh"},MOD(INT((ROW()-2)/20),15)+1)} -> Arjun Shah | C5: {=INDEX({"North","South","East","West","Central"},MOD(ROW()-2,5)+1)} -> West | D5: {=INDEX({"Electronics","Clothing","Furniture","Books","Office Supplies"},MOD(ROW()-2,5)+1)} -> Books | E5: =ROUND(500+MOD((ROW()-2)*137,44500),2) -> 911 | F5: =MOD((ROW()-2)*7,11)+1 -> 11 | G5: =CHOOSE(MOD(ROW()-2,8)+1,0,0.02,0.05,0.08,0.1,0.12,0.15,0.2) -> 0.08 | H5: =DATE(2025,1,1)+MOD(ROW()-2,365) -> 45661 | I5: =ROUND(E5*F5*(1-G5),2) -> 9219.32 | J5: =ROUND(I5*(0.08+MOD(ROW()-2,12)*0.02),2) -> 1290.7 | K5: {=INDEX({"Amit","Neha","Riya","Karan","Pooja","Rahul","Meera","Vikram"},MOD(ROW()-2,8)+1)} -> Karan | L5: {=INDEX({"UPI","Credit Card","Debit Card","Cash","Net Banking"},MOD(ROW()-2,5)+1)} -> Cash | M5: {=INDEX({"Retail","Corporate","Education","Small Business"},MOD(ROW()-2,4)+1)} -> Small Business
A6: ="CUST"&TEXT(ROW()-1,"0000") -> CUST0005 | B6: {=INDEX({"Aarav","Vivaan","Aditya","Arjun","Kabir","Rohan","Ananya","Diya","Ishita","Meera","Riya","Pooja","Neha","Kavya","Aisha","Priya","Rahul","Karan","Vikram","Sahil"},MOD(ROW()-2,20)+1)&" "&INDEX({"Shah","Patel","Mehta","Desai","Joshi","Gupta","Verma","Sharma","Trivedi","Rana","Mishra","Kapoor","Iyer","Nair","Singh"},MOD(INT((ROW()-2)/20),15)+1)} -> Kabir Shah | C6: {=INDEX({"North","South","East","West","Central"},MOD(ROW()-2,5)+1)} -> Central | D6: {=INDEX({"Electronics","Clothing","Furniture","Books","Office Supplies"},MOD(ROW()-2,5)+1)} -> Office Supplies | E6: =ROUND(500+MOD((ROW()-2)*137,44500),2) -> 1048 | F6: =MOD((ROW()-2)*7,11)+1 -> 7 | G6: =CHOOSE(MOD(ROW()-2,8)+1,0,0.02,0.05,0.08,0.1,0.12,0.15,0.2) -> 0.1 | H6: =DATE(2025,1,1)+MOD(ROW()-2,365) -> 45662 | I6: =ROUND(E6*F6*(1-G6),2) -> 6602.4 | J6: =ROUND(I6*(0.08+MOD(ROW()-2,12)*0.02),2) -> 1056.38 | K6: {=INDEX({"Amit","Neha","Riya","Karan","Pooja","Rahul","Meera","Vikram"},MOD(ROW()-2,8)+1)} -> Pooja | L6: {=INDEX({"UPI","Credit Card","Debit Card","Cash","Net Banking"},MOD(ROW()-2,5)+1)} -> Net Banking | M6: {=INDEX({"Retail","Corporate","Education","Small Business"},MOD(ROW()-2,4)+1)} -> Retail
A7: ="CUST"&TEXT(ROW()-1,"0000") -> CUST0006 | B7: {=INDEX({"Aarav","Vivaan","Aditya","Arjun","Kabir","Rohan","Ananya","Diya","Ishita","Meera","Riya","Pooja","Neha","Kavya","Aisha","Priya","Rahul","Karan","Vikram","Sahil"},MOD(ROW()-2,20)+1)&" "&INDEX({"Shah","Patel","Mehta","Desai","Joshi","Gupta","Verma","Sharma","Trivedi","Rana","Mishra","Kapoor","Iyer","Nair","Singh"},MOD(INT((ROW()-2)/20),15)+1)} -> Rohan Shah | C7: {=INDEX({"North","South","East","West","Central"},MOD(ROW()-2,5)+1)} -> North | D7: {=INDEX({"Electronics","Clothing","Furniture","Books","Office Supplies"},MOD(ROW()-2,5)+1)} -> Electronics | E7: =ROUND(500+MOD((ROW()-2)*137,44500),2) -> 1185 | F7: =MOD((ROW()-2)*7,11)+1 -> 3 | G7: =CHOOSE(MOD(ROW()-2,8)+1,0,0.02,0.05,0.08,0.1,0.12,0.15,0.2) -> 0.12 | H7: =DATE(2025,1,1)+MOD(ROW()-2,365) -> 45663 | I7: =ROUND(E7*F7*(1-G7),2) -> 3128.4 | J7: =ROUND(I7*(0.08+MOD(ROW()-2,12)*0.02),2) -> 563.11 | K7: {=INDEX({"Amit","Neha","Riya","Karan","Pooja","Rahul","Meera","Vikram"},MOD(ROW()-2,8)+1)} -> Rahul | L7: {=INDEX({"UPI","Credit Card","Debit Card","Cash","Net Banking"},MOD(ROW()-2,5)+1)} -> UPI | M7: {=INDEX({"Retail","Corporate","Education","Small Business"},MOD(ROW()-2,4)+1)} -> Corporate
A8: ="CUST"&TEXT(ROW()-1,"0000") -> CUST0007 | B8: {=INDEX({"Aarav","Vivaan","Aditya","Arjun","Kabir","Rohan","Ananya","Diya","Ishita","Meera","Riya","Pooja","Neha","Kavya","Aisha","Priya","Rahul","Karan","Vikram","Sahil"},MOD(ROW()-2,20)+1)&" "&INDEX({"Shah","Patel","Mehta","Desai","Joshi","Gupta","Verma","Sharma","Trivedi","Rana","Mishra","Kapoor","Iyer","Nair","Singh"},MOD(INT((ROW()-2)/20),15)+1)} -> Ananya Shah | C8: {=INDEX({"North","South","East","West","Central"},MOD(ROW()-2,5)+1)} -> South | D8: {=INDEX({"Electronics","Clothing","Furniture","Books","Office Supplies"},MOD(ROW()-2,5)+1)} -> Clothing | E8: =ROUND(500+MOD((ROW()-2)*137,44500),2) -> 1322 | F8: =MOD((ROW()-2)*7,11)+1 -> 10 | G8: =CHOOSE(MOD(ROW()-2,8)+1,0,0.02,0.05,0.08,0.1,0.12,0.15,0.2) -> 0.15 | H8: =DATE(2025,1,1)+MOD(ROW()-2,365) -> 45664 | I8: =ROUND(E8*F8*(1-G8),2) -> 11237 | J8: =ROUND(I8*(0.08+MOD(ROW()-2,12)*0.02),2) -> 2247.4 | K8: {=INDEX({"Amit","Neha","Riya","Karan","Pooja","Rahul","Meera","Vikram"},MOD(ROW()-2,8)+1)} -> Meera | L8: {=INDEX({"UPI","Credit Card","Debit Card","Cash","Net Banking"},MOD(ROW()-2,5)+1)} -> Credit Card | M8: {=INDEX({"Retail","Corporate","Education","Small Business"},MOD(ROW()-2,4)+1)} -> Education
A9: ="CUST"&TEXT(ROW()-1,"0000") -> CUST0008 | B9: {=INDEX({"Aarav","Vivaan","Aditya","Arjun","Kabir","Rohan","Ananya","Diya","Ishita","Meera","Riya","Pooja","Neha","Kavya","Aisha","Priya","Rahul","Karan","Vikram","Sahil"},MOD(ROW()-2,20)+1)&" "&INDEX({"Shah","Patel","Mehta","Desai","Joshi","Gupta","Verma","Sharma","Trivedi","Rana","Mishra","Kapoor","Iyer","Nair","Singh"},MOD(INT((ROW()-2)/20),15)+1)} -> Diya Shah | C9: {=INDEX({"North","South","East","West","Central"},MOD(ROW()-2,5)+1)} -> East | D9: {=INDEX({"Electronics","Clothing","Furniture","Books","Office Supplies"},MOD(ROW()-2,5)+1)} -> Furniture | E9: =ROUND(500+MOD((ROW()-2)*137,44500),2) -> 1459 | F9: =MOD((ROW()-2)*7,11)+1 -> 6 | G9: =CHOOSE(MOD(ROW()-2,8)+1,0,0.02,0.05,0.08,0.1,0.12,0.15,0.2) -> 0.2 | H9: =DATE(2025,1,1)+MOD(ROW()-2,365) -> 45665 | I9: =ROUND(E9*F9*(1-G9),2) -> 7003.2 | J9: =ROUND(I9*(0.08+MOD(ROW()-2,12)*0.02),2) -> 1540.7 | K9: {=INDEX({"Amit","Neha","Riya","Karan","Pooja","Rahul","Meera","Vikram"},MOD(ROW()-2,8)+1)} -> Vikram | L9: {=INDEX({"UPI","Credit Card","Debit Card","Cash","Net Banking"},MOD(ROW()-2,5)+1)} -> Debit Card | M9: {=INDEX({"Retail","Corporate","Education","Small Business"},MOD(ROW()-2,4)+1)} -> Small Business
A10: ="CUST"&TEXT(ROW()-1,"0000") -> CUST0009 | B10: {=INDEX({"Aarav","Vivaan","Aditya","Arjun","Kabir","Rohan","Ananya","Diya","Ishita","Meera","Riya","Pooja","Neha","Kavya","Aisha","Priya","Rahul","Karan","Vikram","Sahil"},MOD(ROW()-2,20)+1)&" "&INDEX({"Shah","Patel","Mehta","Desai","Joshi","Gupta","Verma","Sharma","Trivedi","Rana","Mishra","Kapoor","Iyer","Nair","Singh"},MOD(INT((ROW()-2)/20),15)+1)} -> Ishita Shah | C10: {=INDEX({"North","South","East","West","Central"},MOD(ROW()-2,5)+1)} -> West | D10: {=INDEX({"Electronics","Clothing","Furniture","Books","Office Supplies"},MOD(ROW()-2,5)+1)} -> Books | E10: =ROUND(500+MOD((ROW()-2)*137,44500),2) -> 1596 | F10: =MOD((ROW()-2)*7,11)+1 -> 2 | G10: =CHOOSE(MOD(ROW()-2,8)+1,0,0.02,0.05,0.08,0.1,0.12,0.15,0.2) -> 0 | H10: =DATE(2025,1,1)+MOD(ROW()-2,365) -> 45666 | I10: =ROUND(E10*F10*(1-G10),2) -> 3192 | J10: =ROUND(I10*(0.08+MOD(ROW()-2,12)*0.02),2) -> 766.08 | K10: {=INDEX({"Amit","Neha","Riya","Karan","Pooja","Rahul","Meera","Vikram"},MOD(ROW()-2,8)+1)} -> Amit | L10: {=INDEX({"UPI","Credit Card","Debit Card","Cash","Net Banking"},MOD(ROW()-2,5)+1)} -> Cash | M10: {=INDEX({"Retail","Corporate","Education","Small Business"},MOD(ROW()-2,4)+1)} -> Retail
A11: ="CUST"&TEXT(ROW()-1,"0000") -> CUST0010 | B11: {=INDEX({"Aarav","Vivaan","Aditya","Arjun","Kabir","Rohan","Ananya","Diya","Ishita","Meera","Riya","Pooja","Neha","Kavya","Aisha","Priya","Rahul","Karan","Vikram","Sahil"},MOD(ROW()-2,20)+1)&" "&INDEX({"Shah","Patel","Mehta","Desai","Joshi","Gupta","Verma","Sharma","Trivedi","Rana","Mishra","Kapoor","Iyer","Nair","Singh"},MOD(INT((ROW()-2)/20),15)+1)} -> Meera Shah | C11: {=INDEX({"North","South","East","West","Central"},MOD(ROW()-2,5)+1)} -> Central | D11: {=INDEX({"Electronics","Clothing","Furniture","Books","Office Supplies"},MOD(ROW()-2,5)+1)} -> Office Supplies | E11: =ROUND(500+MOD((ROW()-2)*137,44500),2) -> 1733 | F11: =MOD((ROW()-2)*7,11)+1 -> 9 | G11: =CHOOSE(MOD(ROW()-2,8)+1,0,0.02,0.05,0.08,0.1,0.12,0.15,0.2) -> 0.02 | H11: =DATE(2025,1,1)+MOD(ROW()-2,365) -> 45667 | I11: =ROUND(E11*F11*(1-G11),2) -> 15285.06 | J11: =ROUND(I11*(0.08+MOD(ROW()-2,12)*0.02),2) -> 3974.12 | K11: {=INDEX({"Amit","Neha","Riya","Karan","Pooja","Rahul","Meera","Vikram"},MOD(ROW()-2,8)+1)} -> Neha | L11: {=INDEX({"UPI","Credit Card","Debit Card","Cash","Net Banking"},MOD(ROW()-2,5)+1)} -> Net Banking | M11: {=INDEX({"Retail","Corporate","Education","Small Business"},MOD(ROW()-2,4)+1)} -> Corporate
A12: ="CUST"&TEXT(ROW()-1,"0000") -> CUST0011 | B12: {=INDEX({"Aarav","Vivaan","Aditya","Arjun","Kabir","Rohan","Ananya","Diya","Ishita","Meera","Riya","Pooja","Neha","Kavya","Aisha","Priya","Rahul","Karan","Vikram","Sahil"},MOD(ROW()-2,20)+1)&" "&INDEX({"Shah","Patel","Mehta","Desai","Joshi","Gupta","Verma","Sharma","Trivedi","Rana","Mishra","Kapoor","Iyer","Nair","Singh"},MOD(INT((ROW()-2)/20),15)+1)} -> Riya Shah | C12: {=INDEX({"North","South","East","West","Central"},MOD(ROW()-2,5)+1)} -> North | D12: {=INDEX({"Electronics","Clothing","Furniture","Books","Office Supplies"},MOD(ROW()-2,5)+1)} -> Electronics | E12: =ROUND(500+MOD((ROW()-2)*137,44500),2) -> 1870 | F12: =MOD((ROW()-2)*7,11)+1 -> 5 | G12: =CHOOSE(MOD(ROW()-2,8)+1,0,0.02,0.05,0.08,0.1,0.12,0.15,0.2) -> 0.05 | H12: =DATE(2025,1,1)+MOD(ROW()-2,365) -> 45668 | I12: =ROUND(E12*F12*(1-G12),2) -> 8882.5 | J12: =ROUND(I12*(0.08+MOD(ROW()-2,12)*0.02),2) -> 2487.1 | K12: {=INDEX({"Amit","Neha","Riya","Karan","Pooja","Rahul","Meera","Vikram"},MOD(ROW()-2,8)+1)} -> Riya | L12: {=INDEX({"UPI","Credit Card","Debit Card","Cash","Net Banking"},MOD(ROW()-2,5)+1)} -> UPI | M12: {=INDEX({"Retail","Corporate","Education","Small Business"},MOD(ROW()-2,4)+1)} -> Education
A13: ="CUST"&TEXT(ROW()-1,"0000") -> CUST0012 | B13: {=INDEX({"Aarav","Vivaan","Aditya","Arjun","Kabir","Rohan","Ananya","Diya","Ishita","Meera","Riya","Pooja","Neha","Kavya","Aisha","Priya","Rahul","Karan","Vikram","Sahil"},MOD(ROW()-2,20)+1)&" "&INDEX({"Shah","Patel","Mehta","Desai","Joshi","Gupta","Verma","Sharma","Trivedi","Rana","Mishra","Kapoor","Iyer","Nair","Singh"},MOD(INT((ROW()-2)/20),15)+1)} -> Pooja Shah | C13: {=INDEX({"North","South","East","West","Central"},MOD(ROW()-2,5)+1)} -> South | D13: {=INDEX({"Electronics","Clothing","Furniture","Books","Office Supplies"},MOD(ROW()-2,5)+1)} -> Clothing | E13: =ROUND(500+MOD((ROW()-2)*137,44500),2) -> 2007 | F13: =MOD((ROW()-2)*7,11)+1 -> 1 | G13: =CHOOSE(MOD(ROW()-2,8)+1,0,0.02,0.05,0.08,0.1,0.12,0.15,0.2) -> 0.08 | H13: =DATE(2025,1,1)+MOD(ROW()-2,365) -> 45669 | I13: =ROUND(E13*F13*(1-G13),2) -> 1846.44 | J13: =ROUND(I13*(0.08+MOD(ROW()-2,12)*0.02),2) -> 553.93 | K13: {=INDEX({"Amit","Neha","Riya","Karan","Pooja","Rahul","Meera","Vikram"},MOD(ROW()-2,8)+1)} -> Karan | L13: {=INDEX({"UPI","Credit Card","Debit Card","Cash","Net Banking"},MOD(ROW()-2,5)+1)} -> Credit Card | M13: {=INDEX({"Retail","Corporate","Education","Small Business"},MOD(ROW()-2,4)+1)} -> Small Business
... A15: ="CUST"&TEXT(ROW()-1,"0000") -> CUST0014 | B15: {=INDEX({"Aarav","Vivaan","Aditya","Arjun","Kabir","Rohan","Ananya","Diya","Ishita","Meera","Riya","Pooja","Neha","Kavya","Aisha","Priya","Rahul","Karan","Vikram","Sahil"},MOD(ROW()-2,20)+1)&" "&INDEX({"Shah","Patel","Mehta","Desai","Joshi","Gupta","Verma","Sharma","Trivedi","Rana","Mishra","Kapoor","Iyer","Nair","Singh"},MOD(INT((ROW()-2)/20),15)+1)} -> Kavya Shah | C15: {=INDEX({"North","South","East","West","Central"},MOD(ROW()-2,5)+1)} -> West | D15: {=INDEX({"Electronics","Clothing","Furniture","Books","Office Supplies"},MOD(ROW()-2,5)+1)} -> Books | E15: =ROUND(500+MOD((ROW()-2)*137,44500),2) -> 2281 | F15: =MOD((ROW()-2)*7,11)+1 -> 4 | G15: =CHOOSE(MOD(ROW()-2,8)+1,0,0.02,0.05,0.08,0.1,0.12,0.15,0.2) -> 0.12 | H15: =DATE(2025,1,1)+MOD(ROW()-2,365) -> 45671 | I15: =ROUND(E15*F15*(1-G15),2) -> 8029.12 | J15: =ROUND(I15*(0.08+MOD(ROW()-2,12)*0.02),2) -> 802.91 | K15: {=INDEX({"Amit","Neha","Riya","Karan","Pooja","Rahul","Meera","Vikram"},MOD(ROW()-2,8)+1)} -> Rahul | L15: {=INDEX({"UPI","Credit Card","Debit Card","Cash","Net Banking"},MOD(ROW()-2,5)+1)} -> Cash | M15: {=INDEX({"Retail","Corporate","Education","Small Business"},MOD(ROW()-2,4)+1)} -> Corporate
A16: ="CUST"&TEXT(ROW()-1,"0000") -> CUST0015 | B16: Vikram Patel | C16: {=INDEX({"North","South","East","West","Central"},MOD(ROW()-2,5)+1)} -> Central | D16: {=INDEX({"Electronics","Clothing","Furniture","Books","Office Supplies"},MOD(ROW()-2,5)+1)} -> Office Supplies | E16: =ROUND(500+MOD((ROW()-2)*137,44500),2) -> 2418 | F16: =MOD((ROW()-2)*7,11)+1 -> 11 | G16: =CHOOSE(MOD(ROW()-2,8)+1,0,0.02,0.05,0.08,0.1,0.12,0.15,0.2) -> 0.15 | H16: =DATE(2025,1,1)+MOD(ROW()-2,365) -> 45672 | I16: =ROUND(E16*F16*(1-G16),2) -> 22608.3 | J16: =ROUND(I16*(0.08+MOD(ROW()-2,12)*0.02),2) -> 2713 | K16: {=INDEX({"Amit","Neha","Riya","Karan","Pooja","Rahul","Meera","Vikram"},MOD(ROW()-2,8)+1)} -> Meera | L16: {=INDEX({"UPI","Credit Card","Debit Card","Cash","Net Banking"},MOD(ROW()-2,5)+1)} -> Net Banking | M16: {=INDEX({"Retail","Corporate","Education","Small Business"},MOD(ROW()-2,4)+1)} -> Education
A17: ="CUST"&TEXT(ROW()-1,"0000") -> CUST0016 | B17: {=INDEX({"Aarav","Vivaan","Aditya","Arjun","Kabir","Rohan","Ananya","Diya","Ishita","Meera","Riya","Pooja","Neha","Kavya","Aisha","Priya","Rahul","Karan","Vikram","Sahil"},MOD(ROW()-2,20)+1)&" "&INDEX({"Shah","Patel","Mehta","Desai","Joshi","Gupta","Verma","Sharma","Trivedi","Rana","Mishra","Kapoor","Iyer","Nair","Singh"},MOD(INT((ROW()-2)/20),15)+1)} -> Priya Shah | C17: {=INDEX({"North","South","East","West","Central"},MOD(ROW()-2,5)+1)} -> North | D17: {=INDEX({"Electronics","Clothing","Furniture","Books","Office Supplies"},MOD(ROW()-2,5)+1)} -> Electronics | E17: =ROUND(500+MOD((ROW()-2)*137,44500),2) -> 2555 | F17: =MOD((ROW()-2)*7,11)+1 -> 7 | G17: =CHOOSE(MOD(ROW()-2,8)+1,0,0.02,0.05,0.08,0.1,0.12,0.15,0.2) -> 0.2 | H17: 45703 | I17: =ROUND(E17*F17*(1-G17),2) -> 14308 | J17: =ROUND(I17*(0.08+MOD(ROW()-2,12)*0.02),2) -> 2003.12 | K17: {=INDEX({"Amit","Neha","Riya","Karan","Pooja","Rahul","Meera","Vikram"},MOD(ROW()-2,8)+1)} -> Vikram | L17: {=INDEX({"UPI","Credit Card","Debit Card","Cash","Net Banking"},MOD(ROW()-2,5)+1)} -> UPI | M17: {=INDEX({"Retail","Corporate","Education","Small Business"},MOD(ROW()-2,4)+1)} -> Small Business
A18: ="CUST"&TEXT(ROW()-1,"0000") -> CUST0017 | B18: {=INDEX({"Aarav","Vivaan","Aditya","Arjun","Kabir","Rohan","Ananya","Diya","Ishita","Meera","Riya","Pooja","Neha","Kavya","Aisha","Priya","Rahul","Karan","Vikram","Sahil"},MOD(ROW()-2,20)+1)&" "&INDEX({"Shah","Patel","Mehta","Desai","Joshi","Gupta","Verma","Sharma","Trivedi","Rana","Mishra","Kapoor","Iyer","Nair","Singh"},MOD(INT((ROW()-2)/20),15)+1)} -> Rahul Shah | C18: {=INDEX({"North","South","East","West","Central"},MOD(ROW()-2,5)+1)} -> South | D18: {=INDEX({"Electronics","Clothing","Furniture","Books","Office Supplies"},MOD(ROW()-2,5)+1)} -> Clothing | E18: 6802 | F18: =MOD((ROW()-2)*7,11)+1 -> 3 | G18: =CHOOSE(MOD(ROW()-2,8)+1,0,0.02,0.05,0.08,0.1,0.12,0.15,0.2) -> 0 | H18: =DATE(2025,1,1)+MOD(ROW()-2,365) -> 45674 | I18: =ROUND(E18*F18*(1-G18),2) -> 20406 | J18: =ROUND(I18*(0.08+MOD(ROW()-2,12)*0.02),2) -> 3264.96 | K18: {=INDEX({"Amit","Neha","Riya","Karan","Pooja","Rahul","Meera","Vikram"},MOD(ROW()-2,8)+1)} -> Amit | L18: {=INDEX({"UPI","Credit Card","Debit Card","Cash","Net Banking"},MOD(ROW()-2,5)+1)} -> Credit Card | M18: {=INDEX({"Retail","Corporate","Education","Small Business"},MOD(ROW()-2,4)+1)} -> Retail
A19: ="CUST"&TEXT(ROW()-1,"0000") -> CUST0018 | B19: {=INDEX({"Aarav","Vivaan","Aditya","Arjun","Kabir","Rohan","Ananya","Diya","Ishita","Meera","Riya","Pooja","Neha","Kavya","Aisha","Priya","Rahul","Karan","Vikram","Sahil"},MOD(ROW()-2,20)+1)&" "&INDEX({"Shah","Patel","Mehta","Desai","Joshi","Gupta","Verma","Sharma","Trivedi","Rana","Mishra","Kapoor","Iyer","Nair","Singh"},MOD(INT((ROW()-2)/20),15)+1)} -> Karan Shah | C19: {=INDEX({"North","South","East","West","Central"},MOD(ROW()-2,5)+1)} -> East | D19: {=INDEX({"Electronics","Clothing","Furniture","Books","Office Supplies"},MOD(ROW()-2,5)+1)} -> Furniture | E19: =ROUND(500+MOD((ROW()-2)*137,44500),2) -> 2829 | F19: =MOD((ROW()-2)*7,11)+1 -> 10 | G19: =CHOOSE(MOD(ROW()-2,8)+1,0,0.02,0.05,0.08,0.1,0.12,0.15,0.2) -> 0.02 | H19: =DATE(2025,1,1)+MOD(ROW()-2,365) -> 45675 | I19: =ROUND(E19*F19*(1-G19),2) -> 27724.2 | J19: =ROUND(I19*(0.08+MOD(ROW()-2,12)*0.02),2) -> 4990.36 | K19: {=INDEX({"Amit","Neha","Riya","Karan","Pooja","Rahul","Meera","Vikram"},MOD(ROW()-2,8)+1)} -> Neha | L19: {=INDEX({"UPI","Credit Card","Debit Card","Cash","Net Banking"},MOD(ROW()-2,5)+1)} -> Debit Card | M19: {=INDEX({"Retail","Corporate","Education","Small Business"},MOD(ROW()-2,4)+1)} -> Corporate
A20: ="CUST"&TEXT(ROW()-1,"0000") -> CUST0019 | B20: {=INDEX({"Aarav","Vivaan","Aditya","Arjun","Kabir","Rohan","Ananya","Diya","Ishita","Meera","Riya","Pooja","Neha","Kavya","Aisha","Priya","Rahul","Karan","Vikram","Sahil"},MOD(ROW()-2,20)+1)&" "&INDEX({"Shah","Patel","Mehta","Desai","Joshi","Gupta","Verma","Sharma","Trivedi","Rana","Mishra","Kapoor","Iyer","Nair","Singh"},MOD(INT((ROW()-2)/20),15)+1)} -> Vikram Shah | C20: {=INDEX({"North","South","East","West","Central"},MOD(ROW()-2,5)+1)} -> West | D20: {=INDEX({"Electronics","Clothing","Furniture","Books","Office Supplies"},MOD(ROW()-2,5)+1)} -> Books | E20: =ROUND(500+MOD((ROW()-2)*137,44500),2) -> 2966 | F20: =MOD((ROW()-2)*7,11)+1 -> 6 | G20: =CHOOSE(MOD(ROW()-2,8)+1,0,0.02,0.05,0.08,0.1,0.12,0.15,0.2) -> 0.05 | H20: =DATE(2025,1,1)+MOD(ROW()-2,365) -> 45676 | I20: =ROUND(E20*F20*(1-G20),2) -> 16906.2 | J20: =ROUND(I20*(0.08+MOD(ROW()-2,12)*0.02),2) -> 3381.24 | K20: {=INDEX({"Amit","Neha","Riya","Karan","Pooja","Rahul","Meera","Vikram"},MOD(ROW()-2,8)+1)} -> Riya | L20: {=INDEX({"UPI","Credit Card","Debit Card","Cash","Net Banking"},MOD(ROW()-2,5)+1)} -> Cash | M20: {=INDEX({"Retail","Corporate","Education","Small Business"},MOD(ROW()-2,4)+1)} -> Education
A21: ="CUST"&TEXT(ROW()-1,"0000") -> CUST0020 | B21: {=INDEX({"Aarav","Vivaan","Aditya","Arjun","Kabir","Rohan","Ananya","Diya","Ishita","Meera","Riya","Pooja","Neha","Kavya","Aisha","Priya","Rahul","Karan","Vikram","Sahil"},MOD(ROW()-2,20)+1)&" "&INDEX({"Shah","Patel","Mehta","Desai","Joshi","Gupta","Verma","Sharma","Trivedi","Rana","Mishra","Kapoor","Iyer","Nair","Singh"},MOD(INT((ROW()-2)/20),15)+1)} -> Sahil Shah | C21: {=INDEX({"North","South","East","West","Central"},MOD(ROW()-2,5)+1)} -> Central | D21: {=INDEX({"Electronics","Clothing","Furniture","Books","Office Supplies"},MOD(ROW()-2,5)+1)} -> Office Supplies | E21: =ROUND(500+MOD((ROW()-2)*137,44500),2) -> 3103 | F21: =MOD((ROW()-2)*7,11)+1 -> 2 | G21: =CHOOSE(MOD(ROW()-2,8)+1,0,0.02,0.05,0.08,0.1,0.12,0.15,0.2) -> 0.08 | H21: =DATE(2025,1,1)+MOD(ROW()-2,365) -> 45677 | I21: =ROUND(E21*F21*(1-G21),2) -> 5709.52 | J21: =ROUND(I21*(0.08+MOD(ROW()-2,12)*0.02),2) -> 1256.09 | K21: {=INDEX({"Amit","Neha","Riya","Karan","Pooja","Rahul","Meera","Vikram"},MOD(ROW()-2,8)+1)} -> Karan | L21: {=INDEX({"UPI","Credit Card","Debit Card","Cash","Net Banking"},MOD(ROW()-2,5)+1)} -> Net Banking | M21: {=INDEX({"Retail","Corporate","Education","Small Business"},MOD(ROW()-2,4)+1)} -> Small Business
A22: ="CUST"&TEXT(ROW()-1,"0000") -> CUST0021 | B22: {=INDEX({"Aarav","Vivaan","Aditya","Arjun","Kabir","Rohan","Ananya","Diya","Ishita","Meera","Riya","Pooja","Neha","Kavya","Aisha","Priya","Rahul","Karan","Vikram","Sahil"},MOD(ROW()-2,20)+1)&" "&INDEX({"Shah","Patel","Mehta","Desai","Joshi","Gupta","Verma","Sharma","Trivedi","Rana","Mishra","Kapoor","Iyer","Nair","Singh"},MOD(INT((ROW()-2)/20),15)+1)} -> Aarav Patel | C22: {=INDEX({"North","South","East","West","Central"},MOD(ROW()-2,5)+1)} -> North | D22: {=INDEX({"Electronics","Clothing","Furniture","Books","Office Supplies"},MOD(ROW()-2,5)+1)} -> Electronics | E22: =ROUND(500+MOD((ROW()-2)*137,44500),2) -> 3240 | F22: =MOD((ROW()-2)*7,11)+1 -> 9 | G22: =CHOOSE(MOD(ROW()-2,8)+1,0,0.02,0.05,0.08,0.1,0.12,0.15,0.2) -> 0.1 | H22: =DATE(2025,1,1)+MOD(ROW()-2,365) -> 45678 | I22: =ROUND(E22*F22*(1-G22),2) -> 26244 | J22: =ROUND(I22*(0.08+MOD(ROW()-2,12)*0.02),2) -> 6298.56 | K22: {=INDEX({"Amit","Neha","Riya","Karan","Pooja","Rahul","Meera","Vikram"},MOD(ROW()-2,8)+1)} -> Pooja | L22: {=INDEX({"UPI","Credit Card","Debit Card","Cash","Net Banking"},MOD(ROW()-2,5)+1)} -> UPI | M22: {=INDEX({"Retail","Corporate","Education","Small Business"},MOD(ROW()-2,4)+1)} -> Retail
A23: ="CUST"&TEXT(ROW()-1,"0000") -> CUST0022 | B23: {=INDEX({"Aarav","Vivaan","Aditya","Arjun","Kabir","Rohan","Ananya","Diya","Ishita","Meera","Riya","Pooja","Neha","Kavya","Aisha","Priya","Rahul","Karan","Vikram","Sahil"},MOD(ROW()-2,20)+1)&" "&INDEX({"Shah","Patel","Mehta","Desai","Joshi","Gupta","Verma","Sharma","Trivedi","Rana","Mishra","Kapoor","Iyer","Nair","Singh"},MOD(INT((ROW()-2)/20),15)+1)} -> Vivaan Patel | C23: {=INDEX({"North","South","East","West","Central"},MOD(ROW()-2,5)+1)} -> South | D23: {=INDEX({"Electronics","Clothing","Furniture","Books","Office Supplies"},MOD(ROW()-2,5)+1)} -> Clothing | E23: =ROUND(500+MOD((ROW()-2)*137,44500),2) -> 3377 | F23: =MOD((ROW()-2)*7,11)+1 -> 5 | G23: =CHOOSE(MOD(ROW()-2,8)+1,0,0.02,0.05,0.08,0.1,0.12,0.15,0.2) -> 0.12 | H23: =DATE(2025,1,1)+MOD(ROW()-2,365) -> 45679 | I23: =ROUND(E23*F23*(1-G23),2) -> 14858.8 | J23: =ROUND(I23*(0.08+MOD(ROW()-2,12)*0.02),2) -> 3863.29 | K23: {=INDEX({"Amit","Neha","Riya","Karan","Pooja","Rahul","Meera","Vikram"},MOD(ROW()-2,8)+1)} -> Rahul | L23: {=INDEX({"UPI","Credit Card","Debit Card","Cash","Net Banking"},MOD(ROW()-2,5)+1)} -> Credit Card | M23: {=INDEX({"Retail","Corporate","Education","Small Business"},MOD(ROW()-2,4)+1)} -> Corporate
A24: ="CUST"&TEXT(ROW()-1,"0000") -> CUST0023 | B24: {=INDEX({"Aarav","Vivaan","Aditya","Arjun","Kabir","Rohan","Ananya","Diya","Ishita","Meera","Riya","Pooja","Neha","Kavya","Aisha","Priya","Rahul","Karan","Vikram","Sahil"},MOD(ROW()-2,20)+1)&" "&INDEX({"Shah","Patel","Mehta","Desai","Joshi","Gupta","Verma","Sharma","Trivedi","Rana","Mishra","Kapoor","Iyer","Nair","Singh"},MOD(INT((ROW()-2)/20),15)+1)} -> Aditya Patel | C24: {=INDEX({"North","South","East","West","Central"},MOD(ROW()-2,5)+1)} -> East | D24: {=INDEX({"Electronics","Clothing","Furniture","Books","Office Supplies"},MOD(ROW()-2,5)+1)} -> Furniture | E24: =ROUND(500+MOD((ROW()-2)*137,44500),2) -> 3514 | F24: =MOD((ROW()-2)*7,11)+1 -> 1 | G24: =CHOOSE(MOD(ROW()-2,8)+1,0,0.02,0.05,0.08,0.1,0.12,0.15,0.2) -> 0.15 | H24: =DATE(2025,1,1)+MOD(ROW()-2,365) -> 45680 | I24: =ROUND(E24*F24*(1-G24),2) -> 2986.9 | J24: =ROUND(I24*(0.08+MOD(ROW()-2,12)*0.02),2) -> 836.33 | K24: {=INDEX({"Amit","Neha","Riya","Karan","Pooja","Rahul","Meera","Vikram"},MOD(ROW()-2,8)+1)} -> Meera | L24: {=INDEX({"UPI","Credit Card","Debit Card","Cash","Net Banking"},MOD(ROW()-2,5)+1)} -> Debit Card | M24: {=INDEX({"Retail","Corporate","Education","Small Business"},MOD(ROW()-2,4)+1)} -> Education
A25: ="CUST"&TEXT(ROW()-1,"0000") -> CUST0024 | B25: {=INDEX({"Aarav","Vivaan","Aditya","Arjun","Kabir","Rohan","Ananya","Diya","Ishita","Meera","Riya","Pooja","Neha","Kavya","Aisha","Priya","Rahul","Karan","Vikram","Sahil"},MOD(ROW()-2,20)+1)&" "&INDEX({"Shah","Patel","Mehta","Desai","Joshi","Gupta","Verma","Sharma","Trivedi","Rana","Mishra","Kapoor","Iyer","Nair","Singh"},MOD(INT((ROW()-2)/20),15)+1)} -> Arjun Patel | C25: {=INDEX({"North","South","East","West","Central"},MOD(ROW()-2,5)+1)} -> West | D25: {=INDEX({"Electronics","Clothing","Furniture","Books","Office Supplies"},MOD(ROW()-2,5)+1)} -> Books | E25: =ROUND(500+MOD((ROW()-2)*137,44500),2) -> 3651 | F25: 9 | G25: =CHOOSE(MOD(ROW()-2,8)+1,0,0.02,0.05,0.08,0.1,0.12,0.15,0.2) -> 0.2 | H25: =DATE(2025,1,1)+MOD(ROW()-2,365) -> 45681 | I25: =ROUND(E25*F25*(1-G25),2) -> 26287.2 | J25: =ROUND(I25*(0.08+MOD(ROW()-2,12)*0.02),2) -> 7886.16 | K25: {=INDEX({"Amit","Neha","Riya","Karan","Pooja","Rahul","Meera","Vikram"},MOD(ROW()-2,8)+1)} -> Vikram | L25: {=INDEX({"UPI","Credit Card","Debit Card","Cash","Net Banking"},MOD(ROW()-2,5)+1)} -> Cash | M25: {=INDEX({"Retail","Corporate","Education","Small Business"},MOD(ROW()-2,4)+1)} -> Small Business
A26: ="CUST"&TEXT(ROW()-1,"0000") -> CUST0025 | B26: {=INDEX({"Aarav","Vivaan","Aditya","Arjun","Kabir","Rohan","Ananya","Diya","Ishita","Meera","Riya","Pooja","Neha","Kavya","Aisha","Priya","Rahul","Karan","Vikram","Sahil"},MOD(ROW()-2,20)+1)&" "&INDEX({"Shah","Patel","Mehta","Desai","Joshi","Gupta","Verma","Sharma","Trivedi","Rana","Mishra","Kapoor","Iyer","Nair","Singh"},MOD(INT((ROW()-2)/20),15)+1)} -> Kabir Patel | C26: {=INDEX({"North","South","East","West","Central"},MOD(ROW()-2,5)+1)} -> Central | D26: {=INDEX({"Electronics","Clothing","Furniture","Books","Office Supplies"},MOD(ROW()-2,5)+1)} -> Office Supplies | E26: =ROUND(500+MOD((ROW()-2)*137,44500),2) -> 3788 | F26: =MOD((ROW()-2)*7,11)+1 -> 4 | G26: =CHOOSE(MOD(ROW()-2,8)+1,0,0.02,0.05,0.08,0.1,0.12,0.15,0.2) -> 0 | H26: =DATE(2025,1,1)+MOD(ROW()-2,365) -> 45682 | I26: =ROUND(E26*F26*(1-G26),2) -> 15152 | J26: =ROUND(I26*(0.08+MOD(ROW()-2,12)*0.02),2) -> 1212.16 | K26: {=INDEX({"Amit","Neha","Riya","Karan","Pooja","Rahul","Meera","Vikram"},MOD(ROW()-2,8)+1)} -> Amit | L26: {=INDEX({"UPI","Credit Card","Debit Card","Cash","Net Banking"},MOD(ROW()-2,5)+1)} -> Net Banking | M26: {=INDEX({"Retail","Corporate","Education","Small Business"},MOD(ROW()-2,4)+1)} -> Retail
A27: ="CUST"&TEXT(ROW()-1,"0000") -> CUST0026 | B27: {=INDEX({"Aarav","Vivaan","Aditya","Arjun","Kabir","Rohan","Ananya","Diya","Ishita","Meera","Riya","Pooja","Neha","Kavya","Aisha","Priya","Rahul","Karan","Vikram","Sahil"},MOD(ROW()-2,20)+1)&" "&INDEX({"Shah","Patel","Mehta","Desai","Joshi","Gupta","Verma","Sharma","Trivedi","Rana","Mishra","Kapoor","Iyer","Nair","Singh"},MOD(INT((ROW()-2)/20),15)+1)} -> Rohan Patel | C27: {=INDEX({"North","South","East","West","Central"},MOD(ROW()-2,5)+1)} -> North | D27: {=INDEX({"Electronics","Clothing","Furniture","Books","Office Supplies"},MOD(ROW()-2,5)+1)} -> Electronics | E27: =ROUND(500+MOD((ROW()-2)*137,44500),2) -> 3925 | F27: =MOD((ROW()-2)*7,11)+1 -> 11 | G27: =CHOOSE(MOD(ROW()-2,8)+1,0,0.02,0.05,0.08,0.1,0.12,0.15,0.2) -> 0.02 | H27: =DATE(2025,1,1)+MOD(ROW()-2,365) -> 45683 | I27: =ROUND(E27*F27*(1-G27),2) -> 42311.5 | J27: =ROUND(I27*(0.08+MOD(ROW()-2,12)*0.02),2) -> 4231.15 | K27: {=INDEX({"Amit","Neha","Riya","Karan","Pooja","Rahul","Meera","Vikram"},MOD(ROW()-2,8)+1)} -> Neha | L27: {=INDEX({"UPI","Credit Card","Debit Card","Cash","Net Banking"},MOD(ROW()-2,5)+1)} -> UPI | M27: {=INDEX({"Retail","Corporate","Education","Small Business"},MOD(ROW()-2,4)+1)} -> Corporate
A28: ="CUST"&TEXT(ROW()-1,"0000") -> CUST0027 | B28: {=INDEX({"Aarav","Vivaan","Aditya","Arjun","Kabir","Rohan","Ananya","Diya","Ishita","Meera","Riya","Pooja","Neha","Kavya","Aisha","Priya","Rahul","Karan","Vikram","Sahil"},MOD(ROW()-2,20)+1)&" "&INDEX({"Shah","Patel","Mehta","Desai","Joshi","Gupta","Verma","Sharma","Trivedi","Rana","Mishra","Kapoor","Iyer","Nair","Singh"},MOD(INT((ROW()-2)/20),15)+1)} -> Ananya Patel | C28: {=INDEX({"North","South","East","West","Central"},MOD(ROW()-2,5)+1)} -> South | D28: {=INDEX({"Electronics","Clothing","Furniture","Books","Office Supplies"},MOD(ROW()-2,5)+1)} -> Clothing | E28: =ROUND(500+MOD((ROW()-2)*137,44500),2) -> 4062 | F28: =MOD((ROW()-2)*7,11)+1 -> 7 | G28: =CHOOSE(MOD(ROW()-2,8)+1,0,0.02,0.05,0.08,0.1,0.12,0.15,0.2) -> 0.05 | H28: =DATE(2025,1,1)+MOD(ROW()-2,365) -> 45684 | I28: =ROUND(E28*F28*(1-G28),2) -> 27012.3 | J28: =ROUND(I28*(0.08+MOD(ROW()-2,12)*0.02),2) -> 3241.48 | K28: {=INDEX({"Amit","Neha","Riya","Karan","Pooja","Rahul","Meera","Vikram"},MOD(ROW()-2,8)+1)} -> Riya | L28: {=INDEX({"UPI","Credit Card","Debit Card","Cash","Net Banking"},MOD(ROW()-2,5)+1)} -> Credit Card | M28: {=INDEX({"Retail","Corporate","Education","Small Business"},MOD(ROW()-2,4)+1)} -> Education
A29: ="CUST"&TEXT(ROW()-1,"0000") -> CUST0028 | B29: {=INDEX({"Aarav","Vivaan","Aditya","Arjun","Kabir","Rohan","Ananya","Diya","Ishita","Meera","Riya","Pooja","Neha","Kavya","Aisha","Priya","Rahul","Karan","Vikram","Sahil"},MOD(ROW()-2,20)+1)&" "&INDEX({"Shah","Patel","Mehta","Desai","Joshi","Gupta","Verma","Sharma","Trivedi","Rana","Mishra","Kapoor","Iyer","Nair","Singh"},MOD(INT((ROW()-2)/20),15)+1)} -> Diya Patel | C29: {=INDEX({"North","South","East","West","Central"},MOD(ROW()-2,5)+1)} -> East | D29: {=INDEX({"Electronics","Clothing","Furniture","Books","Office Supplies"},MOD(ROW()-2,5)+1)} -> Furniture | E29: =ROUND(500+MOD((ROW()-2)*137,44500),2) -> 4199 | F29: =MOD((ROW()-2)*7,11)+1 -> 3 | G29: =CHOOSE(MOD(ROW()-2,8)+1,0,0.02,0.05,0.08,0.1,0.12,0.15,0.2) -> 0.08 | H29: =DATE(2025,1,1)+MOD(ROW()-2,365) -> 45685 | I29: =ROUND(E29*F29*(1-G29),2) -> 11589.24 | J29: =ROUND(I29*(0.08+MOD(ROW()-2,12)*0.02),2) -> 1622.49 | K29: {=INDEX({"Amit","Neha","Riya","Karan","Pooja","Rahul","Meera","Vikram"},MOD(ROW()-2,8)+1)} -> Karan | L29: {=INDEX({"UPI","Credit Card","Debit Card","Cash","Net Banking"},MOD(ROW()-2,5)+1)} -> Debit Card | M29: {=INDEX({"Retail","Corporate","Education","Small Business"},MOD(ROW()-2,4)+1)} -> Small Business
A30: ="CUST"&TEXT(ROW()-1,"0000") -> CUST0029 | B30: {=INDEX({"Aarav","Vivaan","Aditya","Arjun","Kabir","Rohan","Ananya","Diya","Ishita","Meera","Riya","Pooja","Neha","Kavya","Aisha","Priya","Rahul","Karan","Vikram","Sahil"},MOD(ROW()-2,20)+1)&" "&INDEX({"Shah","Patel","Mehta","Desai","Joshi","Gupta","Verma","Sharma","Trivedi","Rana","Mishra","Kapoor","Iyer","Nair","Singh"},MOD(INT((ROW()-2)/20),15)+1)} -> Ishita Patel | C30: {=INDEX({"North","South","East","West","Central"},MOD(ROW()-2,5)+1)} -> West | D30: {=INDEX({"Electronics","Clothing","Furniture","Books","Office Supplies"},MOD(ROW()-2,5)+1)} -> Books | E30: =ROUND(500+MOD((ROW()-2)*137,44500),2) -> 4336 | F30: =MOD((ROW()-2)*7,11)+1 -> 10 | G30: =CHOOSE(MOD(ROW()-2,8)+1,0,0.02,0.05,0.08,0.1,0.12,0.15,0.2) -> 0.1 | H30: =DATE(2025,1,1)+MOD(ROW()-2,365) -> 45686 | I30: =ROUND(E30*F30*(1-G30),2) -> 39024 | J30: =ROUND(I30*(0.08+MOD(ROW()-2,12)*0.02),2) -> 6243.84 | K30: {=INDEX({"Amit","Neha","Riya","Karan","Pooja","Rahul","Meera","Vikram"},MOD(ROW()-2,8)+1)} -> Pooja | L30: {=INDEX({"UPI","Credit Card","Debit Card","Cash","Net Banking"},MOD(ROW()-2,5)+1)} -> Cash | M30: {=INDEX({"Retail","Corporate","Education","Small Business"},MOD(ROW()-2,4)+1)} -> Retail
A31: ="CUST"&TEXT(ROW()-1,"0000") -> CUST0030 | B31: {=INDEX({"Aarav","Vivaan","Aditya","Arjun","Kabir","Rohan","Ananya","Diya","Ishita","Meera","Riya","Pooja","Neha","Kavya","Aisha","Priya","Rahul","Karan","Vikram","Sahil"},MOD(ROW()-2,20)+1)&" "&INDEX({"Shah","Patel","Mehta","Desai","Joshi","Gupta","Verma","Sharma","Trivedi","Rana","Mishra","Kapoor","Iyer","Nair","Singh"},MOD(INT((ROW()-2)/20),15)+1)} -> Meera Patel | C31: {=INDEX({"North","South","East","West","Central"},MOD(ROW()-2,5)+1)} -> Central | D31: {=INDEX({"Electronics","Clothing","Furniture","Books","Office Supplies"},MOD(ROW()-2,5)+1)} -> Office Supplies | E31: =ROUND(500+MOD((ROW()-2)*137,44500),2) -> 4473 | F31: =MOD((ROW()-2)*7,11)+1 -> 6 | G31: =CHOOSE(MOD(ROW()-2,8)+1,0,0.02,0.05,0.08,0.1,0.12,0.15,0.2) -> 0.12 | H31: =DATE(2025,1,1)+MOD(ROW()-2,365) -> 45687 | I31: =ROUND(E31*F31*(1-G31),2) -> 23617.44 | J31: =ROUND(I31*(0.08+MOD(ROW()-2,12)*0.02),2) -> 4251.14 | K31: {=INDEX({"Amit","Neha","Riya","Karan","Pooja","Rahul","Meera","Vikram"},MOD(ROW()-2,8)+1)} -> Rahul | L31: {=INDEX({"UPI","Credit Card","Debit Card","Cash","Net Banking"},MOD(ROW()-2,5)+1)} -> Net Banking | M31: {=INDEX({"Retail","Corporate","Education","Small Business"},MOD(ROW()-2,4)+1)} -> Corporate
A32: ="CUST"&TEXT(ROW()-1,"0000") -> CUST0031 | B32: {=INDEX({"Aarav","Vivaan","Aditya","Arjun","Kabir","Rohan","Ananya","Diya","Ishita","Meera","Riya","Pooja","Neha","Kavya","Aisha","Priya","Rahul","Karan","Vikram","Sahil"},MOD(ROW()-2,20)+1)&" "&INDEX({"Shah","Patel","Mehta","Desai","Joshi","Gupta","Verma","Sharma","Trivedi","Rana","Mishra","Kapoor","Iyer","Nair","Singh"},MOD(INT((ROW()-2)/20),15)+1)} -> Riya Patel | C32: {=INDEX({"North","South","East","West","Central"},MOD(ROW()-2,5)+1)} -> North | D32: {=INDEX({"Electronics","Clothing","Furniture","Books","Office Supplies"},MOD(ROW()-2,5)+1)} -> Electronics | E32: =ROUND(500+MOD((ROW()-2)*137,44500),2) -> 4610 | F32: =MOD((ROW()-2)*7,11)+1 -> 2 | G32: =CHOOSE(MOD(ROW()-2,8)+1,0,0.02,0.05,0.08,0.1,0.12,0.15,0.2) -> 0.15 | H32: =DATE(2025,1,1)+MOD(ROW()-2,365) -> 45688 | I32: =ROUND(E32*F32*(1-G32),2) -> 7837 | J32: =ROUND(I32*(0.08+MOD(ROW()-2,12)*0.02),2) -> 1567.4 | K32: {=INDEX({"Amit","Neha","Riya","Karan","Pooja","Rahul","Meera","Vikram"},MOD(ROW()-2,8)+1)} -> Meera | L32: {=INDEX({"UPI","Credit Card","Debit Card","Cash","Net Banking"},MOD(ROW()-2,5)+1)} -> UPI | M32: {=INDEX({"Retail","Corporate","Education","Small Business"},MOD(ROW()-2,4)+1)} -> Education
A33: ="CUST"&TEXT(ROW()-1,"0000") -> CUST0032 | B33: {=INDEX({"Aarav","Vivaan","Aditya","Arjun","Kabir","Rohan","Ananya","Diya","Ishita","Meera","Riya","Pooja","Neha","Kavya","Aisha","Priya","Rahul","Karan","Vikram","Sahil"},MOD(ROW()-2,20)+1)&" "&INDEX({"Shah","Patel","Mehta","Desai","Joshi","Gupta","Verma","Sharma","Trivedi","Rana","Mishra","Kapoor","Iyer","Nair","Singh"},MOD(INT((ROW()-2)/20),15)+1)} -> Pooja Patel | C33: {=INDEX({"North","South","East","West","Central"},MOD(ROW()-2,5)+1)} -> South | D33: {=INDEX({"Electronics","Clothing","Furniture","Books","Office Supplies"},MOD(ROW()-2,5)+1)} -> Clothing | E33: =ROUND(500+MOD((ROW()-2)*137,44500),2) -> 4747 | F33: =MOD((ROW()-2)*7,11)+1 -> 9 | G33: =CHOOSE(MOD(ROW()-2,8)+1,0,0.02,0.05,0.08,0.1,0.12,0.15,0.2) -> 0.2 | H33: =DATE(2025,1,1)+MOD(ROW()-2,365) -> 45689 | I33: =ROUND(E33*F33*(1-G33),2) -> 34178.4 | J33: =ROUND(I33*(0.08+MOD(ROW()-2,12)*0.02),2) -> 7519.25 | K33: {=INDEX({"Amit","Neha","Riya","Karan","Pooja","Rahul","Meera","Vikram"},MOD(ROW()-2,8)+1)} -> Vikram | L33: {=INDEX({"UPI","Credit Card","Debit Card","Cash","Net Banking"},MOD(ROW()-2,5)+1)} -> Credit Card | M33: {=INDEX({"Retail","Corporate","Education","Small Business"},MOD(ROW()-2,4)+1)} -> Small Business
A34: ="CUST"&TEXT(ROW()-1,"0000") -> CUST0033 | B34: {=INDEX({"Aarav","Vivaan","Aditya","Arjun","Kabir","Rohan","Ananya","Diya","Ishita","Meera","Riya","Pooja","Neha","Kavya","Aisha","Priya","Rahul","Karan","Vikram","Sahil"},MOD(ROW()-2,20)+1)&" "&INDEX({"Shah","Patel","Mehta","Desai","Joshi","Gupta","Verma","Sharma","Trivedi","Rana","Mishra","Kapoor","Iyer","Nair","Singh"},MOD(INT((ROW()-2)/20),15)+1)} -> Neha Patel | C34: {=INDEX({"North","South","East","West","Central"},MOD(ROW()-2,5)+1)} -> East | D34: {=INDEX({"Electronics","Clothing","Furniture","Books","Office Supplies"},MOD(ROW()-2,5)+1)} -> Furniture | E34: =ROUND(500+MOD((ROW()-2)*137,44500),2) -> 4884 | F34: =MOD((ROW()-2)*7,11)+1 -> 5 | G34: =CHOOSE(MOD(ROW()-2,8)+1,0,0.02,0.05,0.08,0.1,0.12,0.15,0.2) -> 0 | H34: =DATE(2025,1,1)+MOD(ROW()-2,365) -> 45690 | I34: =ROUND(E34*F34*(1-G34),2) -> 24420 | J34: =ROUND(I34*(0.08+MOD(ROW()-2,12)*0.02),2) -> 5860.8 | K34: {=INDEX({"Amit","Neha","Riya","Karan","Pooja","Rahul","Meera","Vikram"},MOD(ROW()-2,8)+1)} -> Amit | L34: {=INDEX({"UPI","Credit Card","Debit Card","Cash","Net Banking"},MOD(ROW()-2,5)+1)} -> Debit Card | M34: {=INDEX({"Retail","Corporate","Education","Small Business"},MOD(ROW()-2,4)+1)} -> Retail
A35: ="CUST"&TEXT(ROW()-1,"0000") -> CUST0034 | B35: {=INDEX({"Aarav","Vivaan","Aditya","Arjun","Kabir","Rohan","Ananya","Diya","Ishita","Meera","Riya","Pooja","Neha","Kavya","Aisha","Priya","Rahul","Karan","Vikram","Sahil"},MOD(ROW()-2,20)+1)&" "&INDEX({"Shah","Patel","Mehta","Desai","Joshi","Gupta","Verma","Sharma","Trivedi","Rana","Mishra","Kapoor","Iyer","Nair","Singh"},MOD(INT((ROW()-2)/20),15)+1)} -> Kavya Patel | C35: {=INDEX({"North","South","East","West","Central"},MOD(ROW()-2,5)+1)} -> West | D35: {=INDEX({"Electronics","Clothing","Furniture","Books","Office Supplies"},MOD(ROW()-2,5)+1)} -> Books | E35: =ROUND(500+MOD((ROW()-2)*137,44500),2) -> 5021 | F35: =MOD((ROW()-2)*7,11)+1 -> 1 | G35: =CHOOSE(MOD(ROW()-2,8)+1,0,0.02,0.05,0.08,0.1,0.12,0.15,0.2) -> 0.02 | H35: =DATE(2025,1,1)+MOD(ROW()-2,365) -> 45691 | I35: =ROUND(E35*F35*(1-G35),2) -> 4920.58 | J35: =ROUND(I35*(0.08+MOD(ROW()-2,12)*0.02),2) -> 1279.35 | K35: {=INDEX({"Amit","Neha","Riya","Karan","Pooja","Rahul","Meera","Vikram"},MOD(ROW()-2,8)+1)} -> Neha | L35: {=INDEX({"UPI","Credit Card","Debit Card","Cash","Net Banking"},MOD(ROW()-2,5)+1)} -> Cash | M35: {=INDEX({"Retail","Corporate","Education","Small Business"},MOD(ROW()-2,4)+1)} -> Corporate
A36: ="CUST"&TEXT(ROW()-1,"0000") -> CUST0035 | B36: {=INDEX({"Aarav","Vivaan","Aditya","Arjun","Kabir","Rohan","Ananya","Diya","Ishita","Meera","Riya","Pooja","Neha","Kavya","Aisha","Priya","Rahul","Karan","Vikram","Sahil"},MOD(ROW()-2,20)+1)&" "&INDEX({"Shah","Patel","Mehta","Desai","Joshi","Gupta","Verma","Sharma","Trivedi","Rana","Mishra","Kapoor","Iyer","Nair","Singh"},MOD(INT((ROW()-2)/20),15)+1)} -> Aisha Patel | C36: {=INDEX({"North","South","East","West","Central"},MOD(ROW()-2,5)+1)} -> Central | D36: {=INDEX({"Electronics","Clothing","Furniture","Books","Office Supplies"},MOD(ROW()-2,5)+1)} -> Office Supplies | E36: =ROUND(500+MOD((ROW()-2)*137,44500),2) -> 5158 | F36: =MOD((ROW()-2)*7,11)+1 -> 8 | G36: =CHOOSE(MOD(ROW()-2,8)+1,0,0.02,0.05,0.08,0.1,0.12,0.15,0.2) -> 0.05 | H36: =DATE(2025,1,1)+MOD(ROW()-2,365) -> 45692 | I36: =ROUND(E36*F36*(1-G36),2) -> 39200.8 | J36: =ROUND(I36*(0.08+MOD(ROW()-2,12)*0.02),2) -> 10976.22 | K36: {=INDEX({"Amit","Neha","Riya","Karan","Pooja","Rahul","Meera","Vikram"},MOD(ROW()-2,8)+1)} -> Riya | L36: {=INDEX({"UPI","Credit Card","Debit Card","Cash","Net Banking"},MOD(ROW()-2,5)+1)} -> Net Banking | M36: {=INDEX({"Retail","Corporate","Education","Small Business"},MOD(ROW()-2,4)+1)} -> Education
A37: ="CUST"&TEXT(ROW()-1,"0000") -> CUST0036 | B37: {=INDEX({"Aarav","Vivaan","Aditya","Arjun","Kabir","Rohan","Ananya","Diya","Ishita","Meera","Riya","Pooja","Neha","Kavya","Aisha","Priya","Rahul","Karan","Vikram","Sahil"},MOD(ROW()-2,20)+1)&" "&INDEX({"Shah","Patel","Mehta","Desai","Joshi","Gupta","Verma","Sharma","Trivedi","Rana","Mishra","Kapoor","Iyer","Nair","Singh"},MOD(INT((ROW()-2)/20),15)+1)} -> Priya Patel | C37: {=INDEX({"North","South","East","West","Central"},MOD(ROW()-2,5)+1)} -> North | D37: {=INDEX({"Electronics","Clothing","Furniture","Books","Office Supplies"},MOD(ROW()-2,5)+1)} -> Electronics | E37: =ROUND(500+MOD((ROW()-2)*137,44500),2) -> 5295 | F37: =MOD((ROW()-2)*7,11)+1 -> 4 | G37: =CHOOSE(MOD(ROW()-2,8)+1,0,0.02,0.05,0.08,0.1,0.12,0.15,0.2) -> 0.08 | H37: =DATE(2025,1,1)+MOD(ROW()-2,365) -> 45693 | I37: =ROUND(E37*F37*(1-G37),2) -> 19485.6 | J37: =ROUND(I37*(0.08+MOD(ROW()-2,12)*0.02),2) -> 5845.68 | K37: {=INDEX({"Amit","Neha","Riya","Karan","Pooja","Rahul","Meera","Vikram"},MOD(ROW()-2,8)+1)} -> Karan | L37: {=INDEX({"UPI","Credit Card","Debit Card","Cash","Net Banking"},MOD(ROW()-2,5)+1)} -> UPI | M37: {=INDEX({"Retail","Corporate","Education","Small Business"},MOD(ROW()-2,4)+1)} -> Small Business
... A51: ="CUST"&TEXT(ROW()-1,"0000") -> CUST0050 | B51: {=INDEX({"Aarav","Vivaan","Aditya","Arjun","Kabir","Rohan","Ananya","Diya","Ishita","Meera","Riya","Pooja","Neha","Kavya","Aisha","Priya","Rahul","Karan","Vikram","Sahil"},MOD(ROW()-2,20)+1)&" "&INDEX({"Shah","Patel","Mehta","Desai","Joshi","Gupta","Verma","Sharma","Trivedi","Rana","Mishra","Kapoor","Iyer","Nair","Singh"},MOD(INT((ROW()-2)/20),15)+1)} -> Meera Mehta | C51: {=INDEX({"North","South","East","West","Central"},MOD(ROW()-2,5)+1)} -> Central | D51: {=INDEX({"Electronics","Clothing","Furniture","Books","Office Supplies"},MOD(ROW()-2,5)+1)} -> Office Supplies | E51: =ROUND(500+MOD((ROW()-2)*137,44500),2) -> 7213 | F51: =MOD((ROW()-2)*7,11)+1 -> 3 | G51: =CHOOSE(MOD(ROW()-2,8)+1,0,0.02,0.05,0.08,0.1,0.12,0.15,0.2) -> 0.02 | H51: =DATE(2025,1,1)+MOD(ROW()-2,365) -> 45707 | I51: =ROUND(E51*F51*(1-G51),2) -> 21206.22 | J51: =ROUND(I51*(0.08+MOD(ROW()-2,12)*0.02),2) -> 2120.62 | K51: {=INDEX({"Amit","Neha","Riya","Karan","Pooja","Rahul","Meera","Vikram"},MOD(ROW()-2,8)+1)} -> Neha | L51: {=INDEX({"UPI","Credit Card","Debit Card","Cash","Net Banking"},MOD(ROW()-2,5)+1)} -> Net Banking | M51: {=INDEX({"Retail","Corporate","Education","Small Business"},MOD(ROW()-2,4)+1)} -> Corporate
A52: ="CUST"&TEXT(ROW()-1,"0000") -> CUST0051 | B52: Rahul Desai | C52: {=INDEX({"North","South","East","West","Central"},MOD(ROW()-2,5)+1)} -> North | D52: {=INDEX({"Electronics","Clothing","Furniture","Books","Office Supplies"},MOD(ROW()-2,5)+1)} -> Electronics | E52: =ROUND(500+MOD((ROW()-2)*137,44500),2) -> 7350 | F52: =MOD((ROW()-2)*7,11)+1 -> 10 | G52: =CHOOSE(MOD(ROW()-2,8)+1,0,0.02,0.05,0.08,0.1,0.12,0.15,0.2) -> 0.05 | H52: =DATE(2025,1,1)+MOD(ROW()-2,365) -> 45708 | I52: =ROUND(E52*F52*(1-G52),2) -> 69825 | J52: =ROUND(I52*(0.08+MOD(ROW()-2,12)*0.02),2) -> 8379 | K52: {=INDEX({"Amit","Neha","Riya","Karan","Pooja","Rahul","Meera","Vikram"},MOD(ROW()-2,8)+1)} -> Riya | L52: {=INDEX({"UPI","Credit Card","Debit Card","Cash","Net Banking"},MOD(ROW()-2,5)+1)} -> UPI | M52: {=INDEX({"Retail","Corporate","Education","Small Business"},MOD(ROW()-2,4)+1)} -> Education
A53: ="CUST"&TEXT(ROW()-1,"0000") -> CUST0052 | B53: {=INDEX({"Aarav","Vivaan","Aditya","Arjun","Kabir","Rohan","Ananya","Diya","Ishita","Meera","Riya","Pooja","Neha","Kavya","Aisha","Priya","Rahul","Karan","Vikram","Sahil"},MOD(ROW()-2,20)+1)&" "&INDEX({"Shah","Patel","Mehta","Desai","Joshi","Gupta","Verma","Sharma","Trivedi","Rana","Mishra","Kapoor","Iyer","Nair","Singh"},MOD(INT((ROW()-2)/20),15)+1)} -> Pooja Mehta | C53: {=INDEX({"North","South","East","West","Central"},MOD(ROW()-2,5)+1)} -> South | D53: {=INDEX({"Electronics","Clothing","Furniture","Books","Office Supplies"},MOD(ROW()-2,5)+1)} -> Clothing | E53: =ROUND(500+MOD((ROW()-2)*137,44500),2) -> 7487 | F53: =MOD((ROW()-2)*7,11)+1 -> 6 | G53: =CHOOSE(MOD(ROW()-2,8)+1,0,0.02,0.05,0.08,0.1,0.12,0.15,0.2) -> 0.08 | H53: =DATE(2025,1,1)+MOD(ROW()-2,365) -> 45709 | I53: =ROUND(E53*F53*(1-G53),2) -> 41328.24 | J53: =ROUND(I53*(0.08+MOD(ROW()-2,12)*0.02),2) -> 5785.95 | K53: {=INDEX({"Amit","Neha","Riya","Karan","Pooja","Rahul","Meera","Vikram"},MOD(ROW()-2,8)+1)} -> Karan | L53: {=INDEX({"UPI","Credit Card","Debit Card","Cash","Net Banking"},MOD(ROW()-2,5)+1)} -> Credit Card | M53: {=INDEX({"Retail","Corporate","Education","Small Business"},MOD(ROW()-2,4)+1)} -> Small Business
A54: ="CUST"&TEXT(ROW()-1,"0000") -> CUST0053 | B54: {=INDEX({"Aarav","Vivaan","Aditya","Arjun","Kabir","Rohan","Ananya","Diya","Ishita","Meera","Riya","Pooja","Neha","Kavya","Aisha","Priya","Rahul","Karan","Vikram","Sahil"},MOD(ROW()-2,20)+1)&" "&INDEX({"Shah","Patel","Mehta","Desai","Joshi","Gupta","Verma","Sharma","Trivedi","Rana","Mishra","Kapoor","Iyer","Nair","Singh"},MOD(INT((ROW()-2)/20),15)+1)} -> Neha Mehta | C54: {=INDEX({"North","South","East","West","Central"},MOD(ROW()-2,5)+1)} -> East | D54: {=INDEX({"Electronics","Clothing","Furniture","Books","Office Supplies"},MOD(ROW()-2,5)+1)} -> Furniture | E54: =ROUND(500+MOD((ROW()-2)*137,44500),2) -> 7624 | F54: =MOD((ROW()-2)*7,11)+1 -> 2 | G54: =CHOOSE(MOD(ROW()-2,8)+1,0,0.02,0.05,0.08,0.1,0.12,0.15,0.2) -> 0.1 | H54: =DATE(2025,1,1)+MOD(ROW()-2,365) -> 45710 | I54: =ROUND(E54*F54*(1-G54),2) -> 13723.2 | J54: =ROUND(I54*(0.08+MOD(ROW()-2,12)*0.02),2) -> 2195.71 | K54: {=INDEX({"Amit","Neha","Riya","Karan","Pooja","Rahul","Meera","Vikram"},MOD(ROW()-2,8)+1)} -> Pooja | L54: {=INDEX({"UPI","Credit Card","Debit Card","Cash","Net Banking"},MOD(ROW()-2,5)+1)} -> Debit Card | M54: {=INDEX({"Retail","Corporate","Education","Small Business"},MOD(ROW()-2,4)+1)} -> Retail
A55: ="CUST"&TEXT(ROW()-1,"0000") -> CUST0054 | B55: {=INDEX({"Aarav","Vivaan","Aditya","Arjun","Kabir","Rohan","Ananya","Diya","Ishita","Meera","Riya","Pooja","Neha","Kavya","Aisha","Priya","Rahul","Karan","Vikram","Sahil"},MOD(ROW()-2,20)+1)&" "&INDEX({"Shah","Patel","Mehta","Desai","Joshi","Gupta","Verma","Sharma","Trivedi","Rana","Mishra","Kapoor","Iyer","Nair","Singh"},MOD(INT((ROW()-2)/20),15)+1)} -> Kavya Mehta | C55: {=INDEX({"North","South","East","West","Central"},MOD(ROW()-2,5)+1)} -> West | D55: {=INDEX({"Electronics","Clothing","Furniture","Books","Office Supplies"},MOD(ROW()-2,5)+1)} -> Books | E55: =ROUND(500+MOD((ROW()-2)*137,44500),2) -> 7761 | F55: =MOD((ROW()-2)*7,11)+1 -> 9 | G55: =CHOOSE(MOD(ROW()-2,8)+1,0,0.02,0.05,0.08,0.1,0.12,0.15,0.2) -> 0.12 | H55: =DATE(2025,1,1)+MOD(ROW()-2,365) -> 45711 | I55: =ROUND(E55*F55*(1-G55),2) -> 61467.12 | J55: =ROUND(I55*(0.08+MOD(ROW()-2,12)*0.02),2) -> 11064.08 | K55: {=INDEX({"Amit","Neha","Riya","Karan","Pooja","Rahul","Meera","Vikram"},MOD(ROW()-2,8)+1)} -> Rahul | L55: {=INDEX({"UPI","Credit Card","Debit Card","Cash","Net Banking"},MOD(ROW()-2,5)+1)} -> Cash | M55: {=INDEX({"Retail","Corporate","Education","Small Business"},MOD(ROW()-2,4)+1)} -> Corporate
A56: ="CUST"&TEXT(ROW()-1,"0000") -> CUST0055 | B56: {=INDEX({"Aarav","Vivaan","Aditya","Arjun","Kabir","Rohan","Ananya","Diya","Ishita","Meera","Riya","Pooja","Neha","Kavya","Aisha","Priya","Rahul","Karan","Vikram","Sahil"},MOD(ROW()-2,20)+1)&" "&INDEX({"Shah","Patel","Mehta","Desai","Joshi","Gupta","Verma","Sharma","Trivedi","Rana","Mishra","Kapoor","Iyer","Nair","Singh"},MOD(INT((ROW()-2)/20),15)+1)} -> Aisha Mehta | C56: {=INDEX({"North","South","East","West","Central"},MOD(ROW()-2,5)+1)} -> Central | D56: {=INDEX({"Electronics","Clothing","Furniture","Books","Office Supplies"},MOD(ROW()-2,5)+1)} -> Office Supplies | E56: =ROUND(500+MOD((ROW()-2)*137,44500),2) -> 7898 | F56: =MOD((ROW()-2)*7,11)+1 -> 5 | G56: =CHOOSE(MOD(ROW()-2,8)+1,0,0.02,0.05,0.08,0.1,0.12,0.15,0.2) -> 0.15 | H56: =DATE(2025,1,1)+MOD(ROW()-2,365) -> 45712 | I56: =ROUND(E56*F56*(1-G56),2) -> 33566.5 | J56: =ROUND(I56*(0.08+MOD(ROW()-2,12)*0.02),2) -> 6713.3 | K56: {=INDEX({"Amit","Neha","Riya","Karan","Pooja","Rahul","Meera","Vikram"},MOD(ROW()-2,8)+1)} -> Meera | L56: {=INDEX({"UPI","Credit Card","Debit Card","Cash","Net Banking"},MOD(ROW()-2,5)+1)} -> Net Banking | M56: {=INDEX({"Retail","Corporate","Education","Small Business"},MOD(ROW()-2,4)+1)} -> Education
A57: ="CUST"&TEXT(ROW()-1,"0000") -> CUST0056 | B57: {=INDEX({"Aarav","Vivaan","Aditya","Arjun","Kabir","Rohan","Ananya","Diya","Ishita","Meera","Riya","Pooja","Neha","Kavya","Aisha","Priya","Rahul","Karan","Vikram","Sahil"},MOD(ROW()-2,20)+1)&" "&INDEX({"Shah","Patel","Mehta","Desai","Joshi","Gupta","Verma","Sharma","Trivedi","Rana","Mishra","Kapoor","Iyer","Nair","Singh"},MOD(INT((ROW()-2)/20),15)+1)} -> Priya Mehta | C57: {=INDEX({"North","South","East","West","Central"},MOD(ROW()-2,5)+1)} -> North | D57: {=INDEX({"Electronics","Clothing","Furniture","Books","Office Supplies"},MOD(ROW()-2,5)+1)} -> Electronics | E57: =ROUND(500+MOD((ROW()-2)*137,44500),2) -> 8035 | F57: =MOD((ROW()-2)*7,11)+1 -> 1 | G57: =CHOOSE(MOD(ROW()-2,8)+1,0,0.02,0.05,0.08,0.1,0.12,0.15,0.2) -> 0.2 | H57: =DATE(2025,1,1)+MOD(ROW()-2,365) -> 45713 | I57: =ROUND(E57*F57*(1-G57),2) -> 6428 | J57: =ROUND(I57*(0.08+MOD(ROW()-2,12)*0.02),2) -> 1414.16 | K57: {=INDEX({"Amit","Neha","Riya","Karan","Pooja","Rahul","Meera","Vikram"},MOD(ROW()-2,8)+1)} -> Vikram | L57: {=INDEX({"UPI","Credit Card","Debit Card","Cash","Net Banking"},MOD(ROW()-2,5)+1)} -> UPI | M57: {=INDEX({"Retail","Corporate","Education","Small Business"},MOD(ROW()-2,4)+1)} -> Small Business
A58: ="CUST"&TEXT(ROW()-1,"0000") -> CUST0057 | B58: {=INDEX({"Aarav","Vivaan","Aditya","Arjun","Kabir","Rohan","Ananya","Diya","Ishita","Meera","Riya","Pooja","Neha","Kavya","Aisha","Priya","Rahul","Karan","Vikram","Sahil"},MOD(ROW()-2,20)+1)&" "&INDEX({"Shah","Patel","Mehta","Desai","Joshi","Gupta","Verma","Sharma","Trivedi","Rana","Mishra","Kapoor","Iyer","Nair","Singh"},MOD(INT((ROW()-2)/20),15)+1)} -> Rahul Mehta | C58: {=INDEX({"North","South","East","West","Central"},MOD(ROW()-2,5)+1)} -> South | D58: {=INDEX({"Electronics","Clothing","Furniture","Books","Office Supplies"},MOD(ROW()-2,5)+1)} -> Clothing | E58: =ROUND(500+MOD((ROW()-2)*137,44500),2) -> 8172 | F58: =MOD((ROW()-2)*7,11)+1 -> 8 | G58: =CHOOSE(MOD(ROW()-2,8)+1,0,0.02,0.05,0.08,0.1,0.12,0.15,0.2) -> 0 | H58: =DATE(2025,1,1)+MOD(ROW()-2,365) -> 45714 | I58: =ROUND(E58*F58*(1-G58),2) -> 65376 | J58: =ROUND(I58*(0.08+MOD(ROW()-2,12)*0.02),2) -> 15690.24 | K58: {=INDEX({"Amit","Neha","Riya","Karan","Pooja","Rahul","Meera","Vikram"},MOD(ROW()-2,8)+1)} -> Amit | L58: {=INDEX({"UPI","Credit Card","Debit Card","Cash","Net Banking"},MOD(ROW()-2,5)+1)} -> Credit Card | M58: {=INDEX({"Retail","Corporate","Education","Small Business"},MOD(ROW()-2,4)+1)} -> Retail
A59: ="CUST"&TEXT(ROW()-1,"0000") -> CUST0058 | B59: {=INDEX({"Aarav","Vivaan","Aditya","Arjun","Kabir","Rohan","Ananya","Diya","Ishita","Meera","Riya","Pooja","Neha","Kavya","Aisha","Priya","Rahul","Karan","Vikram","Sahil"},MOD(ROW()-2,20)+1)&" "&INDEX({"Shah","Patel","Mehta","Desai","Joshi","Gupta","Verma","Sharma","Trivedi","Rana","Mishra","Kapoor","Iyer","Nair","Singh"},MOD(INT((ROW()-2)/20),15)+1)} -> Karan Mehta | C59: {=INDEX({"North","South","East","West","Central"},MOD(ROW()-2,5)+1)} -> East | D59: {=INDEX({"Electronics","Clothing","Furniture","Books","Office Supplies"},MOD(ROW()-2,5)+1)} -> Furniture | E59: =ROUND(500+MOD((ROW()-2)*137,44500),2) -> 8309 | F59: =MOD((ROW()-2)*7,11)+1 -> 4 | G59: =CHOOSE(MOD(ROW()-2,8)+1,0,0.02,0.05,0.08,0.1,0.12,0.15,0.2) -> 0.02 | H59: =DATE(2025,1,1)+MOD(ROW()-2,365) -> 45715 | I59: =ROUND(E59*F59*(1-G59),2) -> 32571.28 | J59: =ROUND(I59*(0.08+MOD(ROW()-2,12)*0.02),2) -> 8468.53 | K59: {=INDEX({"Amit","Neha","Riya","Karan","Pooja","Rahul","Meera","Vikram"},MOD(ROW()-2,8)+1)} -> Neha | L59: {=INDEX({"UPI","Credit Card","Debit Card","Cash","Net Banking"},MOD(ROW()-2,5)+1)} -> Debit Card | M59: {=INDEX({"Retail","Corporate","Education","Small Business"},MOD(ROW()-2,4)+1)} -> Corporate
A60: ="CUST"&TEXT(ROW()-1,"0000") -> CUST0059 | B60: {=INDEX({"Aarav","Vivaan","Aditya","Arjun","Kabir","Rohan","Ananya","Diya","Ishita","Meera","Riya","Pooja","Neha","Kavya","Aisha","Priya","Rahul","Karan","Vikram","Sahil"},MOD(ROW()-2,20)+1)&" "&INDEX({"Shah","Patel","Mehta","Desai","Joshi","Gupta","Verma","Sharma","Trivedi","Rana","Mishra","Kapoor","Iyer","Nair","Singh"},MOD(INT((ROW()-2)/20),15)+1)} -> Vikram Mehta | C60: {=INDEX({"North","South","East","West","Central"},MOD(ROW()-2,5)+1)} -> West | D60: {=INDEX({"Electronics","Clothing","Furniture","Books","Office Supplies"},MOD(ROW()-2,5)+1)} -> Books | E60: =ROUND(500+MOD((ROW()-2)*137,44500),2) -> 8446 | F60: =MOD((ROW()-2)*7,11)+1 -> 11 | G60: =CHOOSE(MOD(ROW()-2,8)+1,0,0.02,0.05,0.08,0.1,0.12,0.15,0.2) -> 0.05 | H60: =DATE(2025,1,1)+MOD(ROW()-2,365) -> 45716 | I60: =ROUND(E60*F60*(1-G60),2) -> 88260.7 | J60: =ROUND(I60*(0.08+MOD(ROW()-2,12)*0.02),2) -> 24713 | K60: {=INDEX({"Amit","Neha","Riya","Karan","Pooja","Rahul","Meera","Vikram"},MOD(ROW()-2,8)+1)} -> Riya | L60: {=INDEX({"UPI","Credit Card","Debit Card","Cash","Net Banking"},MOD(ROW()-2,5)+1)} -> Cash | M60: {=INDEX({"Retail","Corporate","Education","Small Business"},MOD(ROW()-2,4)+1)} -> Education
A61: ="CUST"&TEXT(ROW()-1,"0000") -> CUST0060 | B61: {=INDEX({"Aarav","Vivaan","Aditya","Arjun","Kabir","Rohan","Ananya","Diya","Ishita","Meera","Riya","Pooja","Neha","Kavya","Aisha","Priya","Rahul","Karan","Vikram","Sahil"},MOD(ROW()-2,20)+1)&" "&INDEX({"Shah","Patel","Mehta","Desai","Joshi","Gupta","Verma","Sharma","Trivedi","Rana","Mishra","Kapoor","Iyer","Nair","Singh"},MOD(INT((ROW()-2)/20),15)+1)} -> Sahil Mehta | C61: {=INDEX({"North","South","East","West","Central"},MOD(ROW()-2,5)+1)} -> Central | D61: {=INDEX({"Electronics","Clothing","Furniture","Books","Office Supplies"},MOD(ROW()-2,5)+1)} -> Office Supplies | E61: =ROUND(500+MOD((ROW()-2)*137,44500),2) -> 8583 | F61: =MOD((ROW()-2)*7,11)+1 -> 7 | G61: 0.08 | H61: =DATE(2025,1,1)+MOD(ROW()-2,365) -> 45717 | I61: =ROUND(E61*F61*(1-G61),2) -> 55274.52 | J61: =ROUND(I61*(0.08+MOD(ROW()-2,12)*0.02),2) -> 16582.36 | K61: {=INDEX({"Amit","Neha","Riya","Karan","Pooja","Rahul","Meera","Vikram"},MOD(ROW()-2,8)+1)} -> Karan | L61: {=INDEX({"UPI","Credit Card","Debit Card","Cash","Net Banking"},MOD(ROW()-2,5)+1)} -> Net Banking | M61: {=INDEX({"Retail","Corporate","Education","Small Business"},MOD(ROW()-2,4)+1)} -> Small Business
A62: ="CUST"&TEXT(ROW()-1,"0000") -> CUST0061 | B62: {=INDEX({"Aarav","Vivaan","Aditya","Arjun","Kabir","Rohan","Ananya","Diya","Ishita","Meera","Riya","Pooja","Neha","Kavya","Aisha","Priya","Rahul","Karan","Vikram","Sahil"},MOD(ROW()-2,20)+1)&" "&INDEX({"Shah","Patel","Mehta","Desai","Joshi","Gupta","Verma","Sharma","Trivedi","Rana","Mishra","Kapoor","Iyer","Nair","Singh"},MOD(INT((ROW()-2)/20),15)+1)} -> Aarav Desai | C62: {=INDEX({"North","South","East","West","Central"},MOD(ROW()-2,5)+1)} -> North | D62: {=INDEX({"Electronics","Clothing","Furniture","Books","Office Supplies"},MOD(ROW()-2,5)+1)} -> Electronics | E62: =ROUND(500+MOD((ROW()-2)*137,44500),2) -> 8720 | F62: =MOD((ROW()-2)*7,11)+1 -> 3 | G62: =CHOOSE(MOD(ROW()-2,8)+1,0,0.02,0.05,0.08,0.1,0.12,0.15,0.2) -> 0.1 | H62: =DATE(2025,1,1)+MOD(ROW()-2,365) -> 45718 | I62: =ROUND(E62*F62*(1-G62),2) -> 23544 | J62: =ROUND(I62*(0.08+MOD(ROW()-2,12)*0.02),2) -> 1883.52 | K62: {=INDEX({"Amit","Neha","Riya","Karan","Pooja","Rahul","Meera","Vikram"},MOD(ROW()-2,8)+1)} -> Pooja | L62: {=INDEX({"UPI","Credit Card","Debit Card","Cash","Net Banking"},MOD(ROW()-2,5)+1)} -> UPI | M62: {=INDEX({"Retail","Corporate","Education","Small Business"},MOD(ROW()-2,4)+1)} -> Retail
A63: ="CUST"&TEXT(ROW()-1,"0000") -> CUST0062 | B63: {=INDEX({"Aarav","Vivaan","Aditya","Arjun","Kabir","Rohan","Ananya","Diya","Ishita","Meera","Riya","Pooja","Neha","Kavya","Aisha","Priya","Rahul","Karan","Vikram","Sahil"},MOD(ROW()-2,20)+1)&" "&INDEX({"Shah","Patel","Mehta","Desai","Joshi","Gupta","Verma","Sharma","Trivedi","Rana","Mishra","Kapoor","Iyer","Nair","Singh"},MOD(INT((ROW()-2)/20),15)+1)} -> Vivaan Desai | C63: {=INDEX({"North","South","East","West","Central"},MOD(ROW()-2,5)+1)} -> South | D63: {=INDEX({"Electronics","Clothing","Furniture","Books","Office Supplies"},MOD(ROW()-2,5)+1)} -> Clothing | E63: =ROUND(500+MOD((ROW()-2)*137,44500),2) -> 8857 | F63: =MOD((ROW()-2)*7,11)+1 -> 10 | G63: =CHOOSE(MOD(ROW()-2,8)+1,0,0.02,0.05,0.08,0.1,0.12,0.15,0.2) -> 0.12 | H63: =DATE(2025,1,1)+MOD(ROW()-2,365) -> 45719 | I63: =ROUND(E63*F63*(1-G63),2) -> 77941.6 | J63: =ROUND(I63*(0.08+MOD(ROW()-2,12)*0.02),2) -> 7794.16 | K63: {=INDEX({"Amit","Neha","Riya","Karan","Pooja","Rahul","Meera","Vikram"},MOD(ROW()-2,8)+1)} -> Rahul | L63: {=INDEX({"UPI","Credit Card","Debit Card","Cash","Net Banking"},MOD(ROW()-2,5)+1)} -> Credit Card | M63: {=INDEX({"Retail","Corporate","Education","Small Business"},MOD(ROW()-2,4)+1)} -> Corporate
A64: ="CUST"&TEXT(ROW()-1,"0000") -> CUST0063 | B64: {=INDEX({"Aarav","Vivaan","Aditya","Arjun","Kabir","Rohan","Ananya","Diya","Ishita","Meera","Riya","Pooja","Neha","Kavya","Aisha","Priya","Rahul","Karan","Vikram","Sahil"},MOD(ROW()-2,20)+1)&" "&INDEX({"Shah","Patel","Mehta","Desai","Joshi","Gupta","Verma","Sharma","Trivedi","Rana","Mishra","Kapoor","Iyer","Nair","Singh"},MOD(INT((ROW()-2)/20),15)+1)} -> Aditya Desai | C64: {=INDEX({"North","South","East","West","Central"},MOD(ROW()-2,5)+1)} -> East | D64: {=INDEX({"Electronics","Clothing","Furniture","Books","Office Supplies"},MOD(ROW()-2,5)+1)} -> Furniture | E64: =ROUND(500+MOD((ROW()-2)*137,44500),2) -> 8994 | F64: =MOD((ROW()-2)*7,11)+1 -> 6 | G64: =CHOOSE(MOD(ROW()-2,8)+1,0,0.02,0.05,0.08,0.1,0.12,0.15,0.2) -> 0.15 | H64: =DATE(2025,1,1)+MOD(ROW()-2,365) -> 45720 | I64: =ROUND(E64*F64*(1-G64),2) -> 45869.4 | J64: =ROUND(I64*(0.08+MOD(ROW()-2,12)*0.02),2) -> 5504.33 | K64: {=INDEX({"Amit","Neha","Riya","Karan","Pooja","Rahul","Meera","Vikram"},MOD(ROW()-2,8)+1)} -> Meera | L64: {=INDEX({"UPI","Credit Card","Debit Card","Cash","Net Banking"},MOD(ROW()-2,5)+1)} -> Debit Card | M64: {=INDEX({"Retail","Corporate","Education","Small Business"},MOD(ROW()-2,4)+1)} -> Education
A65: ="CUST"&TEXT(ROW()-1,"0000") -> CUST0064 | B65: {=INDEX({"Aarav","Vivaan","Aditya","Arjun","Kabir","Rohan","Ananya","Diya","Ishita","Meera","Riya","Pooja","Neha","Kavya","Aisha","Priya","Rahul","Karan","Vikram","Sahil"},MOD(ROW()-2,20)+1)&" "&INDEX({"Shah","Patel","Mehta","Desai","Joshi","Gupta","Verma","Sharma","Trivedi","Rana","Mishra","Kapoor","Iyer","Nair","Singh"},MOD(INT((ROW()-2)/20),15)+1)} -> Arjun Desai | C65: {=INDEX({"North","South","East","West","Central"},MOD(ROW()-2,5)+1)} -> West | D65: {=INDEX({"Electronics","Clothing","Furniture","Books","Office Supplies"},MOD(ROW()-2,5)+1)} -> Books | E65: =ROUND(500+MOD((ROW()-2)*137,44500),2) -> 9131 | F65: =MOD((ROW()-2)*7,11)+1 -> 2 | G65: =CHOOSE(MOD(ROW()-2,8)+1,0,0.02,0.05,0.08,0.1,0.12,0.15,0.2) -> 0.2 | H65: =DATE(2025,1,1)+MOD(ROW()-2,365) -> 45721 | I65: =ROUND(E65*F65*(1-G65),2) -> 14609.6 | J65: =ROUND(I65*(0.08+MOD(ROW()-2,12)*0.02),2) -> 2045.34 | K65: {=INDEX({"Amit","Neha","Riya","Karan","Pooja","Rahul","Meera","Vikram"},MOD(ROW()-2,8)+1)} -> Vikram | L65: {=INDEX({"UPI","Credit Card","Debit Card","Cash","Net Banking"},MOD(ROW()-2,5)+1)} -> Cash | M65: {=INDEX({"Retail","Corporate","Education","Small Business"},MOD(ROW()-2,4)+1)} -> Small Business
A66: ="CUST"&TEXT(ROW()-1,"0000") -> CUST0065 | B66: {=INDEX({"Aarav","Vivaan","Aditya","Arjun","Kabir","Rohan","Ananya","Diya","Ishita","Meera","Riya","Pooja","Neha","Kavya","Aisha","Priya","Rahul","Karan","Vikram","Sahil"},MOD(ROW()-2,20)+1)&" "&INDEX({"Shah","Patel","Mehta","Desai","Joshi","Gupta","Verma","Sharma","Trivedi","Rana","Mishra","Kapoor","Iyer","Nair","Singh"},MOD(INT((ROW()-2)/20),15)+1)} -> Kabir Desai | C66: {=INDEX({"North","South","East","West","Central"},MOD(ROW()-2,5)+1)} -> Central | D66: {=INDEX({"Electronics","Clothing","Furniture","Books","Office Supplies"},MOD(ROW()-2,5)+1)} -> Office Supplies | E66: =ROUND(500+MOD((ROW()-2)*137,44500),2) -> 9268 | F66: =MOD((ROW()-2)*7,11)+1 -> 9 | G66: =CHOOSE(MOD(ROW()-2,8)+1,0,0.02,0.05,0.08,0.1,0.12,0.15,0.2) -> 0 | H66: =DATE(2025,1,1)+MOD(ROW()-2,365) -> 45722 | I66: =ROUND(E66*F66*(1-G66),2) -> 83412 | J66: =ROUND(I66*(0.08+MOD(ROW()-2,12)*0.02),2) -> 13345.92 | K66: {=INDEX({"Amit","Neha","Riya","Karan","Pooja","Rahul","Meera","Vikram"},MOD(ROW()-2,8)+1)} -> Amit | L66: {=INDEX({"UPI","Credit Card","Debit Card","Cash","Net Banking"},MOD(ROW()-2,5)+1)} -> Net Banking | M66: {=INDEX({"Retail","Corporate","Education","Small Business"},MOD(ROW()-2,4)+1)} -> Retail
A67: ="CUST"&TEXT(ROW()-1,"0000") -> CUST0066 | B67: {=INDEX({"Aarav","Vivaan","Aditya","Arjun","Kabir","Rohan","Ananya","Diya","Ishita","Meera","Riya","Pooja","Neha","Kavya","Aisha","Priya","Rahul","Karan","Vikram","Sahil"},MOD(ROW()-2,20)+1)&" "&INDEX({"Shah","Patel","Mehta","Desai","Joshi","Gupta","Verma","Sharma","Trivedi","Rana","Mishra","Kapoor","Iyer","Nair","Singh"},MOD(INT((ROW()-2)/20),15)+1)} -> Rohan Desai | C67: {=INDEX({"North","South","East","West","Central"},MOD(ROW()-2,5)+1)} -> North | D67: {=INDEX({"Electronics","Clothing","Furniture","Books","Office Supplies"},MOD(ROW()-2,5)+1)} -> Electronics | E67: =ROUND(500+MOD((ROW()-2)*137,44500),2) -> 9405 | F67: =MOD((ROW()-2)*7,11)+1 -> 5 | G67: =CHOOSE(MOD(ROW()-2,8)+1,0,0.02,0.05,0.08,0.1,0.12,0.15,0.2) -> 0.02 | H67: =DATE(2025,1,1)+MOD(ROW()-2,365) -> 45723 | I67: =ROUND(E67*F67*(1-G67),2) -> 46084.5 | J67: =ROUND(I67*(0.08+MOD(ROW()-2,12)*0.02),2) -> 8295.21 | K67: {=INDEX({"Amit","Neha","Riya","Karan","Pooja","Rahul","Meera","Vikram"},MOD(ROW()-2,8)+1)} -> Neha | L67: {=INDEX({"UPI","Credit Card","Debit Card","Cash","Net Banking"},MOD(ROW()-2,5)+1)} -> UPI | M67: {=INDEX({"Retail","Corporate","Education","Small Business"},MOD(ROW()-2,4)+1)} -> Corporate
A68: ="CUST"&TEXT(ROW()-1,"0000") -> CUST0067 | B68: {=INDEX({"Aarav","Vivaan","Aditya","Arjun","Kabir","Rohan","Ananya","Diya","Ishita","Meera","Riya","Pooja","Neha","Kavya","Aisha","Priya","Rahul","Karan","Vikram","Sahil"},MOD(ROW()-2,20)+1)&" "&INDEX({"Shah","Patel","Mehta","Desai","Joshi","Gupta","Verma","Sharma","Trivedi","Rana","Mishra","Kapoor","Iyer","Nair","Singh"},MOD(INT((ROW()-2)/20),15)+1)} -> Ananya Desai | C68: {=INDEX({"North","South","East","West","Central"},MOD(ROW()-2,5)+1)} -> South | D68: {=INDEX({"Electronics","Clothing","Furniture","Books","Office Supplies"},MOD(ROW()-2,5)+1)} -> Clothing | E68: =ROUND(500+MOD((ROW()-2)*137,44500),2) -> 9542 | F68: =MOD((ROW()-2)*7,11)+1 -> 1 | G68: =CHOOSE(MOD(ROW()-2,8)+1,0,0.02,0.05,0.08,0.1,0.12,0.15,0.2) -> 0.05 | H68: =DATE(2025,1,1)+MOD(ROW()-2,365) -> 45724 | I68: =ROUND(E68*F68*(1-G68),2) -> 9064.9 | J68: =ROUND(I68*(0.08+MOD(ROW()-2,12)*0.02),2) -> 1812.98 | K68: {=INDEX({"Amit","Neha","Riya","Karan","Pooja","Rahul","Meera","Vikram"},MOD(ROW()-2,8)+1)} -> Riya | L68: {=INDEX({"UPI","Credit Card","Debit Card","Cash","Net Banking"},MOD(ROW()-2,5)+1)} -> Credit Card | M68: {=INDEX({"Retail","Corporate","Education","Small Business"},MOD(ROW()-2,4)+1)} -> Education
A69: ="CUST"&TEXT(ROW()-1,"0000") -> CUST0068 | B69: {=INDEX({"Aarav","Vivaan","Aditya","Arjun","Kabir","Rohan","Ananya","Diya","Ishita","Meera","Riya","Pooja","Neha","Kavya","Aisha","Priya","Rahul","Karan","Vikram","Sahil"},MOD(ROW()-2,20)+1)&" "&INDEX({"Shah","Patel","Mehta","Desai","Joshi","Gupta","Verma","Sharma","Trivedi","Rana","Mishra","Kapoor","Iyer","Nair","Singh"},MOD(INT((ROW()-2)/20),15)+1)} -> Diya Desai | C69: {=INDEX({"North","South","East","West","Central"},MOD(ROW()-2,5)+1)} -> East | D69: {=INDEX({"Electronics","Clothing","Furniture","Books","Office Supplies"},MOD(ROW()-2,5)+1)} -> Furniture | E69: =ROUND(500+MOD((ROW()-2)*137,44500),2) -> 9679 | F69: =MOD((ROW()-2)*7,11)+1 -> 8 | G69: =CHOOSE(MOD(ROW()-2,8)+1,0,0.02,0.05,0.08,0.1,0.12,0.15,0.2) -> 0.08 | H69: =DATE(2025,1,1)+MOD(ROW()-2,365) -> 45725 | I69: =ROUND(E69*F69*(1-G69),2) -> 71237.44 | J69: =ROUND(I69*(0.08+MOD(ROW()-2,12)*0.02),2) -> 15672.24 | K69: {=INDEX({"Amit","Neha","Riya","Karan","Pooja","Rahul","Meera","Vikram"},MOD(ROW()-2,8)+1)} -> Karan | L69: {=INDEX({"UPI","Credit Card","Debit Card","Cash","Net Banking"},MOD(ROW()-2,5)+1)} -> Debit Card | M69: {=INDEX({"Retail","Corporate","Education","Small Business"},MOD(ROW()-2,4)+1)} -> Small Business
A70: ="CUST"&TEXT(ROW()-1,"0000") -> CUST0069 | B70: {=INDEX({"Aarav","Vivaan","Aditya","Arjun","Kabir","Rohan","Ananya","Diya","Ishita","Meera","Riya","Pooja","Neha","Kavya","Aisha","Priya","Rahul","Karan","Vikram","Sahil"},MOD(ROW()-2,20)+1)&" "&INDEX({"Shah","Patel","Mehta","Desai","Joshi","Gupta","Verma","Sharma","Trivedi","Rana","Mishra","Kapoor","Iyer","Nair","Singh"},MOD(INT((ROW()-2)/20),15)+1)} -> Ishita Desai | C70: {=INDEX({"North","South","East","West","Central"},MOD(ROW()-2,5)+1)} -> West | D70: {=INDEX({"Electronics","Clothing","Furniture","Books","Office Supplies"},MOD(ROW()-2,5)+1)} -> Books | E70: =ROUND(500+MOD((ROW()-2)*137,44500),2) -> 9816 | F70: =MOD((ROW()-2)*7,11)+1 -> 4 | G70: =CHOOSE(MOD(ROW()-2,8)+1,0,0.02,0.05,0.08,0.1,0.12,0.15,0.2) -> 0.1 | H70: =DATE(2025,1,1)+MOD(ROW()-2,365) -> 45726 | I70: =ROUND(E70*F70*(1-G70),2) -> 35337.6 | J70: =ROUND(I70*(0.08+MOD(ROW()-2,12)*0.02),2) -> 8481.02 | K70: {=INDEX({"Amit","Neha","Riya","Karan","Pooja","Rahul","Meera","Vikram"},MOD(ROW()-2,8)+1)} -> Pooja | L70: {=INDEX({"UPI","Credit Card","Debit Card","Cash","Net Banking"},MOD(ROW()-2,5)+1)} -> Cash | M70: {=INDEX({"Retail","Corporate","Education","Small Business"},MOD(ROW()-2,4)+1)} -> Retail
A71: ="CUST"&TEXT(ROW()-1,"0000") -> CUST0070 | B71: {=INDEX({"Aarav","Vivaan","Aditya","Arjun","Kabir","Rohan","Ananya","Diya","Ishita","Meera","Riya","Pooja","Neha","Kavya","Aisha","Priya","Rahul","Karan","Vikram","Sahil"},MOD(ROW()-2,20)+1)&" "&INDEX({"Shah","Patel","Mehta","Desai","Joshi","Gupta","Verma","Sharma","Trivedi","Rana","Mishra","Kapoor","Iyer","Nair","Singh"},MOD(INT((ROW()-2)/20),15)+1)} -> Meera Desai | C71: {=INDEX({"North","South","East","West","Central"},MOD(ROW()-2,5)+1)} -> Central | D71: {=INDEX({"Electronics","Clothing","Furniture","Books","Office Supplies"},MOD(ROW()-2,5)+1)} -> Office Supplies | E71: =ROUND(500+MOD((ROW()-2)*137,44500),2) -> 9953 | F71: =MOD((ROW()-2)*7,11)+1 -> 11 | G71: =CHOOSE(MOD(ROW()-2,8)+1,0,0.02,0.05,0.08,0.1,0.12,0.15,0.2) -> 0.12 | H71: =DATE(2025,1,1)+MOD(ROW()-2,365) -> 45727 | I71: =ROUND(E71*F71*(1-G71),2) -> 96345.04 | J71: =ROUND(I71*(0.08+MOD(ROW()-2,12)*0.02),2) -> 25049.71 | K71: {=INDEX({"Amit","Neha","Riya","Karan","Pooja","Rahul","Meera","Vikram"},MOD(ROW()-2,8)+1)} -> Rahul | L71: {=INDEX({"UPI","Credit Card","Debit Card","Cash","Net Banking"},MOD(ROW()-2,5)+1)} -> Net Banking | M71: {=INDEX({"Retail","Corporate","Education","Small Business"},MOD(ROW()-2,4)+1)} -> Corporate
A72: ="CUST"&TEXT(ROW()-1,"0000") -> CUST0071 | B72: {=INDEX({"Aarav","Vivaan","Aditya","Arjun","Kabir","Rohan","Ananya","Diya","Ishita","Meera","Riya","Pooja","Neha","Kavya","Aisha","Priya","Rahul","Karan","Vikram","Sahil"},MOD(ROW()-2,20)+1)&" "&INDEX({"Shah","Patel","Mehta","Desai","Joshi","Gupta","Verma","Sharma","Trivedi","Rana","Mishra","Kapoor","Iyer","Nair","Singh"},MOD(INT((ROW()-2)/20),15)+1)} -> Riya Desai | C72: {=INDEX({"North","South","East","West","Central"},MOD(ROW()-2,5)+1)} -> North | D72: {=INDEX({"Electronics","Clothing","Furniture","Books","Office Supplies"},MOD(ROW()-2,5)+1)} -> Electronics | E72: =ROUND(500+MOD((ROW()-2)*137,44500),2) -> 10090 | F72: =MOD((ROW()-2)*7,11)+1 -> 7 | G72: =CHOOSE(MOD(ROW()-2,8)+1,0,0.02,0.05,0.08,0.1,0.12,0.15,0.2) -> 0.15 | H72: =DATE(2025,1,1)+MOD(ROW()-2,365) -> 45728 | I72: =ROUND(E72*F72*(1-G72),2) -> 60035.5 | J72: =ROUND(I72*(0.08+MOD(ROW()-2,12)*0.02),2) -> 16809.94 | K72: {=INDEX({"Amit","Neha","Riya","Karan","Pooja","Rahul","Meera","Vikram"},MOD(ROW()-2,8)+1)} -> Meera | L72: {=INDEX({"UPI","Credit Card","Debit Card","Cash","Net Banking"},MOD(ROW()-2,5)+1)} -> UPI | M72: {=INDEX({"Retail","Corporate","Education","Small Business"},MOD(ROW()-2,4)+1)} -> Education
A73: ="CUST"&TEXT(ROW()-1,"0000") -> CUST0072 | B73: {=INDEX({"Aarav","Vivaan","Aditya","Arjun","Kabir","Rohan","Ananya","Diya","Ishita","Meera","Riya","Pooja","Neha","Kavya","Aisha","Priya","Rahul","Karan","Vikram","Sahil"},MOD(ROW()-2,20)+1)&" "&INDEX({"Shah","Patel","Mehta","Desai","Joshi","Gupta","Verma","Sharma","Trivedi","Rana","Mishra","Kapoor","Iyer","Nair","Singh"},MOD(INT((ROW()-2)/20),15)+1)} -> Pooja Desai | C73: {=INDEX({"North","South","East","West","Central"},MOD(ROW()-2,5)+1)} -> South | D73: {=INDEX({"Electronics","Clothing","Furniture","Books","Office Supplies"},MOD(ROW()-2,5)+1)} -> Clothing | E73: =ROUND(500+MOD((ROW()-2)*137,44500),2) -> 10227 | F73: =MOD((ROW()-2)*7,11)+1 -> 3 | G73: =CHOOSE(MOD(ROW()-2,8)+1,0,0.02,0.05,0.08,0.1,0.12,0.15,0.2) -> 0.2 | H73: =DATE(2025,1,1)+MOD(ROW()-2,365) -> 45729 | I73: =ROUND(E73*F73*(1-G73),2) -> 24544.8 | J73: =ROUND(I73*(0.08+MOD(ROW()-2,12)*0.02),2) -> 7363.44 | K73: {=INDEX({"Amit","Neha","Riya","Karan","Pooja","Rahul","Meera","Vikram"},MOD(ROW()-2,8)+1)} -> Vikram | L73: {=INDEX({"UPI","Credit Card","Debit Card","Cash","Net Banking"},MOD(ROW()-2,5)+1)} -> Credit Card | M73: {=INDEX({"Retail","Corporate","Education","Small Business"},MOD(ROW()-2,4)+1)} -> Small Business
A74: ="CUST"&TEXT(ROW()-1,"0000") -> CUST0073 | B74: {=INDEX({"Aarav","Vivaan","Aditya","Arjun","Kabir","Rohan","Ananya","Diya","Ishita","Meera","Riya","Pooja","Neha","Kavya","Aisha","Priya","Rahul","Karan","Vikram","Sahil"},MOD(ROW()-2,20)+1)&" "&INDEX({"Shah","Patel","Mehta","Desai","Joshi","Gupta","Verma","Sharma","Trivedi","Rana","Mishra","Kapoor","Iyer","Nair","Singh"},MOD(INT((ROW()-2)/20),15)+1)} -> Neha Desai | C74: {=INDEX({"North","South","East","West","Central"},MOD(ROW()-2,5)+1)} -> East | D74: {=INDEX({"Electronics","Clothing","Furniture","Books","Office Supplies"},MOD(ROW()-2,5)+1)} -> Furniture | E74: =ROUND(500+MOD((ROW()-2)*137,44500),2) -> 10364 | F74: =MOD((ROW()-2)*7,11)+1 -> 10 | G74: =CHOOSE(MOD(ROW()-2,8)+1,0,0.02,0.05,0.08,0.1,0.12,0.15,0.2) -> 0 | H74: =DATE(2025,1,1)+MOD(ROW()-2,365) -> 45730 | I74: =ROUND(E74*F74*(1-G74),2) -> 103640 | J74: =ROUND(I74*(0.08+MOD(ROW()-2,12)*0.02),2) -> 8291.2 | K74: {=INDEX({"Amit","Neha","Riya","Karan","Pooja","Rahul","Meera","Vikram"},MOD(ROW()-2,8)+1)} -> Amit | L74: {=INDEX({"UPI","Credit Card","Debit Card","Cash","Net Banking"},MOD(ROW()-2,5)+1)} -> Debit Card | M74: {=INDEX({"Retail","Corporate","Education","Small Business"},MOD(ROW()-2,4)+1)} -> Retail
A75: ="CUST"&TEXT(ROW()-1,"0000") -> CUST0074 | B75: {=INDEX({"Aarav","Vivaan","Aditya","Arjun","Kabir","Rohan","Ananya","Diya","Ishita","Meera","Riya","Pooja","Neha","Kavya","Aisha","Priya","Rahul","Karan","Vikram","Sahil"},MOD(ROW()-2,20)+1)&" "&INDEX({"Shah","Patel","Mehta","Desai","Joshi","Gupta","Verma","Sharma","Trivedi","Rana","Mishra","Kapoor","Iyer","Nair","Singh"},MOD(INT((ROW()-2)/20),15)+1)} -> Kavya Desai | C75: {=INDEX({"North","South","East","West","Central"},MOD(ROW()-2,5)+1)} -> West | D75: {=INDEX({"Electronics","Clothing","Furniture","Books","Office Supplies"},MOD(ROW()-2,5)+1)} -> Books | E75: =ROUND(500+MOD((ROW()-2)*137,44500),2) -> 10501 | F75: =MOD((ROW()-2)*7,11)+1 -> 6 | G75: =CHOOSE(MOD(ROW()-2,8)+1,0,0.02,0.05,0.08,0.1,0.12,0.15,0.2) -> 0.02 | H75: 45761 | I75: =ROUND(E75*F75*(1-G75),2) -> 61745.88 | J75: =ROUND(I75*(0.08+MOD(ROW()-2,12)*0.02),2) -> 6174.59 | K75: {=INDEX({"Amit","Neha","Riya","Karan","Pooja","Rahul","Meera","Vikram"},MOD(ROW()-2,8)+1)} -> Neha | L75: {=INDEX({"UPI","Credit Card","Debit Card","Cash","Net Banking"},MOD(ROW()-2,5)+1)} -> Cash | M75: {=INDEX({"Retail","Corporate","Education","Small Business"},MOD(ROW()-2,4)+1)} -> Corporate
A76: ="CUST"&TEXT(ROW()-1,"0000") -> CUST0075 | B76: {=INDEX({"Aarav","Vivaan","Aditya","Arjun","Kabir","Rohan","Ananya","Diya","Ishita","Meera","Riya","Pooja","Neha","Kavya","Aisha","Priya","Rahul","Karan","Vikram","Sahil"},MOD(ROW()-2,20)+1)&" "&INDEX({"Shah","Patel","Mehta","Desai","Joshi","Gupta","Verma","Sharma","Trivedi","Rana","Mishra","Kapoor","Iyer","Nair","Singh"},MOD(INT((ROW()-2)/20),15)+1)} -> Aisha Desai | C76: {=INDEX({"North","South","East","West","Central"},MOD(ROW()-2,5)+1)} -> Central | D76: {=INDEX({"Electronics","Clothing","Furniture","Books","Office Supplies"},MOD(ROW()-2,5)+1)} -> Office Supplies | E76: =ROUND(500+MOD((ROW()-2)*137,44500),2) -> 10638 | F76: =MOD((ROW()-2)*7,11)+1 -> 2 | G76: =CHOOSE(MOD(ROW()-2,8)+1,0,0.02,0.05,0.08,0.1,0.12,0.15,0.2) -> 0.05 | H76: =DATE(2025,1,1)+MOD(ROW()-2,365) -> 45732 | I76: =ROUND(E76*F76*(1-G76),2) -> 20212.2 | J76: =ROUND(I76*(0.08+MOD(ROW()-2,12)*0.02),2) -> 2425.46 | K76: {=INDEX({"Amit","Neha","Riya","Karan","Pooja","Rahul","Meera","Vikram"},MOD(ROW()-2,8)+1)} -> Riya | L76: {=INDEX({"UPI","Credit Card","Debit Card","Cash","Net Banking"},MOD(ROW()-2,5)+1)} -> Net Banking | M76: {=INDEX({"Retail","Corporate","Education","Small Business"},MOD(ROW()-2,4)+1)} -> Education
A77: ="CUST"&TEXT(ROW()-1,"0000") -> CUST0076 | B77: {=INDEX({"Aarav","Vivaan","Aditya","Arjun","Kabir","Rohan","Ananya","Diya","Ishita","Meera","Riya","Pooja","Neha","Kavya","Aisha","Priya","Rahul","Karan","Vikram","Sahil"},MOD(ROW()-2,20)+1)&" "&INDEX({"Shah","Patel","Mehta","Desai","Joshi","Gupta","Verma","Sharma","Trivedi","Rana","Mishra","Kapoor","Iyer","Nair","Singh"},MOD(INT((ROW()-2)/20),15)+1)} -> Priya Desai | C77: {=INDEX({"North","South","East","West","Central"},MOD(ROW()-2,5)+1)} -> North | D77: {=INDEX({"Electronics","Clothing","Furniture","Books","Office Supplies"},MOD(ROW()-2,5)+1)} -> Electronics | E77: 14885 | F77: =MOD((ROW()-2)*7,11)+1 -> 9 | G77: =CHOOSE(MOD(ROW()-2,8)+1,0,0.02,0.05,0.08,0.1,0.12,0.15,0.2) -> 0.08 | H77: =DATE(2025,1,1)+MOD(ROW()-2,365) -> 45733 | I77: =ROUND(E77*F77*(1-G77),2) -> 123247.8 | J77: =ROUND(I77*(0.08+MOD(ROW()-2,12)*0.02),2) -> 17254.69 | K77: {=INDEX({"Amit","Neha","Riya","Karan","Pooja","Rahul","Meera","Vikram"},MOD(ROW()-2,8)+1)} -> Karan | L77: {=INDEX({"UPI","Credit Card","Debit Card","Cash","Net Banking"},MOD(ROW()-2,5)+1)} -> UPI | M77: {=INDEX({"Retail","Corporate","Education","Small Business"},MOD(ROW()-2,4)+1)} -> Small Business
A78: ="CUST"&TEXT(ROW()-1,"0000") -> CUST0077 | B78: Rahul Desai | C78: {=INDEX({"North","South","East","West","Central"},MOD(ROW()-2,5)+1)} -> South | D78: {=INDEX({"Electronics","Clothing","Furniture","Books","Office Supplies"},MOD(ROW()-2,5)+1)} -> Clothing | E78: =ROUND(500+MOD((ROW()-2)*137,44500),2) -> 10912 | F78: =MOD((ROW()-2)*7,11)+1 -> 5 | G78: =CHOOSE(MOD(ROW()-2,8)+1,0,0.02,0.05,0.08,0.1,0.12,0.15,0.2) -> 0.1 | H78: =DATE(2025,1,1)+MOD(ROW()-2,365) -> 45734 | I78: =ROUND(E78*F78*(1-G78),2) -> 49104 | J78: =ROUND(I78*(0.08+MOD(ROW()-2,12)*0.02),2) -> 7856.64 | K78: {=INDEX({"Amit","Neha","Riya","Karan","Pooja","Rahul","Meera","Vikram"},MOD(ROW()-2,8)+1)} -> Pooja | L78: {=INDEX({"UPI","Credit Card","Debit Card","Cash","Net Banking"},MOD(ROW()-2,5)+1)} -> Credit Card | M78: {=INDEX({"Retail","Corporate","Education","Small Business"},MOD(ROW()-2,4)+1)} -> Retail
A79: ="CUST"&TEXT(ROW()-1,"0000") -> CUST0078 | B79: {=INDEX({"Aarav","Vivaan","Aditya","Arjun","Kabir","Rohan","Ananya","Diya","Ishita","Meera","Riya","Pooja","Neha","Kavya","Aisha","Priya","Rahul","Karan","Vikram","Sahil"},MOD(ROW()-2,20)+1)&" "&INDEX({"Shah","Patel","Mehta","Desai","Joshi","Gupta","Verma","Sharma","Trivedi","Rana","Mishra","Kapoor","Iyer","Nair","Singh"},MOD(INT((ROW()-2)/20),15)+1)} -> Karan Desai | C79: {=INDEX({"North","South","East","West","Central"},MOD(ROW()-2,5)+1)} -> East | D79: {=INDEX({"Electronics","Clothing","Furniture","Books","Office Supplies"},MOD(ROW()-2,5)+1)} -> Furniture | E79: =ROUND(500+MOD((ROW()-2)*137,44500),2) -> 11049 | F79: =MOD((ROW()-2)*7,11)+1 -> 1 | G79: =CHOOSE(MOD(ROW()-2,8)+1,0,0.02,0.05,0.08,0.1,0.12,0.15,0.2) -> 0.12 | H79: =DATE(2025,1,1)+MOD(ROW()-2,365) -> 45735 | I79: =ROUND(E79*F79*(1-G79),2) -> 9723.12 | J79: =ROUND(I79*(0.08+MOD(ROW()-2,12)*0.02),2) -> 1750.16 | K79: {=INDEX({"Amit","Neha","Riya","Karan","Pooja","Rahul","Meera","Vikram"},MOD(ROW()-2,8)+1)} -> Rahul | L79: {=INDEX({"UPI","Credit Card","Debit Card","Cash","Net Banking"},MOD(ROW()-2,5)+1)} -> Debit Card | M79: {=INDEX({"Retail","Corporate","Education","Small Business"},MOD(ROW()-2,4)+1)} -> Corporate
A80: ="CUST"&TEXT(ROW()-1,"0000") -> CUST0079 | B80: {=INDEX({"Aarav","Vivaan","Aditya","Arjun","Kabir","Rohan","Ananya","Diya","Ishita","Meera","Riya","Pooja","Neha","Kavya","Aisha","Priya","Rahul","Karan","Vikram","Sahil"},MOD(ROW()-2,20)+1)&" "&INDEX({"Shah","Patel","Mehta","Desai","Joshi","Gupta","Verma","Sharma","Trivedi","Rana","Mishra","Kapoor","Iyer","Nair","Singh"},MOD(INT((ROW()-2)/20),15)+1)} -> Vikram Desai | C80: {=INDEX({"North","South","East","West","Central"},MOD(ROW()-2,5)+1)} -> West | D80: {=INDEX({"Electronics","Clothing","Furniture","Books","Office Supplies"},MOD(ROW()-2,5)+1)} -> Books | E80: =ROUND(500+MOD((ROW()-2)*137,44500),2) -> 11186 | F80: =MOD((ROW()-2)*7,11)+1 -> 8 | G80: =CHOOSE(MOD(ROW()-2,8)+1,0,0.02,0.05,0.08,0.1,0.12,0.15,0.2) -> 0.15 | H80: =DATE(2025,1,1)+MOD(ROW()-2,365) -> 45736 | I80: =ROUND(E80*F80*(1-G80),2) -> 76064.8 | J80: =ROUND(I80*(0.08+MOD(ROW()-2,12)*0.02),2) -> 15212.96 | K80: {=INDEX({"Amit","Neha","Riya","Karan","Pooja","Rahul","Meera","Vikram"},MOD(ROW()-2,8)+1)} -> Meera | L80: {=INDEX({"UPI","Credit Card","Debit Card","Cash","Net Banking"},MOD(ROW()-2,5)+1)} -> Cash | M80: {=INDEX({"Retail","Corporate","Education","Small Business"},MOD(ROW()-2,4)+1)} -> Education
A81: ="CUST"&TEXT(ROW()-1,"0000") -> CUST0080 | B81: {=INDEX({"Aarav","Vivaan","Aditya","Arjun","Kabir","Rohan","Ananya","Diya","Ishita","Meera","Riya","Pooja","Neha","Kavya","Aisha","Priya","Rahul","Karan","Vikram","Sahil"},MOD(ROW()-2,20)+1)&" "&INDEX({"Shah","Patel","Mehta","Desai","Joshi","Gupta","Verma","Sharma","Trivedi","Rana","Mishra","Kapoor","Iyer","Nair","Singh"},MOD(INT((ROW()-2)/20),15)+1)} -> Sahil Desai | C81: {=INDEX({"North","South","East","West","Central"},MOD(ROW()-2,5)+1)} -> Central | D81: {=INDEX({"Electronics","Clothing","Furniture","Books","Office Supplies"},MOD(ROW()-2,5)+1)} -> Office Supplies | E81: =ROUND(500+MOD((ROW()-2)*137,44500),2) -> 11323 | F81: =MOD((ROW()-2)*7,11)+1 -> 4 | G81: =CHOOSE(MOD(ROW()-2,8)+1,0,0.02,0.05,0.08,0.1,0.12,0.15,0.2) -> 0.2 | H81: =DATE(2025,1,1)+MOD(ROW()-2,365) -> 45737 | I81: =ROUND(E81*F81*(1-G81),2) -> 36233.6 | J81: =ROUND(I81*(0.08+MOD(ROW()-2,12)*0.02),2) -> 7971.39 | K81: {=INDEX({"Amit","Neha","Riya","Karan","Pooja","Rahul","Meera","Vikram"},MOD(ROW()-2,8)+1)} -> Vikram | L81: {=INDEX({"UPI","Credit Card","Debit Card","Cash","Net Banking"},MOD(ROW()-2,5)+1)} -> Net Banking | M81: {=INDEX({"Retail","Corporate","Education","Small Business"},MOD(ROW()-2,4)+1)} -> Small Business
A82: ="CUST"&TEXT(ROW()-1,"0000") -> CUST0081 | B82: {=INDEX({"Aarav","Vivaan","Aditya","Arjun","Kabir","Rohan","Ananya","Diya","Ishita","Meera","Riya","Pooja","Neha","Kavya","Aisha","Priya","Rahul","Karan","Vikram","Sahil"},MOD(ROW()-2,20)+1)&" "&INDEX({"Shah","Patel","Mehta","Desai","Joshi","Gupta","Verma","Sharma","Trivedi","Rana","Mishra","Kapoor","Iyer","Nair","Singh"},MOD(INT((ROW()-2)/20),15)+1)} -> Aarav Joshi | C82: {=INDEX({"North","South","East","West","Central"},MOD(ROW()-2,5)+1)} -> North | D82: {=INDEX({"Electronics","Clothing","Furniture","Books","Office Supplies"},MOD(ROW()-2,5)+1)} -> Electronics | E82: =ROUND(500+MOD((ROW()-2)*137,44500),2) -> 11460 | F82: =MOD((ROW()-2)*7,11)+1 -> 11 | G82: =CHOOSE(MOD(ROW()-2,8)+1,0,0.02,0.05,0.08,0.1,0.12,0.15,0.2) -> 0 | H82: =DATE(2025,1,1)+MOD(ROW()-2,365) -> 45738 | I82: =ROUND(E82*F82*(1-G82),2) -> 126060 | J82: =ROUND(I82*(0.08+MOD(ROW()-2,12)*0.02),2) -> 30254.4 | K82: {=INDEX({"Amit","Neha","Riya","Karan","Pooja","Rahul","Meera","Vikram"},MOD(ROW()-2,8)+1)} -> Amit | L82: {=INDEX({"UPI","Credit Card","Debit Card","Cash","Net Banking"},MOD(ROW()-2,5)+1)} -> UPI | M82: {=INDEX({"Retail","Corporate","Education","Small Business"},MOD(ROW()-2,4)+1)} -> Retail
A83: ="CUST"&TEXT(ROW()-1,"0000") -> CUST0082 | B83: {=INDEX({"Aarav","Vivaan","Aditya","Arjun","Kabir","Rohan","Ananya","Diya","Ishita","Meera","Riya","Pooja","Neha","Kavya","Aisha","Priya","Rahul","Karan","Vikram","Sahil"},MOD(ROW()-2,20)+1)&" "&INDEX({"Shah","Patel","Mehta","Desai","Joshi","Gupta","Verma","Sharma","Trivedi","Rana","Mishra","Kapoor","Iyer","Nair","Singh"},MOD(INT((ROW()-2)/20),15)+1)} -> Vivaan Joshi | C83: {=INDEX({"North","South","East","West","Central"},MOD(ROW()-2,5)+1)} -> South | D83: {=INDEX({"Electronics","Clothing","Furniture","Books","Office Supplies"},MOD(ROW()-2,5)+1)} -> Clothing | E83: =ROUND(500+MOD((ROW()-2)*137,44500),2) -> 11597 | F83: =MOD((ROW()-2)*7,11)+1 -> 7 | G83: =CHOOSE(MOD(ROW()-2,8)+1,0,0.02,0.05,0.08,0.1,0.12,0.15,0.2) -> 0.02 | H83: =DATE(2025,1,1)+MOD(ROW()-2,365) -> 45739 | I83: =ROUND(E83*F83*(1-G83),2) -> 79555.42 | J83: =ROUND(I83*(0.08+MOD(ROW()-2,12)*0.02),2) -> 20684.41 | K83: {=INDEX({"Amit","Neha","Riya","Karan","Pooja","Rahul","Meera","Vikram"},MOD(ROW()-2,8)+1)} -> Neha | L83: {=INDEX({"UPI","Credit Card","Debit Card","Cash","Net Banking"},MOD(ROW()-2,5)+1)} -> Credit Card | M83: {=INDEX({"Retail","Corporate","Education","Small Business"},MOD(ROW()-2,4)+1)} -> Corporate
A84: ="CUST"&TEXT(ROW()-1,"0000") -> CUST0083 | B84: {=INDEX({"Aarav","Vivaan","Aditya","Arjun","Kabir","Rohan","Ananya","Diya","Ishita","Meera","Riya","Pooja","Neha","Kavya","Aisha","Priya","Rahul","Karan","Vikram","Sahil"},MOD(ROW()-2,20)+1)&" "&INDEX({"Shah","Patel","Mehta","Desai","Joshi","Gupta","Verma","Sharma","Trivedi","Rana","Mishra","Kapoor","Iyer","Nair","Singh"},MOD(INT((ROW()-2)/20),15)+1)} -> Aditya Joshi | C84: {=INDEX({"North","South","East","West","Central"},MOD(ROW()-2,5)+1)} -> East | D84: {=INDEX({"Electronics","Clothing","Furniture","Books","Office Supplies"},MOD(ROW()-2,5)+1)} -> Furniture | E84: =ROUND(500+MOD((ROW()-2)*137,44500),2) -> 11734 | F84: 4 | G84: =CHOOSE(MOD(ROW()-2,8)+1,0,0.02,0.05,0.08,0.1,0.12,0.15,0.2) -> 0.05 | H84: =DATE(2025,1,1)+MOD(ROW()-2,365) -> 45740 | I84: =ROUND(E84*F84*(1-G84),2) -> 44589.2 | J84: =ROUND(I84*(0.08+MOD(ROW()-2,12)*0.02),2) -> 12484.98 | K84: {=INDEX({"Amit","Neha","Riya","Karan","Pooja","Rahul","Meera","Vikram"},MOD(ROW()-2,8)+1)} -> Riya | L84: {=INDEX({"UPI","Credit Card","Debit Card","Cash","Net Banking"},MOD(ROW()-2,5)+1)} -> Debit Card | M84: {=INDEX({"Retail","Corporate","Education","Small Business"},MOD(ROW()-2,4)+1)} -> Education
A85: ="CUST"&TEXT(ROW()-1,"0000") -> CUST0084 | B85: {=INDEX({"Aarav","Vivaan","Aditya","Arjun","Kabir","Rohan","Ananya","Diya","Ishita","Meera","Riya","Pooja","Neha","Kavya","Aisha","Priya","Rahul","Karan","Vikram","Sahil"},MOD(ROW()-2,20)+1)&" "&INDEX({"Shah","Patel","Mehta","Desai","Joshi","Gupta","Verma","Sharma","Trivedi","Rana","Mishra","Kapoor","Iyer","Nair","Singh"},MOD(INT((ROW()-2)/20),15)+1)} -> Arjun Joshi | C85: {=INDEX({"North","South","East","West","Central"},MOD(ROW()-2,5)+1)} -> West | D85: {=INDEX({"Electronics","Clothing","Furniture","Books","Office Supplies"},MOD(ROW()-2,5)+1)} -> Books | E85: =ROUND(500+MOD((ROW()-2)*137,44500),2) -> 11871 | F85: =MOD((ROW()-2)*7,11)+1 -> 10 | G85: =CHOOSE(MOD(ROW()-2,8)+1,0,0.02,0.05,0.08,0.1,0.12,0.15,0.2) -> 0.08 | H85: =DATE(2025,1,1)+MOD(ROW()-2,365) -> 45741 | I85: =ROUND(E85*F85*(1-G85),2) -> 109213.2 | J85: =ROUND(I85*(0.08+MOD(ROW()-2,12)*0.02),2) -> 32763.96 | K85: {=INDEX({"Amit","Neha","Riya","Karan","Pooja","Rahul","Meera","Vikram"},MOD(ROW()-2,8)+1)} -> Karan | L85: {=INDEX({"UPI","Credit Card","Debit Card","Cash","Net Banking"},MOD(ROW()-2,5)+1)} -> Cash | M85: {=INDEX({"Retail","Corporate","Education","Small Business"},MOD(ROW()-2,4)+1)} -> Small Business
A86: ="CUST"&TEXT(ROW()-1,"0000") -> CUST0085 | B86: {=INDEX({"Aarav","Vivaan","Aditya","Arjun","Kabir","Rohan","Ananya","Diya","Ishita","Meera","Riya","Pooja","Neha","Kavya","Aisha","Priya","Rahul","Karan","Vikram","Sahil"},MOD(ROW()-2,20)+1)&" "&INDEX({"Shah","Patel","Mehta","Desai","Joshi","Gupta","Verma","Sharma","Trivedi","Rana","Mishra","Kapoor","Iyer","Nair","Singh"},MOD(INT((ROW()-2)/20),15)+1)} -> Kabir Joshi | C86: {=INDEX({"North","South","East","West","Central"},MOD(ROW()-2,5)+1)} -> Central | D86: {=INDEX({"Electronics","Clothing","Furniture","Books","Office Supplies"},MOD(ROW()-2,5)+1)} -> Office Supplies | E86: =ROUND(500+MOD((ROW()-2)*137,44500),2) -> 12008 | F86: =MOD((ROW()-2)*7,11)+1 -> 6 | G86: 0.05 | H86: =DATE(2025,1,1)+MOD(ROW()-2,365) -> 45742 | I86: =ROUND(E86*F86*(1-G86),2) -> 68445.6 | J86: =ROUND(I86*(0.08+MOD(ROW()-2,12)*0.02),2) -> 5475.65 | K86: {=INDEX({"Amit","Neha","Riya","Karan","Pooja","Rahul","Meera","Vikram"},MOD(ROW()-2,8)+1)} -> Pooja | L86: {=INDEX({"UPI","Credit Card","Debit Card","Cash","Net Banking"},MOD(ROW()-2,5)+1)} -> Net Banking | M86: {=INDEX({"Retail","Corporate","Education","Small Business"},MOD(ROW()-2,4)+1)} -> Retail
A87: ="CUST"&TEXT(ROW()-1,"0000") -> CUST0086 | B87: {=INDEX({"Aarav","Vivaan","Aditya","Arjun","Kabir","Rohan","Ananya","Diya","Ishita","Meera","Riya","Pooja","Neha","Kavya","Aisha","Priya","Rahul","Karan","Vikram","Sahil"},MOD(ROW()-2,20)+1)&" "&INDEX({"Shah","Patel","Mehta","Desai","Joshi","Gupta","Verma","Sharma","Trivedi","Rana","Mishra","Kapoor","Iyer","Nair","Singh"},MOD(INT((ROW()-2)/20),15)+1)} -> Rohan Joshi | C87: {=INDEX({"North","South","East","West","Central"},MOD(ROW()-2,5)+1)} -> North | D87: {=INDEX({"Electronics","Clothing","Furniture","Books","Office Supplies"},MOD(ROW()-2,5)+1)} -> Electronics | E87: =ROUND(500+MOD((ROW()-2)*137,44500),2) -> 12145 | F87: =MOD((ROW()-2)*7,11)+1 -> 2 | G87: =CHOOSE(MOD(ROW()-2,8)+1,0,0.02,0.05,0.08,0.1,0.12,0.15,0.2) -> 0.12 | H87: =DATE(2025,1,1)+MOD(ROW()-2,365) -> 45743 | I87: =ROUND(E87*F87*(1-G87),2) -> 21375.2 | J87: =ROUND(I87*(0.08+MOD(ROW()-2,12)*0.02),2) -> 2137.52 | K87: {=INDEX({"Amit","Neha","Riya","Karan","Pooja","Rahul","Meera","Vikram"},MOD(ROW()-2,8)+1)} -> Rahul | L87: {=INDEX({"UPI","Credit Card","Debit Card","Cash","Net Banking"},MOD(ROW()-2,5)+1)} -> UPI | M87: {=INDEX({"Retail","Corporate","Education","Small Business"},MOD(ROW()-2,4)+1)} -> Corporate
A88: ="CUST"&TEXT(ROW()-1,"0000") -> CUST0087 | B88: {=INDEX({"Aarav","Vivaan","Aditya","Arjun","Kabir","Rohan","Ananya","Diya","Ishita","Meera","Riya","Pooja","Neha","Kavya","Aisha","Priya","Rahul","Karan","Vikram","Sahil"},MOD(ROW()-2,20)+1)&" "&INDEX({"Shah","Patel","Mehta","Desai","Joshi","Gupta","Verma","Sharma","Trivedi","Rana","Mishra","Kapoor","Iyer","Nair","Singh"},MOD(INT((ROW()-2)/20),15)+1)} -> Ananya Joshi | C88: {=INDEX({"North","South","East","West","Central"},MOD(ROW()-2,5)+1)} -> South | D88: {=INDEX({"Electronics","Clothing","Furniture","Books","Office Supplies"},MOD(ROW()-2,5)+1)} -> Clothing | E88: =ROUND(500+MOD((ROW()-2)*137,44500),2) -> 12282 | F88: =MOD((ROW()-2)*7,11)+1 -> 9 | G88: =CHOOSE(MOD(ROW()-2,8)+1,0,0.02,0.05,0.08,0.1,0.12,0.15,0.2) -> 0.15 | H88: =DATE(2025,1,1)+MOD(ROW()-2,365) -> 45744 | I88: =ROUND(E88*F88*(1-G88),2) -> 93957.3 | J88: =ROUND(I88*(0.08+MOD(ROW()-2,12)*0.02),2) -> 11274.88 | K88: {=INDEX({"Amit","Neha","Riya","Karan","Pooja","Rahul","Meera","Vikram"},MOD(ROW()-2,8)+1)} -> Meera | L88: {=INDEX({"UPI","Credit Card","Debit Card","Cash","Net Banking"},MOD(ROW()-2,5)+1)} -> Credit Card | M88: {=INDEX({"Retail","Corporate","Education","Small Business"},MOD(ROW()-2,4)+1)} -> Education
A89: ="CUST"&TEXT(ROW()-1,"0000") -> CUST0088 | B89: {=INDEX({"Aarav","Vivaan","Aditya","Arjun","Kabir","Rohan","Ananya","Diya","Ishita","Meera","Riya","Pooja","Neha","Kavya","Aisha","Priya","Rahul","Karan","Vikram","Sahil"},MOD(ROW()-2,20)+1)&" "&INDEX({"Shah","Patel","Mehta","Desai","Joshi","Gupta","Verma","Sharma","Trivedi","Rana","Mishra","Kapoor","Iyer","Nair","Singh"},MOD(INT((ROW()-2)/20),15)+1)} -> Diya Joshi | C89: {=INDEX({"North","South","East","West","Central"},MOD(ROW()-2,5)+1)} -> East | D89: {=INDEX({"Electronics","Clothing","Furniture","Books","Office Supplies"},MOD(ROW()-2,5)+1)} -> Furniture | E89: =ROUND(500+MOD((ROW()-2)*137,44500),2) -> 12419 | F89: =MOD((ROW()-2)*7,11)+1 -> 5 | G89: =CHOOSE(MOD(ROW()-2,8)+1,0,0.02,0.05,0.08,0.1,0.12,0.15,0.2) -> 0.2 | H89: =DATE(2025,1,1)+MOD(ROW()-2,365) -> 45745 | I89: =ROUND(E89*F89*(1-G89),2) -> 49676 | J89: =ROUND(I89*(0.08+MOD(ROW()-2,12)*0.02),2) -> 6954.64 | K89: {=INDEX({"Amit","Neha","Riya","Karan","Pooja","Rahul","Meera","Vikram"},MOD(ROW()-2,8)+1)} -> Vikram | L89: {=INDEX({"UPI","Credit Card","Debit Card","Cash","Net Banking"},MOD(ROW()-2,5)+1)} -> Debit Card | M89: {=INDEX({"Retail","Corporate","Education","Small Business"},MOD(ROW()-2,4)+1)} -> Small Business
A90: ="CUST"&TEXT(ROW()-1,"0000") -> CUST0089 | B90: {=INDEX({"Aarav","Vivaan","Aditya","Arjun","Kabir","Rohan","Ananya","Diya","Ishita","Meera","Riya","Pooja","Neha","Kavya","Aisha","Priya","Rahul","Karan","Vikram","Sahil"},MOD(ROW()-2,20)+1)&" "&INDEX({"Shah","Patel","Mehta","Desai","Joshi","Gupta","Verma","Sharma","Trivedi","Rana","Mishra","Kapoor","Iyer","Nair","Singh"},MOD(INT((ROW()-2)/20),15)+1)} -> Ishita Joshi | C90: {=INDEX({"North","South","East","West","Central"},MOD(ROW()-2,5)+1)} -> West | D90: {=INDEX({"Electronics","Clothing","Furniture","Books","Office Supplies"},MOD(ROW()-2,5)+1)} -> Books | E90: =ROUND(500+MOD((ROW()-2)*137,44500),2) -> 12556 | F90: =MOD((ROW()-2)*7,11)+1 -> 1 | G90: =CHOOSE(MOD(ROW()-2,8)+1,0,0.02,0.05,0.08,0.1,0.12,0.15,0.2) -> 0 | H90: =DATE(2025,1,1)+MOD(ROW()-2,365) -> 45746 | I90: =ROUND(E90*F90*(1-G90),2) -> 12556 | J90: =ROUND(I90*(0.08+MOD(ROW()-2,12)*0.02),2) -> 2008.96 | K90: {=INDEX({"Amit","Neha","Riya","Karan","Pooja","Rahul","Meera","Vikram"},MOD(ROW()-2,8)+1)} -> Amit | L90: {=INDEX({"UPI","Credit Card","Debit Card","Cash","Net Banking"},MOD(ROW()-2,5)+1)} -> Cash | M90: {=INDEX({"Retail","Corporate","Education","Small Business"},MOD(ROW()-2,4)+1)} -> Retail
A91: ="CUST"&TEXT(ROW()-1,"0000") -> CUST0090 | B91: Sahil Gupta | C91: {=INDEX({"North","South","East","West","Central"},MOD(ROW()-2,5)+1)} -> Central | D91: {=INDEX({"Electronics","Clothing","Furniture","Books","Office Supplies"},MOD(ROW()-2,5)+1)} -> Office Supplies | E91: =ROUND(500+MOD((ROW()-2)*137,44500),2) -> 12693 | F91: =MOD((ROW()-2)*7,11)+1 -> 8 | G91: =CHOOSE(MOD(ROW()-2,8)+1,0,0.02,0.05,0.08,0.1,0.12,0.15,0.2) -> 0.02 | H91: =DATE(2025,1,1)+MOD(ROW()-2,365) -> 45747 | I91: =ROUND(E91*F91*(1-G91),2) -> 99513.12 | J91: =ROUND(I91*(0.08+MOD(ROW()-2,12)*0.02),2) -> 17912.36 | K91: {=INDEX({"Amit","Neha","Riya","Karan","Pooja","Rahul","Meera","Vikram"},MOD(ROW()-2,8)+1)} -> Neha | L91: {=INDEX({"UPI","Credit Card","Debit Card","Cash","Net Banking"},MOD(ROW()-2,5)+1)} -> Net Banking | M91: {=INDEX({"Retail","Corporate","Education","Small Business"},MOD(ROW()-2,4)+1)} -> Corporate
A92: ="CUST"&TEXT(ROW()-1,"0000") -> CUST0091 | B92: {=INDEX({"Aarav","Vivaan","Aditya","Arjun","Kabir","Rohan","Ananya","Diya","Ishita","Meera","Riya","Pooja","Neha","Kavya","Aisha","Priya","Rahul","Karan","Vikram","Sahil"},MOD(ROW()-2,20)+1)&" "&INDEX({"Shah","Patel","Mehta","Desai","Joshi","Gupta","Verma","Sharma","Trivedi","Rana","Mishra","Kapoor","Iyer","Nair","Singh"},MOD(INT((ROW()-2)/20),15)+1)} -> Riya Joshi | C92: {=INDEX({"North","South","East","West","Central"},MOD(ROW()-2,5)+1)} -> North | D92: {=INDEX({"Electronics","Clothing","Furniture","Books","Office Supplies"},MOD(ROW()-2,5)+1)} -> Electronics | E92: =ROUND(500+MOD((ROW()-2)*137,44500),2) -> 12830 | F92: =MOD((ROW()-2)*7,11)+1 -> 4 | G92: =CHOOSE(MOD(ROW()-2,8)+1,0,0.02,0.05,0.08,0.1,0.12,0.15,0.2) -> 0.05 | H92: =DATE(2025,1,1)+MOD(ROW()-2,365) -> 45748 | I92: =ROUND(E92*F92*(1-G92),2) -> 48754 | J92: =ROUND(I92*(0.08+MOD(ROW()-2,12)*0.02),2) -> 9750.8 | K92: {=INDEX({"Amit","Neha","Riya","Karan","Pooja","Rahul","Meera","Vikram"},MOD(ROW()-2,8)+1)} -> Riya | L92: {=INDEX({"UPI","Credit Card","Debit Card","Cash","Net Banking"},MOD(ROW()-2,5)+1)} -> UPI | M92: {=INDEX({"Retail","Corporate","Education","Small Business"},MOD(ROW()-2,4)+1)} -> Education
A93: ="CUST"&TEXT(ROW()-1,"0000") -> CUST0092 | B93: {=INDEX({"Aarav","Vivaan","Aditya","Arjun","Kabir","Rohan","Ananya","Diya","Ishita","Meera","Riya","Pooja","Neha","Kavya","Aisha","Priya","Rahul","Karan","Vikram","Sahil"},MOD(ROW()-2,20)+1)&" "&INDEX({"Shah","Patel","Mehta","Desai","Joshi","Gupta","Verma","Sharma","Trivedi","Rana","Mishra","Kapoor","Iyer","Nair","Singh"},MOD(INT((ROW()-2)/20),15)+1)} -> Pooja Joshi | C93: {=INDEX({"North","South","East","West","Central"},MOD(ROW()-2,5)+1)} -> South | D93: {=INDEX({"Electronics","Clothing","Furniture","Books","Office Supplies"},MOD(ROW()-2,5)+1)} -> Clothing | E93: =ROUND(500+MOD((ROW()-2)*137,44500),2) -> 12967 | F93: =MOD((ROW()-2)*7,11)+1 -> 11 | G93: =CHOOSE(MOD(ROW()-2,8)+1,0,0.02,0.05,0.08,0.1,0.12,0.15,0.2) -> 0.08 | H93: =DATE(2025,1,1)+MOD(ROW()-2,365) -> 45749 | I93: =ROUND(E93*F93*(1-G93),2) -> 131226.04 | J93: =ROUND(I93*(0.08+MOD(ROW()-2,12)*0.02),2) -> 28869.73 | K93: {=INDEX({"Amit","Neha","Riya","Karan","Pooja","Rahul","Meera","Vikram"},MOD(ROW()-2,8)+1)} -> Karan | L93: {=INDEX({"UPI","Credit Card","Debit Card","Cash","Net Banking"},MOD(ROW()-2,5)+1)} -> Credit Card | M93: {=INDEX({"Retail","Corporate","Education","Small Business"},MOD(ROW()-2,4)+1)} -> Small Business
A94: ="CUST"&TEXT(ROW()-1,"0000") -> CUST0093 | B94: {=INDEX({"Aarav","Vivaan","Aditya","Arjun","Kabir","Rohan","Ananya","Diya","Ishita","Meera","Riya","Pooja","Neha","Kavya","Aisha","Priya","Rahul","Karan","Vikram","Sahil"},MOD(ROW()-2,20)+1)&" "&INDEX({"Shah","Patel","Mehta","Desai","Joshi","Gupta","Verma","Sharma","Trivedi","Rana","Mishra","Kapoor","Iyer","Nair","Singh"},MOD(INT((ROW()-2)/20),15)+1)} -> Neha Joshi | C94: {=INDEX({"North","South","East","West","Central"},MOD(ROW()-2,5)+1)} -> East | D94: {=INDEX({"Electronics","Clothing","Furniture","Books","Office Supplies"},MOD(ROW()-2,5)+1)} -> Furniture | E94: =ROUND(500+MOD((ROW()-2)*137,44500),2) -> 13104 | F94: =MOD((ROW()-2)*7,11)+1 -> 7 | G94: =CHOOSE(MOD(ROW()-2,8)+1,0,0.02,0.05,0.08,0.1,0.12,0.15,0.2) -> 0.1 | H94: =DATE(2025,1,1)+MOD(ROW()-2,365) -> 45750 | I94: =ROUND(E94*F94*(1-G94),2) -> 82555.2 | J94: =ROUND(I94*(0.08+MOD(ROW()-2,12)*0.02),2) -> 19813.25 | K94: {=INDEX({"Amit","Neha","Riya","Karan","Pooja","Rahul","Meera","Vikram"},MOD(ROW()-2,8)+1)} -> Pooja | L94: {=INDEX({"UPI","Credit Card","Debit Card","Cash","Net Banking"},MOD(ROW()-2,5)+1)} -> Debit Card | M94: {=INDEX({"Retail","Corporate","Education","Small Business"},MOD(ROW()-2,4)+1)} -> Retail
A95: ="CUST"&TEXT(ROW()-1,"0000") -> CUST0094 | B95: {=INDEX({"Aarav","Vivaan","Aditya","Arjun","Kabir","Rohan","Ananya","Diya","Ishita","Meera","Riya","Pooja","Neha","Kavya","Aisha","Priya","Rahul","Karan","Vikram","Sahil"},MOD(ROW()-2,20)+1)&" "&INDEX({"Shah","Patel","Mehta","Desai","Joshi","Gupta","Verma","Sharma","Trivedi","Rana","Mishra","Kapoor","Iyer","Nair","Singh"},MOD(INT((ROW()-2)/20),15)+1)} -> Kavya Joshi | C95: {=INDEX({"North","South","East","West","Central"},MOD(ROW()-2,5)+1)} -> West | D95: {=INDEX({"Electronics","Clothing","Furniture","Books","Office Supplies"},MOD(ROW()-2,5)+1)} -> Books | E95: =ROUND(500+MOD((ROW()-2)*137,44500),2) -> 13241 | F95: =MOD((ROW()-2)*7,11)+1 -> 3 | G95: =CHOOSE(MOD(ROW()-2,8)+1,0,0.02,0.05,0.08,0.1,0.12,0.15,0.2) -> 0.12 | H95: =DATE(2025,1,1)+MOD(ROW()-2,365) -> 45751 | I95: =ROUND(E95*F95*(1-G95),2) -> 34956.24 | J95: =ROUND(I95*(0.08+MOD(ROW()-2,12)*0.02),2) -> 9088.62 | K95: {=INDEX({"Amit","Neha","Riya","Karan","Pooja","Rahul","Meera","Vikram"},MOD(ROW()-2,8)+1)} -> Rahul | L95: {=INDEX({"UPI","Credit Card","Debit Card","Cash","Net Banking"},MOD(ROW()-2,5)+1)} -> Cash | M95: {=INDEX({"Retail","Corporate","Education","Small Business"},MOD(ROW()-2,4)+1)} -> Corporate
A96: ="CUST"&TEXT(ROW()-1,"0000") -> CUST0095 | B96: {=INDEX({"Aarav","Vivaan","Aditya","Arjun","Kabir","Rohan","Ananya","Diya","Ishita","Meera","Riya","Pooja","Neha","Kavya","Aisha","Priya","Rahul","Karan","Vikram","Sahil"},MOD(ROW()-2,20)+1)&" "&INDEX({"Shah","Patel","Mehta","Desai","Joshi","Gupta","Verma","Sharma","Trivedi","Rana","Mishra","Kapoor","Iyer","Nair","Singh"},MOD(INT((ROW()-2)/20),15)+1)} -> Aisha Joshi | C96: {=INDEX({"North","South","East","West","Central"},MOD(ROW()-2,5)+1)} -> Central | D96: {=INDEX({"Electronics","Clothing","Furniture","Books","Office Supplies"},MOD(ROW()-2,5)+1)} -> Office Supplies | E96: =ROUND(500+MOD((ROW()-2)*137,44500),2) -> 13378 | F96: =MOD((ROW()-2)*7,11)+1 -> 10 | G96: =CHOOSE(MOD(ROW()-2,8)+1,0,0.02,0.05,0.08,0.1,0.12,0.15,0.2) -> 0.15 | H96: =DATE(2025,1,1)+MOD(ROW()-2,365) -> 45752 | I96: =ROUND(E96*F96*(1-G96),2) -> 113713 | J96: =ROUND(I96*(0.08+MOD(ROW()-2,12)*0.02),2) -> 31839.64 | K96: {=INDEX({"Amit","Neha","Riya","Karan","Pooja","Rahul","Meera","Vikram"},MOD(ROW()-2,8)+1)} -> Meera | L96: {=INDEX({"UPI","Credit Card","Debit Card","Cash","Net Banking"},MOD(ROW()-2,5)+1)} -> Net Banking | M96: {=INDEX({"Retail","Corporate","Education","Small Business"},MOD(ROW()-2,4)+1)} -> Education
A97: ="CUST"&TEXT(ROW()-1,"0000") -> CUST0096 | B97: {=INDEX({"Aarav","Vivaan","Aditya","Arjun","Kabir","Rohan","Ananya","Diya","Ishita","Meera","Riya","Pooja","Neha","Kavya","Aisha","Priya","Rahul","Karan","Vikram","Sahil"},MOD(ROW()-2,20)+1)&" "&INDEX({"Shah","Patel","Mehta","Desai","Joshi","Gupta","Verma","Sharma","Trivedi","Rana","Mishra","Kapoor","Iyer","Nair","Singh"},MOD(INT((ROW()-2)/20),15)+1)} -> Priya Joshi | C97: {=INDEX({"North","South","East","West","Central"},MOD(ROW()-2,5)+1)} -> North | D97: {=INDEX({"Electronics","Clothing","Furniture","Books","Office Supplies"},MOD(ROW()-2,5)+1)} -> Electronics | E97: =ROUND(500+MOD((ROW()-2)*137,44500),2) -> 13515 | F97: =MOD((ROW()-2)*7,11)+1 -> 6 | G97: =CHOOSE(MOD(ROW()-2,8)+1,0,0.02,0.05,0.08,0.1,0.12,0.15,0.2) -> 0.2 | H97: =DATE(2025,1,1)+MOD(ROW()-2,365) -> 45753 | I97: =ROUND(E97*F97*(1-G97),2) -> 64872 | J97: =ROUND(I97*(0.08+MOD(ROW()-2,12)*0.02),2) -> 19461.6 | K97: {=INDEX({"Amit","Neha","Riya","Karan","Pooja","Rahul","Meera","Vikram"},MOD(ROW()-2,8)+1)} -> Vikram | L97: {=INDEX({"UPI","Credit Card","Debit Card","Cash","Net Banking"},MOD(ROW()-2,5)+1)} -> UPI | M97: {=INDEX({"Retail","Corporate","Education","Small Business"},MOD(ROW()-2,4)+1)} -> Small Business
A98: ="CUST"&TEXT(ROW()-1,"0000") -> CUST0097 | B98: {=INDEX({"Aarav","Vivaan","Aditya","Arjun","Kabir","Rohan","Ananya","Diya","Ishita","Meera","Riya","Pooja","Neha","Kavya","Aisha","Priya","Rahul","Karan","Vikram","Sahil"},MOD(ROW()-2,20)+1)&" "&INDEX({"Shah","Patel","Mehta","Desai","Joshi","Gupta","Verma","Sharma","Trivedi","Rana","Mishra","Kapoor","Iyer","Nair","Singh"},MOD(INT((ROW()-2)/20),15)+1)} -> Rahul Joshi | C98: {=INDEX({"North","South","East","West","Central"},MOD(ROW()-2,5)+1)} -> South | D98: {=INDEX({"Electronics","Clothing","Furniture","Books","Office Supplies"},MOD(ROW()-2,5)+1)} -> Clothing | E98: =ROUND(500+MOD((ROW()-2)*137,44500),2) -> 13652 | F98: =MOD((ROW()-2)*7,11)+1 -> 2 | G98: =CHOOSE(MOD(ROW()-2,8)+1,0,0.02,0.05,0.08,0.1,0.12,0.15,0.2) -> 0 | H98: =DATE(2025,1,1)+MOD(ROW()-2,365) -> 45754 | I98: =ROUND(E98*F98*(1-G98),2) -> 27304 | J98: =ROUND(I98*(0.08+MOD(ROW()-2,12)*0.02),2) -> 2184.32 | K98: {=INDEX({"Amit","Neha","Riya","Karan","Pooja","Rahul","Meera","Vikram"},MOD(ROW()-2,8)+1)} -> Amit | L98: {=INDEX({"UPI","Credit Card","Debit Card","Cash","Net Banking"},MOD(ROW()-2,5)+1)} -> Credit Card | M98: {=INDEX({"Retail","Corporate","Education","Small Business"},MOD(ROW()-2,4)+1)} -> Retail
A99: ="CUST"&TEXT(ROW()-1,"0000") -> CUST0098 | B99: {=INDEX({"Aarav","Vivaan","Aditya","Arjun","Kabir","Rohan","Ananya","Diya","Ishita","Meera","Riya","Pooja","Neha","Kavya","Aisha","Priya","Rahul","Karan","Vikram","Sahil"},MOD(ROW()-2,20)+1)&" "&INDEX({"Shah","Patel","Mehta","Desai","Joshi","Gupta","Verma","Sharma","Trivedi","Rana","Mishra","Kapoor","Iyer","Nair","Singh"},MOD(INT((ROW()-2)/20),15)+1)} -> Karan Joshi | C99: {=INDEX({"North","South","East","West","Central"},MOD(ROW()-2,5)+1)} -> East | D99: {=INDEX({"Electronics","Clothing","Furniture","Books","Office Supplies"},MOD(ROW()-2,5)+1)} -> Furniture | E99: =ROUND(500+MOD((ROW()-2)*137,44500),2) -> 13789 | F99: =MOD((ROW()-2)*7,11)+1 -> 9 | G99: =CHOOSE(MOD(ROW()-2,8)+1,0,0.02,0.05,0.08,0.1,0.12,0.15,0.2) -> 0.02 | H99: =DATE(2025,1,1)+MOD(ROW()-2,365) -> 45755 | I99: =ROUND(E99*F99*(1-G99),2) -> 121618.98 | J99: =ROUND(I99*(0.08+MOD(ROW()-2,12)*0.02),2) -> 12161.9 | K99: {=INDEX({"Amit","Neha","Riya","Karan","Pooja","Rahul","Meera","Vikram"},MOD(ROW()-2,8)+1)} -> Neha | L99: {=INDEX({"UPI","Credit Card","Debit Card","Cash","Net Banking"},MOD(ROW()-2,5)+1)} -> Debit Card | M99: {=INDEX({"Retail","Corporate","Education","Small Business"},MOD(ROW()-2,4)+1)} -> Corporate
A100: ="CUST"&TEXT(ROW()-1,"0000") -> CUST0099 | B100: {=INDEX({"Aarav","Vivaan","Aditya","Arjun","Kabir","Rohan","Ananya","Diya","Ishita","Meera","Riya","Pooja","Neha","Kavya","Aisha","Priya","Rahul","Karan","Vikram","Sahil"},MOD(ROW()-2,20)+1)&" "&INDEX({"Shah","Patel","Mehta","Desai","Joshi","Gupta","Verma","Sharma","Trivedi","Rana","Mishra","Kapoor","Iyer","Nair","Singh"},MOD(INT((ROW()-2)/20),15)+1)} -> Vikram Joshi | C100: {=INDEX({"North","South","East","West","Central"},MOD(ROW()-2,5)+1)} -> West | D100: {=INDEX({"Electronics","Clothing","Furniture","Books","Office Supplies"},MOD(ROW()-2,5)+1)} -> Books | E100: =ROUND(500+MOD((ROW()-2)*137,44500),2) -> 13926 | F100: =MOD((ROW()-2)*7,11)+1 -> 5 | G100: =CHOOSE(MOD(ROW()-2,8)+1,0,0.02,0.05,0.08,0.1,0.12,0.15,0.2) -> 0.05 | H100: =DATE(2025,1,1)+MOD(ROW()-2,365) -> 45756 | I100: =ROUND(E100*F100*(1-G100),2) -> 66148.5 | J100: =ROUND(I100*(0.08+MOD(ROW()-2,12)*0.02),2) -> 7937.82 | K100: {=INDEX({"Amit","Neha","Riya","Karan","Pooja","Rahul","Meera","Vikram"},MOD(ROW()-2,8)+1)} -> Riya | L100: {=INDEX({"UPI","Credit Card","Debit Card","Cash","Net Banking"},MOD(ROW()-2,5)+1)} -> Cash | M100: {=INDEX({"Retail","Corporate","Education","Small Business"},MOD(ROW()-2,4)+1)} -> Education
A101: ="CUST"&TEXT(ROW()-1,"0000") -> CUST0100 | B101: {=INDEX({"Aarav","Vivaan","Aditya","Arjun","Kabir","Rohan","Ananya","Diya","Ishita","Meera","Riya","Pooja","Neha","Kavya","Aisha","Priya","Rahul","Karan","Vikram","Sahil"},MOD(ROW()-2,20)+1)&" "&INDEX({"Shah","Patel","Mehta","Desai","Joshi","Gupta","Verma","Sharma","Trivedi","Rana","Mishra","Kapoor","Iyer","Nair","Singh"},MOD(INT((ROW()-2)/20),15)+1)} -> Sahil Joshi | C101: {=INDEX({"North","South","East","West","Central"},MOD(ROW()-2,5)+1)} -> Central | D101: {=INDEX({"Electronics","Clothing","Furniture","Books","Office Supplies"},MOD(ROW()-2,5)+1)} -> Office Supplies | E101: =ROUND(500+MOD((ROW()-2)*137,44500),2) -> 14063 | F101: =MOD((ROW()-2)*7,11)+1 -> 1 | G101: =CHOOSE(MOD(ROW()-2,8)+1,0,0.02,0.05,0.08,0.1,0.12,0.15,0.2) -> 0.08 | H101: =DATE(2025,1,1)+MOD(ROW()-2,365) -> 45757 | I101: =ROUND(E101*F101*(1-G101),2) -> 12937.96 | J101: =ROUND(I101*(0.08+MOD(ROW()-2,12)*0.02),2) -> 1811.31 | K101: {=INDEX({"Amit","Neha","Riya","Karan","Pooja","Rahul","Meera","Vikram"},MOD(ROW()-2,8)+1)} -> Karan | L101: {=INDEX({"UPI","Credit Card","Debit Card","Cash","Net Banking"},MOD(ROW()-2,5)+1)} -> Net Banking | M101: {=INDEX({"Retail","Corporate","Education","Small Business"},MOD(ROW()-2,4)+1)} -> Small Business
A102: ="CUST"&TEXT(ROW()-1,"0000") -> CUST0101 | B102: {=INDEX({"Aarav","Vivaan","Aditya","Arjun","Kabir","Rohan","Ananya","Diya","Ishita","Meera","Riya","Pooja","Neha","Kavya","Aisha","Priya","Rahul","Karan","Vikram","Sahil"},MOD(ROW()-2,20)+1)&" "&INDEX({"Shah","Patel","Mehta","Desai","Joshi","Gupta","Verma","Sharma","Trivedi","Rana","Mishra","Kapoor","Iyer","Nair","Singh"},MOD(INT((ROW()-2)/20),15)+1)} -> Aarav Gupta | C102: {=INDEX({"North","South","East","West","Central"},MOD(ROW()-2,5)+1)} -> North | D102: {=INDEX({"Electronics","Clothing","Furniture","Books","Office Supplies"},MOD(ROW()-2,5)+1)} -> Electronics | E102: =ROUND(500+MOD((ROW()-2)*137,44500),2) -> 14200 | F102: =MOD((ROW()-2)*7,11)+1 -> 8 | G102: =CHOOSE(MOD(ROW()-2,8)+1,0,0.02,0.05,0.08,0.1,0.12,0.15,0.2) -> 0.1 | H102: =DATE(2025,1,1)+MOD(ROW()-2,365) -> 45758 | I102: =ROUND(E102*F102*(1-G102),2) -> 102240 | J102: =ROUND(I102*(0.08+MOD(ROW()-2,12)*0.02),2) -> 16358.4 | K102: {=INDEX({"Amit","Neha","Riya","Karan","Pooja","Rahul","Meera","Vikram"},MOD(ROW()-2,8)+1)} -> Pooja | L102: {=INDEX({"UPI","Credit Card","Debit Card","Cash","Net Banking"},MOD(ROW()-2,5)+1)} -> UPI | M102: {=INDEX({"Retail","Corporate","Education","Small Business"},MOD(ROW()-2,4)+1)} -> Retail
A103: ="CUST"&TEXT(ROW()-1,"0000") -> CUST0102 | B103: {=INDEX({"Aarav","Vivaan","Aditya","Arjun","Kabir","Rohan","Ananya","Diya","Ishita","Meera","Riya","Pooja","Neha","Kavya","Aisha","Priya","Rahul","Karan","Vikram","Sahil"},MOD(ROW()-2,20)+1)&" "&INDEX({"Shah","Patel","Mehta","Desai","Joshi","Gupta","Verma","Sharma","Trivedi","Rana","Mishra","Kapoor","Iyer","Nair","Singh"},MOD(INT((ROW()-2)/20),15)+1)} -> Vivaan Gupta | C103: {=INDEX({"North","South","East","West","Central"},MOD(ROW()-2,5)+1)} -> South | D103: {=INDEX({"Electronics","Clothing","Furniture","Books","Office Supplies"},MOD(ROW()-2,5)+1)} -> Clothing | E103: =ROUND(500+MOD((ROW()-2)*137,44500),2) -> 14337 | F103: =MOD((ROW()-2)*7,11)+1 -> 4 | G103: =CHOOSE(MOD(ROW()-2,8)+1,0,0.02,0.05,0.08,0.1,0.12,0.15,0.2) -> 0.12 | H103: =DATE(2025,1,1)+MOD(ROW()-2,365) -> 45759 | I103: =ROUND(E103*F103*(1-G103),2) -> 50466.24 | J103: =ROUND(I103*(0.08+MOD(ROW()-2,12)*0.02),2) -> 9083.92 | K103: {=INDEX({"Amit","Neha","Riya","Karan","Pooja","Rahul","Meera","Vikram"},MOD(ROW()-2,8)+1)} -> Rahul | L103: {=INDEX({"UPI","Credit Card","Debit Card","Cash","Net Banking"},MOD(ROW()-2,5)+1)} -> Credit Card | M103: {=INDEX({"Retail","Corporate","Education","Small Business"},MOD(ROW()-2,4)+1)} -> Corporate
... A128: ="CUST"&TEXT(ROW()-1,"0000") -> CUST0127 | B128: {=INDEX({"Aarav","Vivaan","Aditya","Arjun","Kabir","Rohan","Ananya","Diya","Ishita","Meera","Riya","Pooja","Neha","Kavya","Aisha","Priya","Rahul","Karan","Vikram","Sahil"},MOD(ROW()-2,20)+1)&" "&INDEX({"Shah","Patel","Mehta","Desai","Joshi","Gupta","Verma","Sharma","Trivedi","Rana","Mishra","Kapoor","Iyer","Nair","Singh"},MOD(INT((ROW()-2)/20),15)+1)} -> Ananya Verma | C128: {=INDEX({"North","South","East","West","Central"},MOD(ROW()-2,5)+1)} -> South | D128: {=INDEX({"Electronics","Clothing","Furniture","Books","Office Supplies"},MOD(ROW()-2,5)+1)} -> Clothing | E128: =ROUND(500+MOD((ROW()-2)*137,44500),2) -> 17762 | F128: =MOD((ROW()-2)*7,11)+1 -> 3 | G128: =CHOOSE(MOD(ROW()-2,8)+1,0,0.02,0.05,0.08,0.1,0.12,0.15,0.2) -> 0.15 | H128: =DATE(2025,1,1)+MOD(ROW()-2,365) -> 45784 | I128: =ROUND(E128*F128*(1-G128),2) -> 45293.1 | J128: =ROUND(I128*(0.08+MOD(ROW()-2,12)*0.02),2) -> 9058.62 | K128: {=INDEX({"Amit","Neha","Riya","Karan","Pooja","Rahul","Meera","Vikram"},MOD(ROW()-2,8)+1)} -> Meera | L128: {=INDEX({"UPI","Credit Card","Debit Card","Cash","Net Banking"},MOD(ROW()-2,5)+1)} -> Credit Card | M128: {=INDEX({"Retail","Corporate","Education","Small Business"},MOD(ROW()-2,4)+1)} -> Education
A129: ="CUST"&TEXT(ROW()-1,"0000") -> CUST0128 | B129: {=INDEX({"Aarav","Vivaan","Aditya","Arjun","Kabir","Rohan","Ananya","Diya","Ishita","Meera","Riya","Pooja","Neha","Kavya","Aisha","Priya","Rahul","Karan","Vikram","Sahil"},MOD(ROW()-2,20)+1)&" "&INDEX({"Shah","Patel","Mehta","Desai","Joshi","Gupta","Verma","Sharma","Trivedi","Rana","Mishra","Kapoor","Iyer","Nair","Singh"},MOD(INT((ROW()-2)/20),15)+1)} -> Diya Verma | C129: {=INDEX({"North","South","East","West","Central"},MOD(ROW()-2,5)+1)} -> East | D129: {=INDEX({"Electronics","Clothing","Furniture","Books","Office Supplies"},MOD(ROW()-2,5)+1)} -> Furniture | E129: 23379 | F129: =MOD((ROW()-2)*7,11)+1 -> 10 | G129: =CHOOSE(MOD(ROW()-2,8)+1,0,0.02,0.05,0.08,0.1,0.12,0.15,0.2) -> 0.2 | H129: =DATE(2025,1,1)+MOD(ROW()-2,365) -> 45785 | I129: =ROUND(E129*F129*(1-G129),2) -> 187032 | J129: =ROUND(I129*(0.08+MOD(ROW()-2,12)*0.02),2) -> 41147.04 | K129: {=INDEX({"Amit","Neha","Riya","Karan","Pooja","Rahul","Meera","Vikram"},MOD(ROW()-2,8)+1)} -> Vikram | L129: {=INDEX({"UPI","Credit Card","Debit Card","Cash","Net Banking"},MOD(ROW()-2,5)+1)} -> Debit Card | M129: {=INDEX({"Retail","Corporate","Education","Small Business"},MOD(ROW()-2,4)+1)} -> Small Business
A130: ="CUST"&TEXT(ROW()-1,"0000") -> CUST0129 | B130: {=INDEX({"Aarav","Vivaan","Aditya","Arjun","Kabir","Rohan","Ananya","Diya","Ishita","Meera","Riya","Pooja","Neha","Kavya","Aisha","Priya","Rahul","Karan","Vikram","Sahil"},MOD(ROW()-2,20)+1)&" "&INDEX({"Shah","Patel","Mehta","Desai","Joshi","Gupta","Verma","Sharma","Trivedi","Rana","Mishra","Kapoor","Iyer","Nair","Singh"},MOD(INT((ROW()-2)/20),15)+1)} -> Ishita Verma | C130: {=INDEX({"North","South","East","West","Central"},MOD(ROW()-2,5)+1)} -> West | D130: {=INDEX({"Electronics","Clothing","Furniture","Books","Office Supplies"},MOD(ROW()-2,5)+1)} -> Books | E130: =ROUND(500+MOD((ROW()-2)*137,44500),2) -> 18036 | F130: =MOD((ROW()-2)*7,11)+1 -> 6 | G130: =CHOOSE(MOD(ROW()-2,8)+1,0,0.02,0.05,0.08,0.1,0.12,0.15,0.2) -> 0 | H130: =DATE(2025,1,1)+MOD(ROW()-2,365) -> 45786 | I130: =ROUND(E130*F130*(1-G130),2) -> 108216 | J130: =ROUND(I130*(0.08+MOD(ROW()-2,12)*0.02),2) -> 25971.84 | K130: {=INDEX({"Amit","Neha","Riya","Karan","Pooja","Rahul","Meera","Vikram"},MOD(ROW()-2,8)+1)} -> Amit | L130: {=INDEX({"UPI","Credit Card","Debit Card","Cash","Net Banking"},MOD(ROW()-2,5)+1)} -> Cash | M130: {=INDEX({"Retail","Corporate","Education","Small Business"},MOD(ROW()-2,4)+1)} -> Retail
A131: ="CUST"&TEXT(ROW()-1,"0000") -> CUST0130 | B131: {=INDEX({"Aarav","Vivaan","Aditya","Arjun","Kabir","Rohan","Ananya","Diya","Ishita","Meera","Riya","Pooja","Neha","Kavya","Aisha","Priya","Rahul","Karan","Vikram","Sahil"},MOD(ROW()-2,20)+1)&" "&INDEX({"Shah","Patel","Mehta","Desai","Joshi","Gupta","Verma","Sharma","Trivedi","Rana","Mishra","Kapoor","Iyer","Nair","Singh"},MOD(INT((ROW()-2)/20),15)+1)} -> Meera Verma | C131: {=INDEX({"North","South","East","West","Central"},MOD(ROW()-2,5)+1)} -> Central | D131: {=INDEX({"Electronics","Clothing","Furniture","Books","Office Supplies"},MOD(ROW()-2,5)+1)} -> Office Supplies | E131: =ROUND(500+MOD((ROW()-2)*137,44500),2) -> 18173 | F131: =MOD((ROW()-2)*7,11)+1 -> 2 | G131: =CHOOSE(MOD(ROW()-2,8)+1,0,0.02,0.05,0.08,0.1,0.12,0.15,0.2) -> 0.02 | H131: =DATE(2025,1,1)+MOD(ROW()-2,365) -> 45787 | I131: =ROUND(E131*F131*(1-G131),2) -> 35619.08 | J131: =ROUND(I131*(0.08+MOD(ROW()-2,12)*0.02),2) -> 9260.96 | K131: {=INDEX({"Amit","Neha","Riya","Karan","Pooja","Rahul","Meera","Vikram"},MOD(ROW()-2,8)+1)} -> Neha | L131: {=INDEX({"UPI","Credit Card","Debit Card","Cash","Net Banking"},MOD(ROW()-2,5)+1)} -> Net Banking | M131: {=INDEX({"Retail","Corporate","Education","Small Business"},MOD(ROW()-2,4)+1)} -> Corporate
A132: ="CUST"&TEXT(ROW()-1,"0000") -> CUST0131 | B132: {=INDEX({"Aarav","Vivaan","Aditya","Arjun","Kabir","Rohan","Ananya","Diya","Ishita","Meera","Riya","Pooja","Neha","Kavya","Aisha","Priya","Rahul","Karan","Vikram","Sahil"},MOD(ROW()-2,20)+1)&" "&INDEX({"Shah","Patel","Mehta","Desai","Joshi","Gupta","Verma","Sharma","Trivedi","Rana","Mishra","Kapoor","Iyer","Nair","Singh"},MOD(INT((ROW()-2)/20),15)+1)} -> Riya Verma | C132: {=INDEX({"North","South","East","West","Central"},MOD(ROW()-2,5)+1)} -> North | D132: {=INDEX({"Electronics","Clothing","Furniture","Books","Office Supplies"},MOD(ROW()-2,5)+1)} -> Electronics | E132: =ROUND(500+MOD((ROW()-2)*137,44500),2) -> 18310 | F132: =MOD((ROW()-2)*7,11)+1 -> 9 | G132: =CHOOSE(MOD(ROW()-2,8)+1,0,0.02,0.05,0.08,0.1,0.12,0.15,0.2) -> 0.05 | H132: =DATE(2025,1,1)+MOD(ROW()-2,365) -> 45788 | I132: =ROUND(E132*F132*(1-G132),2) -> 156550.5 | J132: =ROUND(I132*(0.08+MOD(ROW()-2,12)*0.02),2) -> 43834.14 | K132: {=INDEX({"Amit","Neha","Riya","Karan","Pooja","Rahul","Meera","Vikram"},MOD(ROW()-2,8)+1)} -> Riya | L132: {=INDEX({"UPI","Credit Card","Debit Card","Cash","Net Banking"},MOD(ROW()-2,5)+1)} -> UPI | M132: {=INDEX({"Retail","Corporate","Education","Small Business"},MOD(ROW()-2,4)+1)} -> Education
A133: ="CUST"&TEXT(ROW()-1,"0000") -> CUST0132 | B133: {=INDEX({"Aarav","Vivaan","Aditya","Arjun","Kabir","Rohan","Ananya","Diya","Ishita","Meera","Riya","Pooja","Neha","Kavya","Aisha","Priya","Rahul","Karan","Vikram","Sahil"},MOD(ROW()-2,20)+1)&" "&INDEX({"Shah","Patel","Mehta","Desai","Joshi","Gupta","Verma","Sharma","Trivedi","Rana","Mishra","Kapoor","Iyer","Nair","Singh"},MOD(INT((ROW()-2)/20),15)+1)} -> Pooja Verma | C133: {=INDEX({"North","South","East","West","Central"},MOD(ROW()-2,5)+1)} -> South | D133: {=INDEX({"Electronics","Clothing","Furniture","Books","Office Supplies"},MOD(ROW()-2,5)+1)} -> Clothing | E133: =ROUND(500+MOD((ROW()-2)*137,44500),2) -> 18447 | F133: =MOD((ROW()-2)*7,11)+1 -> 5 | G133: =CHOOSE(MOD(ROW()-2,8)+1,0,0.02,0.05,0.08,0.1,0.12,0.15,0.2) -> 0.08 | H133: =DATE(2025,1,1)+MOD(ROW()-2,365) -> 45789 | I133: =ROUND(E133*F133*(1-G133),2) -> 84856.2 | J133: =ROUND(I133*(0.08+MOD(ROW()-2,12)*0.02),2) -> 25456.86 | K133: {=INDEX({"Amit","Neha","Riya","Karan","Pooja","Rahul","Meera","Vikram"},MOD(ROW()-2,8)+1)} -> Karan | L133: {=INDEX({"UPI","Credit Card","Debit Card","Cash","Net Banking"},MOD(ROW()-2,5)+1)} -> Credit Card | M133: {=INDEX({"Retail","Corporate","Education","Small Business"},MOD(ROW()-2,4)+1)} -> Small Business
A134: ="CUST"&TEXT(ROW()-1,"0000") -> CUST0133 | B134: {=INDEX({"Aarav","Vivaan","Aditya","Arjun","Kabir","Rohan","Ananya","Diya","Ishita","Meera","Riya","Pooja","Neha","Kavya","Aisha","Priya","Rahul","Karan","Vikram","Sahil"},MOD(ROW()-2,20)+1)&" "&INDEX({"Shah","Patel","Mehta","Desai","Joshi","Gupta","Verma","Sharma","Trivedi","Rana","Mishra","Kapoor","Iyer","Nair","Singh"},MOD(INT((ROW()-2)/20),15)+1)} -> Neha Verma | C134: {=INDEX({"North","South","East","West","Central"},MOD(ROW()-2,5)+1)} -> East | D134: {=INDEX({"Electronics","Clothing","Furniture","Books","Office Supplies"},MOD(ROW()-2,5)+1)} -> Furniture | E134: =ROUND(500+MOD((ROW()-2)*137,44500),2) -> 18584 | F134: =MOD((ROW()-2)*7,11)+1 -> 1 | G134: =CHOOSE(MOD(ROW()-2,8)+1,0,0.02,0.05,0.08,0.1,0.12,0.15,0.2) -> 0.1 | H134: =DATE(2025,1,1)+MOD(ROW()-2,365) -> 45790 | I134: =ROUND(E134*F134*(1-G134),2) -> 16725.6 | J134: =ROUND(I134*(0.08+MOD(ROW()-2,12)*0.02),2) -> 1338.05 | K134: {=INDEX({"Amit","Neha","Riya","Karan","Pooja","Rahul","Meera","Vikram"},MOD(ROW()-2,8)+1)} -> Pooja | L134: {=INDEX({"UPI","Credit Card","Debit Card","Cash","Net Banking"},MOD(ROW()-2,5)+1)} -> Debit Card | M134: {=INDEX({"Retail","Corporate","Education","Small Business"},MOD(ROW()-2,4)+1)} -> Retail
A135: ="CUST"&TEXT(ROW()-1,"0000") -> CUST0134 | B135: {=INDEX({"Aarav","Vivaan","Aditya","Arjun","Kabir","Rohan","Ananya","Diya","Ishita","Meera","Riya","Pooja","Neha","Kavya","Aisha","Priya","Rahul","Karan","Vikram","Sahil"},MOD(ROW()-2,20)+1)&" "&INDEX({"Shah","Patel","Mehta","Desai","Joshi","Gupta","Verma","Sharma","Trivedi","Rana","Mishra","Kapoor","Iyer","Nair","Singh"},MOD(INT((ROW()-2)/20),15)+1)} -> Kavya Verma | C135: {=INDEX({"North","South","East","West","Central"},MOD(ROW()-2,5)+1)} -> West | D135: {=INDEX({"Electronics","Clothing","Furniture","Books","Office Supplies"},MOD(ROW()-2,5)+1)} -> Books | E135: =ROUND(500+MOD((ROW()-2)*137,44500),2) -> 18721 | F135: =MOD((ROW()-2)*7,11)+1 -> 8 | G135: =CHOOSE(MOD(ROW()-2,8)+1,0,0.02,0.05,0.08,0.1,0.12,0.15,0.2) -> 0.12 | H135: =DATE(2025,1,1)+MOD(ROW()-2,365) -> 45791 | I135: =ROUND(E135*F135*(1-G135),2) -> 131795.84 | J135: =ROUND(I135*(0.08+MOD(ROW()-2,12)*0.02),2) -> 13179.58 | K135: {=INDEX({"Amit","Neha","Riya","Karan","Pooja","Rahul","Meera","Vikram"},MOD(ROW()-2,8)+1)} -> Rahul | L135: {=INDEX({"UPI","Credit Card","Debit Card","Cash","Net Banking"},MOD(ROW()-2,5)+1)} -> Cash | M135: {=INDEX({"Retail","Corporate","Education","Small Business"},MOD(ROW()-2,4)+1)} -> Corporate
A136: ="CUST"&TEXT(ROW()-1,"0000") -> CUST0135 | B136: {=INDEX({"Aarav","Vivaan","Aditya","Arjun","Kabir","Rohan","Ananya","Diya","Ishita","Meera","Riya","Pooja","Neha","Kavya","Aisha","Priya","Rahul","Karan","Vikram","Sahil"},MOD(ROW()-2,20)+1)&" "&INDEX({"Shah","Patel","Mehta","Desai","Joshi","Gupta","Verma","Sharma","Trivedi","Rana","Mishra","Kapoor","Iyer","Nair","Singh"},MOD(INT((ROW()-2)/20),15)+1)} -> Aisha Verma | C136: {=INDEX({"North","South","East","West","Central"},MOD(ROW()-2,5)+1)} -> Central | D136: {=INDEX({"Electronics","Clothing","Furniture","Books","Office Supplies"},MOD(ROW()-2,5)+1)} -> Office Supplies | E136: =ROUND(500+MOD((ROW()-2)*137,44500),2) -> 18858 | F136: =MOD((ROW()-2)*7,11)+1 -> 4 | G136: =CHOOSE(MOD(ROW()-2,8)+1,0,0.02,0.05,0.08,0.1,0.12,0.15,0.2) -> 0.15 | H136: =DATE(2025,1,1)+MOD(ROW()-2,365) -> 45792 | I136: =ROUND(E136*F136*(1-G136),2) -> 64117.2 | J136: =ROUND(I136*(0.08+MOD(ROW()-2,12)*0.02),2) -> 7694.06 | K136: {=INDEX({"Amit","Neha","Riya","Karan","Pooja","Rahul","Meera","Vikram"},MOD(ROW()-2,8)+1)} -> Meera | L136: {=INDEX({"UPI","Credit Card","Debit Card","Cash","Net Banking"},MOD(ROW()-2,5)+1)} -> Net Banking | M136: {=INDEX({"Retail","Corporate","Education","Small Business"},MOD(ROW()-2,4)+1)} -> Education
A137: ="CUST"&TEXT(ROW()-1,"0000") -> CUST0136 | B137: {=INDEX({"Aarav","Vivaan","Aditya","Arjun","Kabir","Rohan","Ananya","Diya","Ishita","Meera","Riya","Pooja","Neha","Kavya","Aisha","Priya","Rahul","Karan","Vikram","Sahil"},MOD(ROW()-2,20)+1)&" "&INDEX({"Shah","Patel","Mehta","Desai","Joshi","Gupta","Verma","Sharma","Trivedi","Rana","Mishra","Kapoor","Iyer","Nair","Singh"},MOD(INT((ROW()-2)/20),15)+1)} -> Priya Verma | C137: {=INDEX({"North","South","East","West","Central"},MOD(ROW()-2,5)+1)} -> North | D137: {=INDEX({"Electronics","Clothing","Furniture","Books","Office Supplies"},MOD(ROW()-2,5)+1)} -> Electronics | E137: =ROUND(500+MOD((ROW()-2)*137,44500),2) -> 18995 | F137: =MOD((ROW()-2)*7,11)+1 -> 11 | G137: =CHOOSE(MOD(ROW()-2,8)+1,0,0.02,0.05,0.08,0.1,0.12,0.15,0.2) -> 0.2 | H137: 45823 | I137: =ROUND(E137*F137*(1-G137),2) -> 167156 | J137: =ROUND(I137*(0.08+MOD(ROW()-2,12)*0.02),2) -> 23401.84 | K137: {=INDEX({"Amit","Neha","Riya","Karan","Pooja","Rahul","Meera","Vikram"},MOD(ROW()-2,8)+1)} -> Vikram | L137: {=INDEX({"UPI","Credit Card","Debit Card","Cash","Net Banking"},MOD(ROW()-2,5)+1)} -> UPI | M137: {=INDEX({"Retail","Corporate","Education","Small Business"},MOD(ROW()-2,4)+1)} -> Small Business
A138: ="CUST"&TEXT(ROW()-1,"0000") -> CUST0137 | B138: {=INDEX({"Aarav","Vivaan","Aditya","Arjun","Kabir","Rohan","Ananya","Diya","Ishita","Meera","Riya","Pooja","Neha","Kavya","Aisha","Priya","Rahul","Karan","Vikram","Sahil"},MOD(ROW()-2,20)+1)&" "&INDEX({"Shah","Patel","Mehta","Desai","Joshi","Gupta","Verma","Sharma","Trivedi","Rana","Mishra","Kapoor","Iyer","Nair","Singh"},MOD(INT((ROW()-2)/20),15)+1)} -> Rahul Verma | C138: {=INDEX({"North","South","East","West","Central"},MOD(ROW()-2,5)+1)} -> South | D138: {=INDEX({"Electronics","Clothing","Furniture","Books","Office Supplies"},MOD(ROW()-2,5)+1)} -> Clothing | E138: =ROUND(500+MOD((ROW()-2)*137,44500),2) -> 19132 | F138: =MOD((ROW()-2)*7,11)+1 -> 7 | G138: =CHOOSE(MOD(ROW()-2,8)+1,0,0.02,0.05,0.08,0.1,0.12,0.15,0.2) -> 0 | H138: =DATE(2025,1,1)+MOD(ROW()-2,365) -> 45794 | I138: =ROUND(E138*F138*(1-G138),2) -> 133924 | J138: =ROUND(I138*(0.08+MOD(ROW()-2,12)*0.02),2) -> 21427.84 | K138: {=INDEX({"Amit","Neha","Riya","Karan","Pooja","Rahul","Meera","Vikram"},MOD(ROW()-2,8)+1)} -> Amit | L138: {=INDEX({"UPI","Credit Card","Debit Card","Cash","Net Banking"},MOD(ROW()-2,5)+1)} -> Credit Card | M138: {=INDEX({"Retail","Corporate","Education","Small Business"},MOD(ROW()-2,4)+1)} -> Retail
...

Sheet Dashboard
A1: Sales Dahsboard
D3: Total Sales | I3: Total Profit | N3: Total Quantity | T3: Total Orders
D4: =SUM(DataSet!I2:I229) -> 19453783 | I4: =SUM(DataSet!J2:J229) -> 3655425.9 | N4: =SUM(DataSet!F2:F229) -> 1365 | T4: =COUNTA(DataSet!A2:A229) -> 228

Sheet Main Task
A1: Task 4.1: Use VLOOKUP to retrieve the Region Manager for each customer based on their Region. | K1: Task 5.1: Create a column chart showing Total Sales by Region.
S2: Task 7: Documentation
A3: Customer_ID | B3: Region | C3: Region_Manager | E3: Region | F3: Region_Manager | G3: Region_Target | M3: Region | N3: Total Sales
A4: =DataSet!A2 -> CUST0001 | B4: =DataSet!C2 -> North | C4: =IFERROR(VLOOKUP(B4,$E$4:$F$8,2,FALSE),"Not Found") -> Amit Shah | E4: North | F4: Amit Shah | G4: 500000 | M4: North | N4: =SUMIF(DataSet!$C$2:$C$328,M4,DataSet!$I$2:$I$230) -> 3866226.5 | S4: Workbook Sheets
A5: =DataSet!A3 -> CUST0002 | B5: =DataSet!C3 -> South | C5: =IFERROR(VLOOKUP(B5,$E$4:$F$8,2,FALSE),"Not Found") -> Neha Patel | E5: South | F5: Neha Patel | G5: 450000 | M5: South | N5: =SUMIF(DataSet!$C$2:$C$328,M5,DataSet!$I$2:$I$230) -> 3919562.1 | S5: Dataset – Contains the cleaned sales dataset
A6: =DataSet!A4 -> CUST0003 | B6: =DataSet!C4 -> East | C6: =IFERROR(VLOOKUP(B6,$E$4:$F$8,2,FALSE),"Not Found") -> Riya Mehta | E6: East | F6: Riya Mehta | G6: 400000 | M6: East | N6: =SUMIF(DataSet!$C$2:$C$328,M6,DataSet!$I$2:$I$230) -> 3891741.7 | S6: Pivot Tables – Contains Pivot Tables, Slicer and Timeline
A7: =DataSet!A5 -> CUST0004 | B7: =DataSet!C5 -> West | C7: =IFERROR(VLOOKUP(B7,$E$4:$F$8,2,FALSE),"Not Found") -> Karan Desai | E7: West | F7: Karan Desai | G7: 550000 | M7: West | N7: =SUMIF(DataSet!$C$2:$C$328,M7,DataSet!$I$2:$I$230) -> 4097279.9 | S7: Main Task – Contains formulas, calculations and charts
A8: =DataSet!A6 -> CUST0005 | B8: =DataSet!C6 -> Central | C8: =IFERROR(VLOOKUP(B8,$E$4:$F$8,2,FALSE),"Not Found") -> Pooja Joshi | E8: Central | F8: Pooja Joshi | G8: 480000 | M8: Central | N8: =SUMIF(DataSet!$C$2:$C$328,M8,DataSet!$I$2:$I$230) -> 3678973.1 | S8: Dashboard – Contains KPIs and visual charts
A9: =DataSet!A7 -> CUST0006 | B9: =DataSet!C7 -> North | C9: =IFERROR(VLOOKUP(B9,$E$4:$F$8,2,FALSE),"Not Found") -> Amit Shah | S9: Key Excel Functions Used
A10: =DataSet!A8 -> CUST0007 | B10: =DataSet!C8 -> South | C10: =IFERROR(VLOOKUP(B10,$E$4:$F$8,2,FALSE),"Not Found") -> Neha Patel | S10: SUM, SUMIF, COUNTA, IF, Nested IF, VLOOKUP, INDEX-MATCH
A11: =DataSet!A9 -> CUST0008 | B11: =DataSet!C9 -> East | C11: =IFERROR(VLOOKUP(B11,$E$4:$F$8,2,FALSE),"Not Found") -> Riya Mehta | S11: Dashboard Components
A12: =DataSet!A10 -> CUST0009 | B12: =DataSet!C10 -> West | C12: =IFERROR(VLOOKUP(B12,$E$4:$F$8,2,FALSE),"Not Found") -> Karan Desai | S12: KPI Cards, Column Charts, Bar Chart, Slicer and Timeline
A13: =DataSet!A11 -> CUST0010 | B13: =DataSet!C11 -> Central | C13: =IFERROR(VLOOKUP(B13,$E$4:$F$8,2,FALSE),"Not Found") -> Pooja Joshi | S13: Instructions
A14: =DataSet!A12 -> CUST0011 | B14: =DataSet!C12 -> North | C14: =IFERROR(VLOOKUP(B14,$E$4:$F$8,2,FALSE),"Not Found") -> Amit Shah | S14: Use the Slicer and Timeline on the Pivot Tables sheet to filter Pivot Table data.
A15: =DataSet!A13 -> CUST0012 | B15: =DataSet!C13 -> South | C15: =IFERROR(VLOOKUP(B15,$E$4:$F$8,2,FALSE),"Not Found") -> Neha Patel | S15: The Dataset contains 228 sales records and has been cleaned and formatted for analysis.
A16: =DataSet!A14 -> CUST0013 | B16: =DataSet!C14 -> East | C16: =IFERROR(VLOOKUP(B16,$E$4:$F$8,2,FALSE),"Not Found") -> Riya Mehta | S16: Naming Convention
A17: =DataSet!A15 -> CUST0014 | B17: =DataSet!C15 -> West | C17: =IFERROR(VLOOKUP(B17,$E$4:$F$8,2,FALSE),"Not Found") -> Karan Desai | S17: Sheets and charts are given clear and descriptive names for easy identification.
A18: =DataSet!A16 -> CUST0015 | B18: =DataSet!C16 -> Central | C18: =IFERROR(VLOOKUP(B18,$E$4:$F$8,2,FALSE),"Not Found") -> Pooja Joshi
A19: =DataSet!A17 -> CUST0016 | B19: =DataSet!C17 -> North | C19: =IFERROR(VLOOKUP(B19,$E$4:$F$8,2,FALSE),"Not Found") -> Amit Shah
A20: =DataSet!A18 -> CUST0017 | B20: =DataSet!C18 -> South | C20: =IFERROR(VLOOKUP(B20,$E$4:$F$8,2,FALSE),"Not Found") -> Neha Patel
A21: =DataSet!A19 -> CUST0018 | B21: =DataSet!C19 -> East | C21: =IFERROR(VLOOKUP(B21,$E$4:$F$8,2,FALSE),"Not Found") -> Riya Mehta
A22: =DataSet!A20 -> CUST0019 | B22: =DataSet!C20 -> West | C22: =IFERROR(VLOOKUP(B22,$E$4:$F$8,2,FALSE),"Not Found") -> Karan Desai
A23: =DataSet!A21 -> CUST0020 | B23: =DataSet!C21 -> Central | C23: =IFERROR(VLOOKUP(B23,$E$4:$F$8,2,FALSE),"Not Found") -> Pooja Joshi
A24: =DataSet!A22 -> CUST0021 | B24: =DataSet!C22 -> North | C24: =IFERROR(VLOOKUP(B24,$E$4:$F$8,2,FALSE),"Not Found") -> Amit Shah
A25: =DataSet!A23 -> CUST0022 | B25: =DataSet!C23 -> South | C25: =IFERROR(VLOOKUP(B25,$E$4:$F$8,2,FALSE),"Not Found") -> Neha Patel
A26: =DataSet!A24 -> CUST0023 | B26: =DataSet!C24 -> East | C26: =IFERROR(VLOOKUP(B26,$E$4:$F$8,2,FALSE),"Not Found") -> Riya Mehta
A27: =DataSet!A25 -> CUST0024 | B27: =DataSet!C25 -> West | C27: =IFERROR(VLOOKUP(B27,$E$4:$F$8,2,FALSE),"Not Found") -> Karan Desai | J27: Task 5.2: Apply conditional formatting to highlight High Value orders.
A28: =DataSet!A26 -> CUST0025 | B28: =DataSet!C26 -> Central | C28: =IFERROR(VLOOKUP(B28,$E$4:$F$8,2,FALSE),"Not Found") -> Pooja Joshi
A29: =DataSet!A27 -> CUST0026 | B29: =DataSet!C27 -> North | C29: =IFERROR(VLOOKUP(B29,$E$4:$F$8,2,FALSE),"Not Found") -> Amit Shah | J29: Customer_ID | K29: Sales | L29: Order_Type
A30: =DataSet!A28 -> CUST0027 | B30: =DataSet!C28 -> South | C30: =IFERROR(VLOOKUP(B30,$E$4:$F$8,2,FALSE),"Not Found") -> Neha Patel | J30: =DataSet!A2 -> CUST0001 | K30: =DataSet!I2 -> 500 | L30: =IF(K30>=25000,"High Value","Regular") -> Regular
A31: =DataSet!A29 -> CUST0028 | B31: =DataSet!C29 -> East | C31: =IFERROR(VLOOKUP(B31,$E$4:$F$8,2,FALSE),"Not Found") -> Riya Mehta | J31: =DataSet!A3 -> CUST0002 | K31: =DataSet!I3 -> 4994.08 | L31: =IF(K31>=25000,"High Value","Regular") -> Regular
A32: =DataSet!A30 -> CUST0029 | B32: =DataSet!C30 -> West | C32: =IFERROR(VLOOKUP(B32,$E$4:$F$8,2,FALSE),"Not Found") -> Karan Desai | J32: =DataSet!A4 -> CUST0003 | K32: =DataSet!I4 -> 2941.2 | L32: =IF(K32>=25000,"High Value","Regular") -> Regular
A33: =DataSet!A31 -> CUST0030 | B33: =DataSet!C31 -> Central | C33: =IFERROR(VLOOKUP(B33,$E$4:$F$8,2,FALSE),"Not Found") -> Pooja Joshi | J33: =DataSet!A5 -> CUST0004 | K33: =DataSet!I5 -> 9219.32 | L33: =IF(K33>=25000,"High Value","Regular") -> Regular
A34: =DataSet!A32 -> CUST0031 | B34: =DataSet!C32 -> North | C34: =IFERROR(VLOOKUP(B34,$E$4:$F$8,2,FALSE),"Not Found") -> Amit Shah | J34: =DataSet!A6 -> CUST0005 | K34: =DataSet!I6 -> 6602.4 | L34: =IF(K34>=25000,"High Value","Regular") -> Regular
A35: =DataSet!A33 -> CUST0032 | B35: =DataSet!C33 -> South | C35: =IFERROR(VLOOKUP(B35,$E$4:$F$8,2,FALSE),"Not Found") -> Neha Patel | J35: =DataSet!A7 -> CUST0006 | K35: =DataSet!I7 -> 3128.4 | L35: =IF(K35>=25000,"High Value","Regular") -> Regular
A36: =DataSet!A34 -> CUST0033 | B36: =DataSet!C34 -> East | C36: =IFERROR(VLOOKUP(B36,$E$4:$F$8,2,FALSE),"Not Found") -> Riya Mehta | J36: =DataSet!A8 -> CUST0007 | K36: =DataSet!I8 -> 11237 | L36: =IF(K36>=25000,"High Value","Regular") -> Regular
A37: =DataSet!A35 -> CUST0034 | B37: =DataSet!C35 -> West | C37: =IFERROR(VLOOKUP(B37,$E$4:$F$8,2,FALSE),"Not Found") -> Karan Desai | J37: =DataSet!A9 -> CUST0008 | K37: =DataSet!I9 -> 7003.2 | L37: =IF(K37>=25000,"High Value","Regular") -> Regular
A38: =DataSet!A36 -> CUST0035 | B38: =DataSet!C36 -> Central | C38: =IFERROR(VLOOKUP(B38,$E$4:$F$8,2,FALSE),"Not Found") -> Pooja Joshi | J38: =DataSet!A10 -> CUST0009 | K38: =DataSet!I10 -> 3192 | L38: =IF(K38>=25000,"High Value","Regular") -> Regular
A39: =DataSet!A37 -> CUST0036 | B39: =DataSet!C37 -> North | C39: =IFERROR(VLOOKUP(B39,$E$4:$F$8,2,FALSE),"Not Found") -> Amit Shah | J39: =DataSet!A11 -> CUST0010 | K39: =DataSet!I11 -> 15285.06 | L39: =IF(K39>=25000,"High Value","Regular") -> Regular
A40: =DataSet!A38 -> CUST0037 | B40: =DataSet!C38 -> South | C40: =IFERROR(VLOOKUP(B40,$E$4:$F$8,2,FALSE),"Not Found") -> Neha Patel | J40: =DataSet!A12 -> CUST0011 | K40: =DataSet!I12 -> 8882.5 | L40: =IF(K40>=25000,"High Value","Regular") -> Regular
A41: =DataSet!A39 -> CUST0038 | B41: =DataSet!C39 -> East | C41: =IFERROR(VLOOKUP(B41,$E$4:$F$8,2,FALSE),"Not Found") -> Riya Mehta | J41: =DataSet!A13 -> CUST0012 | K41: =DataSet!I13 -> 1846.44 | L41: =IF(K41>=25000,"High Value","Regular") -> Regular
... A229: =DataSet!A227 -> CUST0079 | B229: =DataSet!C227 -> West | C229: =IFERROR(VLOOKUP(B229,$E$4:$F$8,2,FALSE),"Not Found") -> Karan Desai | J229: =DataSet!A201 -> CUST0200 | K229: =DataSet!I201 -> 177683.2 | L229: =IF(K229>=25000,"High Value","Regular") -> High Value
J230: =DataSet!A202 -> CUST0201 | K230: =DataSet!I202 -> 111600 | L230: =IF(K230>=25000,"High Value","Regular") -> High Value
J231: =DataSet!A203 -> CUST0202 | K231: =DataSet!I203 -> 302238.86 | L231: =IF(K231>=25000,"High Value","Regular") -> High Value
A232: Task 4.2: Use INDEX-MATCH to retrieve the Region Target based on the Region. | J232: =DataSet!A204 -> CUST0203 | K232: =DataSet!I204 -> 187357.1 | L232: =IF(K232>=25000,"High Value","Regular") -> High Value
J233: =DataSet!A205 -> CUST0204 | K233: =DataSet!I205 -> 78138.36 | L233: =IF(K233>=25000,"High Value","Regular") -> High Value
A234: Customer_ID | B234: Region | C234: Region_Target | J234: =DataSet!A206 -> CUST0205 | K234: =DataSet!I206 -> 256032 | L234: =IF(K234>=25000,"High Value","Regular") -> High Value
A235: =DataSet!A2 -> CUST0001 | B235: =DataSet!C2 -> North | C235: =IFERROR(INDEX($G$4:$G$8,MATCH(B235,$E$4:$E$8,0)),"Not Found") -> 500000 | J235: =DataSet!A207 -> CUST0206 | K235: =DataSet!I207 -> 150928.8 | L235: =IF(K235>=25000,"High Value","Regular") -> High Value
A236: =DataSet!A3 -> CUST0002 | B236: =DataSet!C3 -> South | C236: =IFERROR(INDEX($G$4:$G$8,MATCH(B236,$E$4:$E$8,0)),"Not Found") -> 450000 | J236: =DataSet!A208 -> CUST0207 | K236: =DataSet!I208 -> 48827.4 | L236: =IF(K236>=25000,"High Value","Regular") -> High Value
A237: =DataSet!A4 -> CUST0003 | B237: =DataSet!C4 -> East | C237: =IFERROR(INDEX($G$4:$G$8,MATCH(B237,$E$4:$E$8,0)),"Not Found") -> 400000 | J237: =DataSet!A209 -> CUST0208 | K237: =DataSet!I209 -> 207784.8 | L237: =IF(K237>=25000,"High Value","Regular") -> High Value
A238: =DataSet!A5 -> CUST0004 | B238: =DataSet!C5 -> West | C238: =IFERROR(INDEX($G$4:$G$8,MATCH(B238,$E$4:$E$8,0)),"Not Found") -> 550000 | J238: =DataSet!A210 -> CUST0209 | K238: =DataSet!I210 -> 144980 | L238: =IF(K238>=25000,"High Value","Regular") -> High Value
A239: =DataSet!A6 -> CUST0005 | B239: =DataSet!C6 -> Central | C239: =IFERROR(INDEX($G$4:$G$8,MATCH(B239,$E$4:$E$8,0)),"Not Found") -> 480000 | J239: =DataSet!A211 -> CUST0210 | K239: =DataSet!I211 -> 28550.34 | L239: =IF(K239>=25000,"High Value","Regular") -> High Value
A240: =DataSet!A7 -> CUST0006 | B240: =DataSet!C7 -> North | C240: =IFERROR(INDEX($G$4:$G$8,MATCH(B240,$E$4:$E$8,0)),"Not Found") -> 500000 | J240: =DataSet!A212 -> CUST0211 | K240: =DataSet!I212 -> 222452 | L240: =IF(K240>=25000,"High Value","Regular") -> High Value
A241: =DataSet!A8 -> CUST0007 | B241: =DataSet!C8 -> South | C241: =IFERROR(INDEX($G$4:$G$8,MATCH(B241,$E$4:$E$8,0)),"Not Found") -> 450000 | J241: =DataSet!A213 -> CUST0212 | K241: =DataSet!I213 -> 108217.76 | L241: =IF(K241>=25000,"High Value","Regular") -> High Value
A242: =DataSet!A9 -> CUST0008 | B242: =DataSet!C9 -> East | C242: =IFERROR(INDEX($G$4:$G$8,MATCH(B242,$E$4:$E$8,0)),"Not Found") -> 400000 | J242: =DataSet!A214 -> CUST0213 | K242: =DataSet!I214 -> 292485.6 | L242: =IF(K242>=25000,"High Value","Regular") -> High Value
A243: =DataSet!A10 -> CUST0009 | B243: =DataSet!C10 -> West | C243: =IFERROR(INDEX($G$4:$G$8,MATCH(B243,$E$4:$E$8,0)),"Not Found") -> 550000 | J243: =DataSet!A215 -> CUST0214 | K243: =DataSet!I215 -> 182834.96 | L243: =IF(K243>=25000,"High Value","Regular") -> High Value
A244: =DataSet!A11 -> CUST0010 | B244: =DataSet!C11 -> Central | C244: =IFERROR(INDEX($G$4:$G$8,MATCH(B244,$E$4:$E$8,0)),"Not Found") -> 480000 | J244: =DataSet!A216 -> CUST0215 | K244: =DataSet!I216 -> 76035.9 | L244: =IF(K244>=25000,"High Value","Regular") -> High Value
A245: =DataSet!A12 -> CUST0011 | B245: =DataSet!C12 -> North | C245: =IFERROR(INDEX($G$4:$G$8,MATCH(B245,$E$4:$E$8,0)),"Not Found") -> 500000 | J245: =DataSet!A217 -> CUST0216 | K245: =DataSet!I217 -> 239640 | L245: =IF(K245>=25000,"High Value","Regular") -> High Value
A246: =DataSet!A13 -> CUST0012 | B246: =DataSet!C13 -> South | C246: =IFERROR(INDEX($G$4:$G$8,MATCH(B246,$E$4:$E$8,0)),"Not Found") -> 450000 | J246: =DataSet!A218 -> CUST0217 | K246: =DataSet!I218 -> 180552 | L246: =IF(K246>=25000,"High Value","Regular") -> High Value
... A257: =DataSet!A24 -> CUST0023 | B257: =DataSet!C24 -> East | C257: =IFERROR(INDEX($G$4:$G$8,MATCH(B257,$E$4:$E$8,0)),"Not Found") -> 400000 | J257: =DataSet!A229 -> CUST0159 | K257: =DataSet!I229 -> 131768.7 | L257: =IF(K257>=25000,"High Value","Regular") -> High Value
A258: =DataSet!A25 -> CUST0024 | B258: =DataSet!C25 -> West | C258: =IFERROR(INDEX($G$4:$G$8,MATCH(B258,$E$4:$E$8,0)),"Not Found") -> 550000
A259: =DataSet!A26 -> CUST0025 | B259: =DataSet!C26 -> Central | C259: =IFERROR(INDEX($G$4:$G$8,MATCH(B259,$E$4:$E$8,0)),"Not Found") -> 480000
A260: =DataSet!A27 -> CUST0026 | B260: =DataSet!C27 -> North | C260: =IFERROR(INDEX($G$4:$G$8,MATCH(B260,$E$4:$E$8,0)),"Not Found") -> 500000 | J260: Task 5.3: Create a chart comparing Total Sales and Total Profit by Product Category.
A261: =DataSet!A28 -> CUST0027 | B261: =DataSet!C28 -> South | C261: =IFERROR(INDEX($G$4:$G$8,MATCH(B261,$E$4:$E$8,0)),"Not Found") -> 450000
A262: =DataSet!A29 -> CUST0028 | B262: =DataSet!C29 -> East | C262: =IFERROR(INDEX($G$4:$G$8,MATCH(B262,$E$4:$E$8,0)),"Not Found") -> 400000 | J262: Product_Category | K262: Total Sales | L262: Total Profit
A263: =DataSet!A30 -> CUST0029 | B263: =DataSet!C30 -> West | C263: =IFERROR(INDEX($G$4:$G$8,MATCH(B263,$E$4:$E$8,0)),"Not Found") -> 550000 | J263: Electronics | K263: =SUMIF(DataSet!$D$2:$D$230,J263,DataSet!$I$2:$I$230) -> 3866226.5 | L263: =SUMIF(DataSet!$D$2:$D$230,J263,DataSet!$J$2:$J$230) -> 769795.44
A264: =DataSet!A31 -> CUST0030 | B264: =DataSet!C31 -> Central | C264: =IFERROR(INDEX($G$4:$G$8,MATCH(B264,$E$4:$E$8,0)),"Not Found") -> 480000 | J264: Clothing | K264: =SUMIF(DataSet!$D$2:$D$230,J264,DataSet!$I$2:$I$230) -> 3919562.1 | L264: =SUMIF(DataSet!$D$2:$D$230,J264,DataSet!$J$2:$J$230) -> 746508.07
A265: =DataSet!A32 -> CUST0031 | B265: =DataSet!C32 -> North | C265: =IFERROR(INDEX($G$4:$G$8,MATCH(B265,$E$4:$E$8,0)),"Not Found") -> 500000 | J265: Furniture | K265: =SUMIF(DataSet!$D$2:$D$230,J265,DataSet!$I$2:$I$230) -> 3891741.7 | L265: =SUMIF(DataSet!$D$2:$D$230,J265,DataSet!$J$2:$J$230) -> 729963.8
A266: =DataSet!A33 -> CUST0032 | B266: =DataSet!C33 -> South | C266: =IFERROR(INDEX($G$4:$G$8,MATCH(B266,$E$4:$E$8,0)),"Not Found") -> 450000 | J266: Books | K266: =SUMIF(DataSet!$D$2:$D$230,J266,DataSet!$I$2:$I$230) -> 4097279.9 | L266: =SUMIF(DataSet!$D$2:$D$230,J266,DataSet!$J$2:$J$230) -> 726304.07
A267: =DataSet!A34 -> CUST0033 | B267: =DataSet!C34 -> East | C267: =IFERROR(INDEX($G$4:$G$8,MATCH(B267,$E$4:$E$8,0)),"Not Found") -> 400000 | J267: Office Supplies | K267: =SUMIF(DataSet!$D$2:$D$230,J267,DataSet!$I$2:$I$230) -> 3678973.1 | L267: =SUMIF(DataSet!$D$2:$D$230,J267,DataSet!$J$2:$J$230) -> 682854.52
A268: =DataSet!A35 -> CUST0034 | B268: =DataSet!C35 -> West | C268: =IFERROR(INDEX($G$4:$G$8,MATCH(B268,$E$4:$E$8,0)),"Not Found") -> 550000
A269: =DataSet!A36 -> CUST0035 | B269: =DataSet!C36 -> Central | C269: =IFERROR(INDEX($G$4:$G$8,MATCH(B269,$E$4:$E$8,0)),"Not Found") -> 480000
A270: =DataSet!A37 -> CUST0036 | B270: =DataSet!C37 -> North | C270: =IFERROR(INDEX($G$4:$G$8,MATCH(B270,$E$4:$E$8,0)),"Not Found") -> 500000
A271: =DataSet!A38 -> CUST0037 | B271: =DataSet!C38 -> South | C271: =IFERROR(INDEX($G$4:$G$8,MATCH(B271,$E$4:$E$8,0)),"Not Found") -> 450000
A272: =DataSet!A39 -> CUST0038 | B272: =DataSet!C39 -> East | C272: =IFERROR(INDEX($G$4:$G$8,MATCH(B272,$E$4:$E$8,0)),"Not Found") -> 400000
A273: =DataSet!A40 -> CUST0039 | B273: =DataSet!C40 -> West | C273: =IFERROR(INDEX($G$4:$G$8,MATCH(B273,$E$4:$E$8,0)),"Not Found") -> 550000
A274: =DataSet!A41 -> CUST0040 | B274: =DataSet!C41 -> Central | C274: =IFERROR(INDEX($G$4:$G$8,MATCH(B274,$E$4:$E$8,0)),"Not Found") -> 480000
A275: =DataSet!A42 -> CUST0041 | B275: =DataSet!C42 -> North | C275: =IFERROR(INDEX($G$4:$G$8,MATCH(B275,$E$4:$E$8,0)),"Not Found") -> 500000
A276: =DataSet!A43 -> CUST0042 | B276: =DataSet!C43 -> South | C276: =IFERROR(INDEX($G$4:$G$8,MATCH(B276,$E$4:$E$8,0)),"Not Found") -> 450000
A277: =DataSet!A44 -> CUST0043 | B277: =DataSet!C44 -> East | C277: =IFERROR(INDEX($G$4:$G$8,MATCH(B277,$E$4:$E$8,0)),"Not Found") -> 400000
A278: =DataSet!A45 -> CUST0044 | B278: =DataSet!C45 -> West | C278: =IFERROR(INDEX($G$4:$G$8,MATCH(B278,$E$4:$E$8,0)),"Not Found") -> 550000
A279: =DataSet!A46 -> CUST0045 | B279: =DataSet!C46 -> Central | C279: =IFERROR(INDEX($G$4:$G$8,MATCH(B279,$E$4:$E$8,0)),"Not Found") -> 480000
... A285: =DataSet!A52 -> CUST0051 | B285: =DataSet!C52 -> North | C285: =IFERROR(INDEX($G$4:$G$8,MATCH(B285,$E$4:$E$8,0)),"Not Found") -> 500000
A286: =DataSet!A53 -> CUST0052 | B286: =DataSet!C53 -> South | C286: =IFERROR(INDEX($G$4:$G$8,MATCH(B286,$E$4:$E$8,0)),"Not Found") -> 450000 | J286: Task 5.4: Create a bar chart showing Total Quantity by Salesperson.
A287: =DataSet!A54 -> CUST0053 | B287: =DataSet!C54 -> East | C287: =IFERROR(INDEX($G$4:$G$8,MATCH(B287,$E$4:$E$8,0)),"Not Found") -> 400000
A288: =DataSet!A55 -> CUST0054 | B288: =DataSet!C55 -> West | C288: =IFERROR(INDEX($G$4:$G$8,MATCH(B288,$E$4:$E$8,0)),"Not Found") -> 550000 | K288: Salesperson | L288: Total Quantiy
A289: =DataSet!A56 -> CUST0055 | B289: =DataSet!C56 -> Central | C289: =IFERROR(INDEX($G$4:$G$8,MATCH(B289,$E$4:$E$8,0)),"Not Found") -> 480000 | K289: Amit | L289: =SUMIF(DataSet!$K$2:$K$230,K289,DataSet!$F$2:$F$230) -> 153
A290: =DataSet!A57 -> CUST0056 | B290: =DataSet!C57 -> North | C290: =IFERROR(INDEX($G$4:$G$8,MATCH(B290,$E$4:$E$8,0)),"Not Found") -> 500000 | K290: Neha | L290: 172
A291: =DataSet!A58 -> CUST0057 | B291: =DataSet!C58 -> South | C291: =IFERROR(INDEX($G$4:$G$8,MATCH(B291,$E$4:$E$8,0)),"Not Found") -> 450000 | K291: Riya | L291: =SUMIF(DataSet!$K$2:$K$230,K291,DataSet!$F$2:$F$230) -> 179
A292: =DataSet!A59 -> CUST0058 | B292: =DataSet!C59 -> East | C292: =IFERROR(INDEX($G$4:$G$8,MATCH(B292,$E$4:$E$8,0)),"Not Found") -> 400000 | K292: Karan | L292: =SUMIF(DataSet!$K$2:$K$230,K292,DataSet!$F$2:$F$230) -> 163
A293: =DataSet!A60 -> CUST0059 | B293: =DataSet!C60 -> West | C293: =IFERROR(INDEX($G$4:$G$8,MATCH(B293,$E$4:$E$8,0)),"Not Found") -> 550000 | K293: Pooja | L293: =SUMIF(DataSet!$K$2:$K$230,K293,DataSet!$F$2:$F$230) -> 179
A294: =DataSet!A61 -> CUST0060 | B294: =DataSet!C61 -> Central | C294: =IFERROR(INDEX($G$4:$G$8,MATCH(B294,$E$4:$E$8,0)),"Not Found") -> 480000 | K294: Rahul | L294: =SUMIF(DataSet!$K$2:$K$230,K294,DataSet!$F$2:$F$230) -> 165
A295: =DataSet!A62 -> CUST0061 | B295: =DataSet!C62 -> North | C295: =IFERROR(INDEX($G$4:$G$8,MATCH(B295,$E$4:$E$8,0)),"Not Found") -> 500000 | K295: Meera | L295: =SUMIF(DataSet!$K$2:$K$230,K295,DataSet!$F$2:$F$230) -> 180
A296: =DataSet!A63 -> CUST0062 | B296: =DataSet!C63 -> South | C296: =IFERROR(INDEX($G$4:$G$8,MATCH(B296,$E$4:$E$8,0)),"Not Found") -> 450000 | K296: Vikram | L296: =SUMIF(DataSet!$K$2:$K$230,K296,DataSet!$F$2:$F$230) -> 173
A297: =DataSet!A64 -> CUST0063 | B297: =DataSet!C64 -> East | C297: =IFERROR(INDEX($G$4:$G$8,MATCH(B297,$E$4:$E$8,0)),"Not Found") -> 400000
A298: =DataSet!A65 -> CUST0064 | B298: =DataSet!C65 -> West | C298: =IFERROR(INDEX($G$4:$G$8,MATCH(B298,$E$4:$E$8,0)),"Not Found") -> 550000
A299: =DataSet!A66 -> CUST0065 | B299: =DataSet!C66 -> Central | C299: =IFERROR(INDEX($G$4:$G$8,MATCH(B299,$E$4:$E$8,0)),"Not Found") -> 480000
A300: =DataSet!A67 -> CUST0066 | B300: =DataSet!C67 -> North | C300: =IFERROR(INDEX($G$4:$G$8,MATCH(B300,$E$4:$E$8,0)),"Not Found") -> 500000
A301: =DataSet!A68 -> CUST0067 | B301: =DataSet!C68 -> South | C301: =IFERROR(INDEX($G$4:$G$8,MATCH(B301,$E$4:$E$8,0)),"Not Found") -> 450000
A302: =DataSet!A69 -> CUST0068 | B302: =DataSet!C69 -> East | C302: =IFERROR(INDEX($G$4:$G$8,MATCH(B302,$E$4:$E$8,0)),"Not Found") -> 400000
...
